Workbook

Sheet Inicio
B2: GRIFF SALUD SA
B3: Tablero de Facturación e Impuestos
B4: Período: 2026
B6: Datos de la empresa
B7: Razón Social: | C7: GRIFF SALUD SA
B8: CUIT: | C8: 30-71713418-0
B9: Forma Jurídica: | C9: Sociedad Anónima
B10: Domicilio Fiscal: | C10: Loreto Virrey 1710, Piso 10 Dpto E - CABA
B11: Condición AFIP: | C11: Responsable Inscripto
B12: Inicio actividades: | C12: 10/2025
B13: Cierre ejercicio: | C13: Diciembre
B14: Actividad principal: | C14: 869090 - Servicios relacionados con la salud humana NCP
B15: Actividad secundaria: | C15: 702010 - Servicios de gerenciamiento de instituciones de salud
B16: Actividades IIBB: | C16: 702010 - Gerenciamiento / 651110 - Servicios de seguros
B17: Jurisdicciones IIBB: | C17: Convenio Multilateral - CABA (901) + Córdoba (904)
B18: Tasa Municipal: | C18: Comercio e Industria - Córdoba
B20: Estructura del libro
B21: Reglas | C21: Alícuotas, coeficientes y parámetros editables. ⚠️ Modificar acá los valores fiscales.
B22: Facturacion | C22: Registro maestro: una fila por factura emitida. Base de todos los cálculos.
B23: Checklist | C23: Control mensual de facturas a emitir por cliente fijo. Verde = emitida, Rojo = falta.
B24: Cobranzas | C24: Estado de cobro de cada factura. Por ahora manual.
B25: Impuestos | C25: Cálculo automático mensual: IVA, IIBB CABA, IIBB Córdoba, Tasa Comercio.
B26: Resumen | C26: Vista ejecutiva: totales del año, próximos vencimientos, alertas.
B28: Convenciones de color
B29: Texto azul | C29: Datos cargados manualmente (editables)
B30: Texto negro | C30: Fórmulas calculadas automáticamente (no editar)
B31: Texto verde | C31: Referencia a otra hoja del libro
B32: Fondo amarillo | C32: Parámetro clave - revisar y ajustar
B34: ℹ️ Importante
B35: Todos los cálculos de impuestos son APROXIMADOS. No reemplazan la liquidación profesional. El crédito fiscal de IVA es estimado por prorrateo (parametrizable en hoja Reglas). Las retenciones, percepciones y pagos a cuenta deben cargarse en hoja Impuestos al recibir los certificados. NOTAS DE CRÉDITO: cargar Tipo como 'NCA', 'NCB', 'NCC' o 'NCE'. Los montos se ingresan en POSITIVO; el sistema invierte el signo automáticamente y resta del IVA, IIBB y demás impuestos del período.

Sheet Reglas
B2: REGLAS Y PARÁMETROS FISCALES
B3: Modifique los valores en azul / fondo amarillo. Las fórmulas del resto del libro los toman automáticamente.
B5: 1. IVA
B6: Concepto | C6: Valor | F6: Notas
B7: Alícuota IVA general | C7: 0.21 | F7: 21% - alícuota general para servicios
B8: Alícuota IVA reducida | C8: 0.105 | F8: 10,5% - servicios de salud, intereses, etc.
B9: Crédito fiscal - método | C9: Prorrateo | F9: Prorrateo aproximado: IVA crédito = % débito mensual
B10: % Crédito fiscal estimado (sobre débito) | C10: 0.3 | F10: ⚠️ AJUSTAR según realidad: % de IVA crédito como proporción del débito
B12: 2. IIBB - Convenio Multilateral
B13: Jurisdicción | C13: Código | D13: Coef. Unificado | F13: Notas
B14: CABA | C14: 901 | D14: 0.0433 | F14: Coeficiente unificado Convenio Multilateral 2026
B15: Córdoba | C15: 904 | D15: 0.9567 | F15: Coeficiente unificado Convenio Multilateral 2026
B16: Suma coeficientes (debe ser 1,0000) | D16: =Reglas!$D$14+Reglas!$D$15
B18: 3. IIBB - Alícuotas por actividad y jurisdicción
B19: Código actividad | C19: Descripción | D19: Alícuota CABA | E19: Alícuota Córdoba | F19: Notas
B20: 702010 | C20: Servicios de gerenciamiento de instituciones de salud | D20: 0.03 | E20: 0.055 | F20: Honorarios, administración, gerenciamiento
B21: 651110 | C21: Servicios de seguros de salud | D21: 0.055 | E21: 0.03 | F21: Capitas, refuerzos de cápita, vacunación, enfermería
B23: 4. Tasa Comercio e Industria - Municipalidad de Córdoba
B24: Año | C24: Alícuota | F24: Notas
B25: 2025 | C25: 0.05 | F25: Alícuota vigente 2025
B26: 2026 | C26: 0.049 | F26: Alícuota vigente 2026
B27: Aplica solo a actividad en Córdoba (Cba en CM)
B29: 5. Mapeo de Concepto → Actividad IIBB
B30: Texto en el concepto (en mayúsculas o minúsculas) | C30: Actividad | D30: Notas
B31: CAPITA | C31: 651110 | D31: Capitas - servicio de seguro
B32: REFUERZO | C32: 651110 | D32: Refuerzo de cápita
B33: VACUNACION | C33: 651110 | D33: Convenio de vacunación
B34: ENFERMERIA | C34: 651110 | D34: Convenio de enfermería
B35: APORTES | C35: 651110 | D35: Aportes MMRC u otros
B36: HONORARIOS | C36: 702010 | D36: Honorarios prestacionales/administrativos
B37: ADMINISTRACION | C37: 702010 | D37: Honorarios de administración
B38: GERENCIAMIENTO | C38: 702010 | D38: Servicios de gerenciamiento
B39: ALQUILER | C39: 702010 | D39: Alquiler ecógrafo / equipos
B40: AUDITORIA | C40: 702010 | D40: Servicios de auditoría
B41: PRESTACIONAL | C41: 702010 | D41: Servicios prestacionales generales
B42: OTROS | C42: 702010 | D42: Cualquier otro concepto - default
B44: 6. Distribución de facturación por actividad (auto - lectura desde hoja Facturación)
B45: Cada factura se asigna a una actividad según el mapeo del punto 5. La distribución por jurisdicción se hace con los coeficientes del punto 2.
B47: 7. Vencimientos (informativo)
B48: Impuesto | C48: Día vencimiento | F48: Notas
B49: IVA | C49: 20 | F49: Mes siguiente al período fiscal (entre 18-22 según CUIT)
B50: IIBB CM | C50: 18 | F50: Mes siguiente al período (cronograma CM)
B51: Tasa Comercio Cba | C51: 15 | F51: Mes siguiente al período
B52: Ganancias - Anticipos | C52: 15 | F52: Bimestral según cronograma AFIP
B54: 8. Clientes fijos mensuales (para Checklist)
B55: Cliente | C55: Concepto | D55: Actividad IIBB | E55: % Honorarios | F55: Detalle
B56: OSPLYF | C56: Capita | D56: 651110 | F56: Capitas por precio unitario
B57: OSPLYF | C57: Honorarios Supervisa Salud | D57: 702010 | E57: 0.2 | F57: % sobre Fc Pascolo Silvina - auditoria
B58: OSSURRBAC | C58: Capita | D58: 651110 | F58: Capitas por precio unitario
B59: OSSURRBAC | C59: Alquiler Ecografo | D59: 702010 | E59: 0.15 | F59: Servicios prestacionales ecografo
B60: OSSURRBAC | C60: Honorarios Administracion | D60: 702010 | E60: 0.2 | F60: Servicios prestacionales
B61: AMSURRBAC | C61: Capita Vacunacion | D61: 651110 | F61: Convenio de vacunacion
B62: AMSURRBAC | C62: Capita Enfermeria | D62: 651110 | F62: Convenio de enfermeria
B63: OSPEVIC | C63: Capita | D63: 651110 | F63: Capitas por precio unitario
B64: OSPEVIC | C64: Refuerzo Capita 1-2 | D64: 651110 | F64: Precio fijo - 6 MM
B65: OSPEVIC | C65: Refuerzo Capita 2-2 | D65: 651110 | F65: Precio fijo - 6 MM
B66: MOSAISTAS | C66: Honorarios | D66: 702010 | E66: 0.08 | F66: 8% + $3.500.000 fijo
B67: UOM | C67: Honorarios | D67: 702010 | E67: 0.05 | F67: Monto fijo + aumento Convenio UOM
B68: OSPIF | C68: Capita | D68: 651110 | F68: Capitas por precio unitario
B69: OSPIF | C69: Honorarios | D69: 702010 | F69: Monto fijo $5.600.000
B70: OSPIF | C70: Honorarios x caso | D70: 702010 | F70: DIAZ Juan B / MIRANDA Joaquin - $8.977.000
B71: OSPIF | C71: Aportes MMRC | D71: 651110 | E71: 0.95 | F71: Padron aportes - comision 95%
B72: FUNDACION BIENESTAR SIRELYF | C72: Servicios Prestacionales | D72: 702010 | F72: A definir
B73: CFC | C73: Servicios Prestacionales | D73: 702010 | E73: 0.15 | F73: Porcentaje prestacional

Sheet Facturacion
A1: Fecha | B1: Tipo | C1: Pto Vta | D1: Número | E1: Cliente | F1: CUIT | G1: Concepto | H1: Actividad IIBB | I1: Neto Gravado | J1: No Grav. / Exento | K1: IVA 21% | L1: IVA 10,5% | M1: Percepciones | N1: Total | O1: Período | P1: Año | Q1: Mes | R1: Estado AFIP | S1: Estado Cobro | T1: Fecha Cobro | U1: Monto Cobrado | V1: Saldo Pendiente | W1: Observaciones | X1: Signo | Y1: Neto Efectivo | Z1: NoGrav Efectivo | AA1: IVA21 Efectivo | AB1: IVA105 Efectivo | AC1: Total Efectivo
A2: 46143 | B2: NCB | C2: 1 | D2: 55 | E2: OSSURRBAC | F2: 30714341746 | G2: Error Monto - Servicios prestacionales | H2: =IF(G2="","",IF(ISNUMBER(SEARCH("CAPITA",UPPER(G2))),651110,IF(ISNUMBER(SEARCH("REFUERZO",UPPER(G2))),651110,IF(ISNUMBER(SEARCH("VACUNACION",UPPER(G2))),651110,IF(ISNUMBER(SEARCH("ENFERMERIA",UPPER(G2))),651110,IF(ISNUMBER(SEARCH("APORTES",UPPER(G2))),651110,IF(ISNUMBER(SEARCH("HONORARIOS",UPPER(G2))),702010,IF(ISNUMBER(SEARCH("ADMINISTRACION",UPPER(G2))),702010,IF(ISNUMBER(SEARCH("GERENCIAMIENTO",UPPER(G2))),702010,IF(ISNUMBER(SEARCH("ALQUILER",UPPER(G2))),702010,IF(ISNUMBER(SEARCH("AUDITORIA",UPPER(G2))),702010,IF(ISNUMBER(SEARCH("PRESTACIONAL",UPPER(G2))),702010,702010)))))))))))) | I2: 0 | J2: 1320000 | K2: =IF(N(I2)>0,ROUND(N(I2)*IVA_general,2),0) | L2: 0 | M2: 0 | N2: =IF(SUM(I2:M2)=0,"",SUM(I2:M2)) | O2: =IF(A2="","",TEXT(A2,"yyyy-mm")) | P2: =IF(A2="","",YEAR(A2)) | Q2: =IF(A2="","",MONTH(A2)) | R2: Emitida | S2: Pendiente | U2: 0 | V2: =IF(B2="","",N2-U2) | W2: Auto: 30717134180_008_00001_00000055 (1).pdf | OBRA SOCIAL DEL SINDICATO UNICO DE RECOLECTORES DE RESIDUOS | X2: =IF(B2="","",IF(LEFT(B2,2)="NC",-1,1)) | Y2: =IF(B2="",0,N(I2)*X2) | Z2: =IF(B2="",0,N(J2)*X2) | AA2: =IF(B2="",0,N(K2)*X2) | AB2: =IF(B2="",0,N(L2)*X2) | AC2: =IF(B2="",0,N(N2)*X2)
A3: 46143 | B3: B | C3: 1 | D3: 612 | E3: AMSURRBAC | F3: 30710660995 | G3: Capita correspondiente al mes de | H3: =IF(G3="","",IF(ISNUMBER(SEARCH("CAPITA",UPPER(G3))),651110,IF(ISNUMBER(SEARCH("REFUERZO",UPPER(G3))),651110,IF(ISNUMBER(SEARCH("VACUNACION",UPPER(G3))),651110,IF(ISNUMBER(SEARCH("ENFERMERIA",UPPER(G3))),651110,IF(ISNUMBER(SEARCH("APORTES",UPPER(G3))),651110,IF(ISNUMBER(SEARCH("HONORARIOS",UPPER(G3))),702010,IF(ISNUMBER(SEARCH("ADMINISTRACION",UPPER(G3))),702010,IF(ISNUMBER(SEARCH("GERENCIAMIENTO",UPPER(G3))),702010,IF(ISNUMBER(SEARCH("ALQUILER",UPPER(G3))),702010,IF(ISNUMBER(SEARCH("AUDITORIA",UPPER(G3))),702010,IF(ISNUMBER(SEARCH("PRESTACIONAL",UPPER(G3))),702010,702010)))))))))))) | I3: 0 | J3: 2827915.2 | K3: =IF(N(I3)>0,ROUND(N(I3)*IVA_general,2),0) | L3: 0 | M3: 0 | N3: =IF(SUM(I3:M3)=0,"",SUM(I3:M3)) | O3: =IF(A3="","",TEXT(A3,"yyyy-mm")) | P3: =IF(A3="","",YEAR(A3)) | Q3: =IF(A3="","",MONTH(A3)) | R3: Emitida | S3: Pendiente | U3: 0 | V3: =IF(B3="","",N3-U3) | W3: Auto: 30717134180_006_00001_00000612 (1).pdf | MUTUAL ASOCIACION MUTUAL DEL SINDICATO UNICO DE RECOLECTORES | X3: =IF(B3="","",IF(LEFT(B3,2)="NC",-1,1)) | Y3: =IF(B3="",0,N(I3)*X3) | Z3: =IF(B3="",0,N(J3)*X3) | AA3: =IF(B3="",0,N(K3)*X3) | AB3: =IF(B3="",0,N(L3)*X3) | AC3: =IF(B3="",0,N(N3)*X3)
A4: 46143 | B4: B | C4: 1 | D4: 613 | E4: AMSURRBAC | F4: 30710660995 | G4: Capita correspondiente al mes de | H4: =IF(G4="","",IF(ISNUMBER(SEARCH("CAPITA",UPPER(G4))),651110,IF(ISNUMBER(SEARCH("REFUERZO",UPPER(G4))),651110,IF(ISNUMBER(SEARCH("VACUNACION",UPPER(G4))),651110,IF(ISNUMBER(SEARCH("ENFERMERIA",UPPER(G4))),651110,IF(ISNUMBER(SEARCH("APORTES",UPPER(G4))),651110,IF(ISNUMBER(SEARCH("HONORARIOS",UPPER(G4))),702010,IF(ISNUMBER(SEARCH("ADMINISTRACION",UPPER(G4))),702010,IF(ISNUMBER(SEARCH("GERENCIAMIENTO",UPPER(G4))),702010,IF(ISNUMBER(SEARCH("ALQUILER",UPPER(G4))),702010,IF(ISNUMBER(SEARCH("AUDITORIA",UPPER(G4))),702010,IF(ISNUMBER(SEARCH("PRESTACIONAL",UPPER(G4))),702010,702010)))))))))))) | I4: 0 | J4: 2965651.9 | K4: =IF(N(I4)>0,ROUND(N(I4)*IVA_general,2),0) | L4: 0 | M4: 0 | N4: =IF(SUM(I4:M4)=0,"",SUM(I4:M4)) | O4: =IF(A4="","",TEXT(A4,"yyyy-mm")) | P4: =IF(A4="","",YEAR(A4)) | Q4: =IF(A4="","",MONTH(A4)) | R4: Emitida | S4: Pendiente | U4: 0 | V4: =IF(B4="","",N4-U4) | W4: Auto: 30717134180_006_00001_00000613 (1).pdf | MUTUAL ASOCIACION MUTUAL DEL SINDICATO UNICO DE RECOLECTORES | X4: =IF(B4="","",IF(LEFT(B4,2)="NC",-1,1)) | Y4: =IF(B4="",0,N(I4)*X4) | Z4: =IF(B4="",0,N(J4)*X4) | AA4: =IF(B4="",0,N(K4)*X4) | AB4: =IF(B4="",0,N(L4)*X4) | AC4: =IF(B4="",0,N(N4)*X4)
A5: 46143 | B5: B | C5: 1 | D5: 614 | E5: OSPEVIC | F5: 30606579906 | G5: Capitas mensuales periodo Abril 2026 | H5: =IF(G5="","",IF(ISNUMBER(SEARCH("CAPITA",UPPER(G5))),651110,IF(ISNUMBER(SEARCH("REFUERZO",UPPER(G5))),651110,IF(ISNUMBER(SEARCH("VACUNACION",UPPER(G5))),651110,IF(ISNUMBER(SEARCH("ENFERMERIA",UPPER(G5))),651110,IF(ISNUMBER(SEARCH("APORTES",UPPER(G5))),651110,IF(ISNUMBER(SEARCH("HONORARIOS",UPPER(G5))),702010,IF(ISNUMBER(SEARCH("ADMINISTRACION",UPPER(G5))),702010,IF(ISNUMBER(SEARCH("GERENCIAMIENTO",UPPER(G5))),702010,IF(ISNUMBER(SEARCH("ALQUILER",UPPER(G5))),702010,IF(ISNUMBER(SEARCH("AUDITORIA",UPPER(G5))),702010,IF(ISNUMBER(SEARCH("PRESTACIONAL",UPPER(G5))),702010,702010)))))))))))) | I5: 0 | J5: 1.9867229e+08 | K5: =IF(N(I5)>0,ROUND(N(I5)*IVA_general,2),0) | L5: 0 | M5: 0 | N5: =IF(SUM(I5:M5)=0,"",SUM(I5:M5)) | O5: =IF(A5="","",TEXT(A5,"yyyy-mm")) | P5: =IF(A5="","",YEAR(A5)) | Q5: =IF(A5="","",MONTH(A5)) | R5: Emitida | S5: Cobrada | U5: 1.9867229e+08 | V5: =IF(B5="","",N5-U5) | W5: Auto: 30717134180_006_00001_00000614 (1).pdf | OBRA SOCIAL DEL PERSONAL DE VIGILANCIA Y SEGURIDAD COMERCIAL | X5: =IF(B5="","",IF(LEFT(B5,2)="NC",-1,1)) | Y5: =IF(B5="",0,N(I5)*X5) | Z5: =IF(B5="",0,N(J5)*X5) | AA5: =IF(B5="",0,N(K5)*X5) | AB5: =IF(B5="",0,N(L5)*X5) | AC5: =IF(B5="",0,N(N5)*X5)
A6: 46143 | B6: B | C6: 1 | D6: 615 | E6: OSSURRBAC | F6: 30714341746 | G6: Servicios prestacionales ecografo Abril | H6: =IF(G6="","",IF(ISNUMBER(SEARCH("CAPITA",UPPER(G6))),651110,IF(ISNUMBER(SEARCH("REFUERZO",UPPER(G6))),651110,IF(ISNUMBER(SEARCH("VACUNACION",UPPER(G6))),651110,IF(ISNUMBER(SEARCH("ENFERMERIA",UPPER(G6))),651110,IF(ISNUMBER(SEARCH("APORTES",UPPER(G6))),651110,IF(ISNUMBER(SEARCH("HONORARIOS",UPPER(G6))),702010,IF(ISNUMBER(SEARCH("ADMINISTRACION",UPPER(G6))),702010,IF(ISNUMBER(SEARCH("GERENCIAMIENTO",UPPER(G6))),702010,IF(ISNUMBER(SEARCH("ALQUILER",UPPER(G6))),702010,IF(ISNUMBER(SEARCH("AUDITORIA",UPPER(G6))),702010,IF(ISNUMBER(SEARCH("PRESTACIONAL",UPPER(G6))),702010,702010)))))))))))) | I6: 3713132.9 | J6: 0 | K6: =IF(N(I6)>0,ROUND(N(I6)*IVA_general,2),0) | L6: 0 | M6: 0 | N6: =IF(SUM(I6:M6)=0,"",SUM(I6:M6)) | O6: =IF(A6="","",TEXT(A6,"yyyy-mm")) | P6: =IF(A6="","",YEAR(A6)) | Q6: =IF(A6="","",MONTH(A6)) | R6: Emitida | S6: Pendiente | U6: 0 | V6: =IF(B6="","",N6-U6) | W6: Auto: 30717134180_006_00001_00000615 (1).pdf | OBRA SOCIAL DEL SINDICATO UNICO DE RECOLECTORES DE RESIDUOS | X6: =IF(B6="","",IF(LEFT(B6,2)="NC",-1,1)) | Y6: =IF(B6="",0,N(I6)*X6) | Z6: =IF(B6="",0,N(J6)*X6) | AA6: =IF(B6="",0,N(K6)*X6) | AB6: =IF(B6="",0,N(L6)*X6) | AC6: =IF(B6="",0,N(N6)*X6)
A7: 46143 | B7: B | C7: 1 | D7: 616 | E7: OSSURRBAC | F7: 30714341746 | G7: Capita correspondiente al mes de Abril | H7: =IF(G7="","",IF(ISNUMBER(SEARCH("CAPITA",UPPER(G7))),651110,IF(ISNUMBER(SEARCH("REFUERZO",UPPER(G7))),651110,IF(ISNUMBER(SEARCH("VACUNACION",UPPER(G7))),651110,IF(ISNUMBER(SEARCH("ENFERMERIA",UPPER(G7))),651110,IF(ISNUMBER(SEARCH("APORTES",UPPER(G7))),651110,IF(ISNUMBER(SEARCH("HONORARIOS",UPPER(G7))),702010,IF(ISNUMBER(SEARCH("ADMINISTRACION",UPPER(G7))),702010,IF(ISNUMBER(SEARCH("GERENCIAMIENTO",UPPER(G7))),702010,IF(ISNUMBER(SEARCH("ALQUILER",UPPER(G7))),702010,IF(ISNUMBER(SEARCH("AUDITORIA",UPPER(G7))),702010,IF(ISNUMBER(SEARCH("PRESTACIONAL",UPPER(G7))),702010,702010)))))))))))) | I7: 0 | J7: 7893768.1 | K7: =IF(N(I7)>0,ROUND(N(I7)*IVA_general,2),0) | L7: 0 | M7: 0 | N7: =IF(SUM(I7:M7)=0,"",SUM(I7:M7)) | O7: =IF(A7="","",TEXT(A7,"yyyy-mm")) | P7: =IF(A7="","",YEAR(A7)) | Q7: =IF(A7="","",MONTH(A7)) | R7: Emitida | S7: Pendiente | U7: 0 | V7: =IF(B7="","",N7-U7) | W7: Auto: 30717134180_006_00001_00000616 (1).pdf | OBRA SOCIAL DEL SINDICATO UNICO DE RECOLECTORES DE RESIDUOS | X7: =IF(B7="","",IF(LEFT(B7,2)="NC",-1,1)) | Y7: =IF(B7="",0,N(I7)*X7) | Z7: =IF(B7="",0,N(J7)*X7) | AA7: =IF(B7="",0,N(K7)*X7) | AB7: =IF(B7="",0,N(L7)*X7) | AC7: =IF(B7="",0,N(N7)*X7)
A8: 46143 | B8: B | C8: 1 | D8: 617 | E8: OSPLYF | F8: 30565846538 | G8: Capita correspondiente al mes de Abril | H8: =IF(G8="","",IF(ISNUMBER(SEARCH("CAPITA",UPPER(G8))),651110,IF(ISNUMBER(SEARCH("REFUERZO",UPPER(G8))),651110,IF(ISNUMBER(SEARCH("VACUNACION",UPPER(G8))),651110,IF(ISNUMBER(SEARCH("ENFERMERIA",UPPER(G8))),651110,IF(ISNUMBER(SEARCH("APORTES",UPPER(G8))),651110,IF(ISNUMBER(SEARCH("HONORARIOS",UPPER(G8))),702010,IF(ISNUMBER(SEARCH("ADMINISTRACION",UPPER(G8))),702010,IF(ISNUMBER(SEARCH("GERENCIAMIENTO",UPPER(G8))),702010,IF(ISNUMBER(SEARCH("ALQUILER",UPPER(G8))),702010,IF(ISNUMBER(SEARCH("AUDITORIA",UPPER(G8))),702010,IF(ISNUMBER(SEARCH("PRESTACIONAL",UPPER(G8))),702010,702010)))))))))))) | I8: 0 | J8: 18001763 | K8: =IF(N(I8)>0,ROUND(N(I8)*IVA_general,2),0) | L8: 0 | M8: 0 | N8: =IF(SUM(I8:M8)=0,"",SUM(I8:M8)) | O8: =IF(A8="","",TEXT(A8,"yyyy-mm")) | P8: =IF(A8="","",YEAR(A8)) | Q8: =IF(A8="","",MONTH(A8)) | R8: Emitida | S8: Pendiente | U8: 0 | V8: =IF(B8="","",N8-U8) | W8: Auto: 30717134180_006_00001_00000617 (1).pdf | OBRA SOCIAL DEL PERSONAL DE LUZ Y FUERZA DE CORDOBA | X8: =IF(B8="","",IF(LEFT(B8,2)="NC",-1,1)) | Y8: =IF(B8="",0,N(I8)*X8) | Z8: =IF(B8="",0,N(J8)*X8) | AA8: =IF(B8="",0,N(K8)*X8) | AB8: =IF(B8="",0,N(L8)*X8) | AC8: =IF(B8="",0,N(N8)*X8)
A9: 46143 | B9: B | C9: 1 | D9: 618 | E9: OSPLYF | F9: 30565846538 | G9: Capita correspondiente al mes de Abril | H9: =IF(G9="","",IF(ISNUMBER(SEARCH("CAPITA",UPPER(G9))),651110,IF(ISNUMBER(SEARCH("REFUERZO",UPPER(G9))),651110,IF(ISNUMBER(SEARCH("VACUNACION",UPPER(G9))),651110,IF(ISNUMBER(SEARCH("ENFERMERIA",UPPER(G9))),651110,IF(ISNUMBER(SEARCH("APORTES",UPPER(G9))),651110,IF(ISNUMBER(SEARCH("HONORARIOS",UPPER(G9))),702010,IF(ISNUMBER(SEARCH("ADMINISTRACION",UPPER(G9))),702010,IF(ISNUMBER(SEARCH("GERENCIAMIENTO",UPPER(G9))),702010,IF(ISNUMBER(SEARCH("ALQUILER",UPPER(G9))),702010,IF(ISNUMBER(SEARCH("AUDITORIA",UPPER(G9))),702010,IF(ISNUMBER(SEARCH("PRESTACIONAL",UPPER(G9))),702010,702010)))))))))))) | I9: 0 | J9: 468049.54 | K9: =IF(N(I9)>0,ROUND(N(I9)*IVA_general,2),0) | L9: 0 | M9: 0 | N9: =IF(SUM(I9:M9)=0,"",SUM(I9:M9)) | O9: =IF(A9="","",TEXT(A9,"yyyy-mm")) | P9: =IF(A9="","",YEAR(A9)) | Q9: =IF(A9="","",MONTH(A9)) | R9: Emitida | S9: Pendiente | U9: 0 | V9: =IF(B9="","",N9-U9) | W9: Auto: 30717134180_006_00001_00000618 (1).pdf | OBRA SOCIAL DEL PERSONAL DE LUZ Y FUERZA DE CORDOBA | X9: =IF(B9="","",IF(LEFT(B9,2)="NC",-1,1)) | Y9: =IF(B9="",0,N(I9)*X9) | Z9: =IF(B9="",0,N(J9)*X9) | AA9: =IF(B9="",0,N(K9)*X9) | AB9: =IF(B9="",0,N(L9)*X9) | AC9: =IF(B9="",0,N(N9)*X9)
A10: 46143 | B10: B | C10: 1 | D10: 619 | E10: UOM | F10: 30585207760 | G10: Servicios medico prestacionales | H10: =IF(G10="","",IF(ISNUMBER(SEARCH("CAPITA",UPPER(G10))),651110,IF(ISNUMBER(SEARCH("REFUERZO",UPPER(G10))),651110,IF(ISNUMBER(SEARCH("VACUNACION",UPPER(G10))),651110,IF(ISNUMBER(SEARCH("ENFERMERIA",UPPER(G10))),651110,IF(ISNUMBER(SEARCH("APORTES",UPPER(G10))),651110,IF(ISNUMBER(SEARCH("HONORARIOS",UPPER(G10))),702010,IF(ISNUMBER(SEARCH("ADMINISTRACION",UPPER(G10))),702010,IF(ISNUMBER(SEARCH("GERENCIAMIENTO",UPPER(G10))),702010,IF(ISNUMBER(SEARCH("ALQUILER",UPPER(G10))),702010,IF(ISNUMBER(SEARCH("AUDITORIA",UPPER(G10))),702010,IF(ISNUMBER(SEARCH("PRESTACIONAL",UPPER(G10))),702010,702010)))))))))))) | I10: 0 | J10: 7374506.6 | K10: =IF(N(I10)>0,ROUND(N(I10)*IVA_general,2),0) | L10: 0 | M10: 0 | N10: =IF(SUM(I10:M10)=0,"",SUM(I10:M10)) | O10: =IF(A10="","",TEXT(A10,"yyyy-mm")) | P10: =IF(A10="","",YEAR(A10)) | Q10: =IF(A10="","",MONTH(A10)) | R10: Emitida | S10: Pendiente | U10: 0 | V10: =IF(B10="","",N10-U10) | W10: Auto: 30717134180_006_00001_00000619 (1).pdf | OBRA SOCIAL DE LA UNION OBRERA METALURGICA DE LA REPUBLICA A | X10: =IF(B10="","",IF(LEFT(B10,2)="NC",-1,1)) | Y10: =IF(B10="",0,N(I10)*X10) | Z10: =IF(B10="",0,N(J10)*X10) | AA10: =IF(B10="",0,N(K10)*X10) | AB10: =IF(B10="",0,N(L10)*X10) | AC10: =IF(B10="",0,N(N10)*X10)
A11: 46143 | B11: B | C11: 1 | D11: 620 | E11: OSSURRBAC | F11: 30714341746 | G11: Servicios prestacionales | H11: =IF(G11="","",IF(ISNUMBER(SEARCH("CAPITA",UPPER(G11))),651110,IF(ISNUMBER(SEARCH("REFUERZO",UPPER(G11))),651110,IF(ISNUMBER(SEARCH("VACUNACION",UPPER(G11))),651110,IF(ISNUMBER(SEARCH("ENFERMERIA",UPPER(G11))),651110,IF(ISNUMBER(SEARCH("APORTES",UPPER(G11))),651110,IF(ISNUMBER(SEARCH("HONORARIOS",UPPER(G11))),702010,IF(ISNUMBER(SEARCH("ADMINISTRACION",UPPER(G11))),702010,IF(ISNUMBER(SEARCH("GERENCIAMIENTO",UPPER(G11))),702010,IF(ISNUMBER(SEARCH("ALQUILER",UPPER(G11))),702010,IF(ISNUMBER(SEARCH("AUDITORIA",UPPER(G11))),702010,IF(ISNUMBER(SEARCH("PRESTACIONAL",UPPER(G11))),702010,702010)))))))))))) | I11: 0 | J11: 1320000 | K11: =IF(N(I11)>0,ROUND(N(I11)*IVA_general,2),0) | L11: 0 | M11: 0 | N11: =IF(SUM(I11:M11)=0,"",SUM(I11:M11)) | O11: =IF(A11="","",TEXT(A11,"yyyy-mm")) | P11: =IF(A11="","",YEAR(A11)) | Q11: =IF(A11="","",MONTH(A11)) | R11: Emitida | S11: Pendiente | U11: 0 | V11: =IF(B11="","",N11-U11) | W11: Auto: 30717134180_006_00001_00000620 (2).pdf | OBRA SOCIAL DEL SINDICATO UNICO DE RECOLECTORES DE RESIDUOS | X11: =IF(B11="","",IF(LEFT(B11,2)="NC",-1,1)) | Y11: =IF(B11="",0,N(I11)*X11) | Z11: =IF(B11="",0,N(J11)*X11) | AA11: =IF(B11="",0,N(K11)*X11) | AB11: =IF(B11="",0,N(L11)*X11) | AC11: =IF(B11="",0,N(N11)*X11)
A12: 46143 | B12: B | C12: 1 | D12: 621 | E12: OSSURRBAC | F12: 30714341746 | G12: Servicios prestacionales | H12: =IF(G12="","",IF(ISNUMBER(SEARCH("CAPITA",UPPER(G12))),651110,IF(ISNUMBER(SEARCH("REFUERZO",UPPER(G12))),651110,IF(ISNUMBER(SEARCH("VACUNACION",UPPER(G12))),651110,IF(ISNUMBER(SEARCH("ENFERMERIA",UPPER(G12))),651110,IF(ISNUMBER(SEARCH("APORTES",UPPER(G12))),651110,IF(ISNUMBER(SEARCH("HONORARIOS",UPPER(G12))),702010,IF(ISNUMBER(SEARCH("ADMINISTRACION",UPPER(G12))),702010,IF(ISNUMBER(SEARCH("GERENCIAMIENTO",UPPER(G12))),702010,IF(ISNUMBER(SEARCH("ALQUILER",UPPER(G12))),702010,IF(ISNUMBER(SEARCH("AUDITORIA",UPPER(G12))),702010,IF(ISNUMBER(SEARCH("PRESTACIONAL",UPPER(G12))),702010,702010)))))))))))) | I12: 0 | J12: 3250000 | K12: =IF(N(I12)>0,ROUND(N(I12)*IVA_general,2),0) | L12: 0 | M12: 0 | N12: =IF(SUM(I12:M12)=0,"",SUM(I12:M12)) | O12: =IF(A12="","",TEXT(A12,"yyyy-mm")) | P12: =IF(A12="","",YEAR(A12)) | Q12: =IF(A12="","",MONTH(A12)) | R12: Emitida | S12: Pendiente | U12: 0 | V12: =IF(B12="","",N12-U12) | W12: Auto: 30717134180_006_00001_00000621 (1).pdf | OBRA SOCIAL DEL SINDICATO UNICO DE RECOLECTORES DE RESIDUOS | X12: =IF(B12="","",IF(LEFT(B12,2)="NC",-1,1)) | Y12: =IF(B12="",0,N(I12)*X12) | Z12: =IF(B12="",0,N(J12)*X12) | AA12: =IF(B12="",0,N(K12)*X12) | AB12: =IF(B12="",0,N(L12)*X12) | AC12: =IF(B12="",0,N(N12)*X12)
A13: 46147 | B13: NCB | C13: 1 | D13: 56 | E13: OSPLYF | F13: 30565846538 | G13: Extra Capita_ OSPLYFC Andrada | H13: =IF(G13="","",IF(ISNUMBER(SEARCH("CAPITA",UPPER(G13))),651110,IF(ISNUMBER(SEARCH("REFUERZO",UPPER(G13))),651110,IF(ISNUMBER(SEARCH("VACUNACION",UPPER(G13))),651110,IF(ISNUMBER(SEARCH("ENFERMERIA",UPPER(G13))),651110,IF(ISNUMBER(SEARCH("APORTES",UPPER(G13))),651110,IF(ISNUMBER(SEARCH("HONORARIOS",UPPER(G13))),702010,IF(ISNUMBER(SEARCH("ADMINISTRACION",UPPER(G13))),702010,IF(ISNUMBER(SEARCH("GERENCIAMIENTO",UPPER(G13))),702010,IF(ISNUMBER(SEARCH("ALQUILER",UPPER(G13))),702010,IF(ISNUMBER(SEARCH("AUDITORIA",UPPER(G13))),702010,IF(ISNUMBER(SEARCH("PRESTACIONAL",UPPER(G13))),702010,702010)))))))))))) | I13: 0 | J13: 4585560 | K13: =IF(N(I13)>0,ROUND(N(I13)*IVA_general,2),0) | L13: 0 | M13: 0 | N13: =IF(SUM(I13:M13)=0,"",SUM(I13:M13)) | O13: =IF(A13="","",TEXT(A13,"yyyy-mm")) | P13: =IF(A13="","",YEAR(A13)) | Q13: =IF(A13="","",MONTH(A13)) | R13: Emitida | S13: Pendiente | U13: 0 | V13: =IF(B13="","",N13-U13) | W13: Auto: 30717134180_008_00001_00000056 (1).pdf | OBRA SOCIAL DEL PERSONAL DE LUZ Y FUERZA DE CORDOBA | X13: =IF(B13="","",IF(LEFT(B13,2)="NC",-1,1)) | Y13: =IF(B13="",0,N(I13)*X13) | Z13: =IF(B13="",0,N(J13)*X13) | AA13: =IF(B13="",0,N(K13)*X13) | AB13: =IF(B13="",0,N(L13)*X13) | AC13: =IF(B13="",0,N(N13)*X13)
... A25: 46153 | B25: A | C25: 1 | D25: 82 | E25: OSPIF | F25: 30661691707 | G25: Servicios medico asistenciales correspondientes | H25: =IF(G25="","",IF(ISNUMBER(SEARCH("CAPITA",UPPER(G25))),651110,IF(ISNUMBER(SEARCH("REFUERZO",UPPER(G25))),651110,IF(ISNUMBER(SEARCH("VACUNACION",UPPER(G25))),651110,IF(ISNUMBER(SEARCH("ENFERMERIA",UPPER(G25))),651110,IF(ISNUMBER(SEARCH("APORTES",UPPER(G25))),651110,IF(ISNUMBER(SEARCH("HONORARIOS",UPPER(G25))),702010,IF(ISNUMBER(SEARCH("ADMINISTRACION",UPPER(G25))),702010,IF(ISNUMBER(SEARCH("GERENCIAMIENTO",UPPER(G25))),702010,IF(ISNUMBER(SEARCH("ALQUILER",UPPER(G25))),702010,IF(ISNUMBER(SEARCH("AUDITORIA",UPPER(G25))),702010,IF(ISNUMBER(SEARCH("PRESTACIONAL",UPPER(G25))),702010,702010)))))))))))) | I25: 0 | J25: 57518139 | K25: =IF(N(I25)>0,ROUND(N(I25)*IVA_general,2),0) | L25: 0 | M25: 0 | N25: =IF(SUM(I25:M25)=0,"",SUM(I25:M25)) | O25: =IF(A25="","",TEXT(A25,"yyyy-mm")) | P25: =IF(A25="","",YEAR(A25)) | Q25: =IF(A25="","",MONTH(A25)) | R25: Emitida | S25: Pendiente | U25: 0 | V25: =IF(B25="","",N25-U25) | W25: Auto: 30717134180_001_00001_00000082.pdf | OBRA SOCIAL PARA EL PERSONAL DE LA INDUSTRIA FIDEERA | X25: =IF(B25="","",IF(LEFT(B25,2)="NC",-1,1)) | Y25: =IF(B25="",0,N(I25)*X25) | Z25: =IF(B25="",0,N(J25)*X25) | AA25: =IF(B25="",0,N(K25)*X25) | AB25: =IF(B25="",0,N(L25)*X25) | AC25: =IF(B25="",0,N(N25)*X25)
H26: =IF(G26="","",IF(ISNUMBER(SEARCH("CAPITA",UPPER(G26))),651110,IF(ISNUMBER(SEARCH("REFUERZO",UPPER(G26))),651110,IF(ISNUMBER(SEARCH("VACUNACION",UPPER(G26))),651110,IF(ISNUMBER(SEARCH("ENFERMERIA",UPPER(G26))),651110,IF(ISNUMBER(SEARCH("APORTES",UPPER(G26))),651110,IF(ISNUMBER(SEARCH("HONORARIOS",UPPER(G26))),702010,IF(ISNUMBER(SEARCH("ADMINISTRACION",UPPER(G26))),702010,IF(ISNUMBER(SEARCH("GERENCIAMIENTO",UPPER(G26))),702010,IF(ISNUMBER(SEARCH("ALQUILER",UPPER(G26))),702010,IF(ISNUMBER(SEARCH("AUDITORIA",UPPER(G26))),702010,IF(ISNUMBER(SEARCH("PRESTACIONAL",UPPER(G26))),702010,702010)))))))))))) | K26: =IF(N(I26)>0,ROUND(N(I26)*IVA_general,2),0) | L26: 0 | N26: =IF(SUM(I26:M26)=0,"",SUM(I26:M26)) | O26: =IF(A26="","",TEXT(A26,"yyyy-mm")) | P26: =IF(A26="","",YEAR(A26)) | Q26: =IF(A26="","",MONTH(A26)) | U26: 0 | V26: =IF(B26="","",N26-U26) | X26: =IF(B26="","",IF(LEFT(B26,2)="NC",-1,1)) | Y26: =IF(B26="",0,N(I26)*X26) | Z26: =IF(B26="",0,N(J26)*X26) | AA26: =IF(B26="",0,N(K26)*X26) | AB26: =IF(B26="",0,N(L26)*X26) | AC26: =IF(B26="",0,N(N26)*X26)
H27: =IF(G27="","",IF(ISNUMBER(SEARCH("CAPITA",UPPER(G27))),651110,IF(ISNUMBER(SEARCH("REFUERZO",UPPER(G27))),651110,IF(ISNUMBER(SEARCH("VACUNACION",UPPER(G27))),651110,IF(ISNUMBER(SEARCH("ENFERMERIA",UPPER(G27))),651110,IF(ISNUMBER(SEARCH("APORTES",UPPER(G27))),651110,IF(ISNUMBER(SEARCH("HONORARIOS",UPPER(G27))),702010,IF(ISNUMBER(SEARCH("ADMINISTRACION",UPPER(G27))),702010,IF(ISNUMBER(SEARCH("GERENCIAMIENTO",UPPER(G27))),702010,IF(ISNUMBER(SEARCH("ALQUILER",UPPER(G27))),702010,IF(ISNUMBER(SEARCH("AUDITORIA",UPPER(G27))),702010,IF(ISNUMBER(SEARCH("PRESTACIONAL",UPPER(G27))),702010,702010)))))))))))) | K27: =IF(N(I27)>0,ROUND(N(I27)*IVA_general,2),0) | L27: 0 | N27: =IF(SUM(I27:M27)=0,"",SUM(I27:M27)) | O27: =IF(A27="","",TEXT(A27,"yyyy-mm")) | P27: =IF(A27="","",YEAR(A27)) | Q27: =IF(A27="","",MONTH(A27)) | U27: 0 | V27: =IF(B27="","",N27-U27) | X27: =IF(B27="","",IF(LEFT(B27,2)="NC",-1,1)) | Y27: =IF(B27="",0,N(I27)*X27) | Z27: =IF(B27="",0,N(J27)*X27) | AA27: =IF(B27="",0,N(K27)*X27) | AB27: =IF(B27="",0,N(L27)*X27) | AC27: =IF(B27="",0,N(N27)*X27)
H28: =IF(G28="","",IF(ISNUMBER(SEARCH("CAPITA",UPPER(G28))),651110,IF(ISNUMBER(SEARCH("REFUERZO",UPPER(G28))),651110,IF(ISNUMBER(SEARCH("VACUNACION",UPPER(G28))),651110,IF(ISNUMBER(SEARCH("ENFERMERIA",UPPER(G28))),651110,IF(ISNUMBER(SEARCH("APORTES",UPPER(G28))),651110,IF(ISNUMBER(SEARCH("HONORARIOS",UPPER(G28))),702010,IF(ISNUMBER(SEARCH("ADMINISTRACION",UPPER(G28))),702010,IF(ISNUMBER(SEARCH("GERENCIAMIENTO",UPPER(G28))),702010,IF(ISNUMBER(SEARCH("ALQUILER",UPPER(G28))),702010,IF(ISNUMBER(SEARCH("AUDITORIA",UPPER(G28))),702010,IF(ISNUMBER(SEARCH("PRESTACIONAL",UPPER(G28))),702010,702010)))))))))))) | K28: =IF(N(I28)>0,ROUND(N(I28)*IVA_general,2),0) | L28: 0 | N28: =IF(SUM(I28:M28)=0,"",SUM(I28:M28)) | O28: =IF(A28="","",TEXT(A28,"yyyy-mm")) | P28: =IF(A28="","",YEAR(A28)) | Q28: =IF(A28="","",MONTH(A28)) | U28: 0 | V28: =IF(B28="","",N28-U28) | X28: =IF(B28="","",IF(LEFT(B28,2)="NC",-1,1)) | Y28: =IF(B28="",0,N(I28)*X28) | Z28: =IF(B28="",0,N(J28)*X28) | AA28: =IF(B28="",0,N(K28)*X28) | AB28: =IF(B28="",0,N(L28)*X28) | AC28: =IF(B28="",0,N(N28)*X28)
H29: =IF(G29="","",IF(ISNUMBER(SEARCH("CAPITA",UPPER(G29))),651110,IF(ISNUMBER(SEARCH("REFUERZO",UPPER(G29))),651110,IF(ISNUMBER(SEARCH("VACUNACION",UPPER(G29))),651110,IF(ISNUMBER(SEARCH("ENFERMERIA",UPPER(G29))),651110,IF(ISNUMBER(SEARCH("APORTES",UPPER(G29))),651110,IF(ISNUMBER(SEARCH("HONORARIOS",UPPER(G29))),702010,IF(ISNUMBER(SEARCH("ADMINISTRACION",UPPER(G29))),702010,IF(ISNUMBER(SEARCH("GERENCIAMIENTO",UPPER(G29))),702010,IF(ISNUMBER(SEARCH("ALQUILER",UPPER(G29))),702010,IF(ISNUMBER(SEARCH("AUDITORIA",UPPER(G29))),702010,IF(ISNUMBER(SEARCH("PRESTACIONAL",UPPER(G29))),702010,702010)))))))))))) | K29: =IF(N(I29)>0,ROUND(N(I29)*IVA_general,2),0) | L29: 0 | N29: =IF(SUM(I29:M29)=0,"",SUM(I29:M29)) | O29: =IF(A29="","",TEXT(A29,"yyyy-mm")) | P29: =IF(A29="","",YEAR(A29)) | Q29: =IF(A29="","",MONTH(A29)) | U29: 0 | V29: =IF(B29="","",N29-U29) | X29: =IF(B29="","",IF(LEFT(B29,2)="NC",-1,1)) | Y29: =IF(B29="",0,N(I29)*X29) | Z29: =IF(B29="",0,N(J29)*X29) | AA29: =IF(B29="",0,N(K29)*X29) | AB29: =IF(B29="",0,N(L29)*X29) | AC29: =IF(B29="",0,N(N29)*X29)
H30: =IF(G30="","",IF(ISNUMBER(SEARCH("CAPITA",UPPER(G30))),651110,IF(ISNUMBER(SEARCH("REFUERZO",UPPER(G30))),651110,IF(ISNUMBER(SEARCH("VACUNACION",UPPER(G30))),651110,IF(ISNUMBER(SEARCH("ENFERMERIA",UPPER(G30))),651110,IF(ISNUMBER(SEARCH("APORTES",UPPER(G30))),651110,IF(ISNUMBER(SEARCH("HONORARIOS",UPPER(G30))),702010,IF(ISNUMBER(SEARCH("ADMINISTRACION",UPPER(G30))),702010,IF(ISNUMBER(SEARCH("GERENCIAMIENTO",UPPER(G30))),702010,IF(ISNUMBER(SEARCH("ALQUILER",UPPER(G30))),702010,IF(ISNUMBER(SEARCH("AUDITORIA",UPPER(G30))),702010,IF(ISNUMBER(SEARCH("PRESTACIONAL",UPPER(G30))),702010,702010)))))))))))) | K30: =IF(N(I30)>0,ROUND(N(I30)*IVA_general,2),0) | L30: 0 | N30: =IF(SUM(I30:M30)=0,"",SUM(I30:M30)) | O30: =IF(A30="","",TEXT(A30,"yyyy-mm")) | P30: =IF(A30="","",YEAR(A30)) | Q30: =IF(A30="","",MONTH(A30)) | U30: 0 | V30: =IF(B30="","",N30-U30) | X30: =IF(B30="","",IF(LEFT(B30,2)="NC",-1,1)) | Y30: =IF(B30="",0,N(I30)*X30) | Z30: =IF(B30="",0,N(J30)*X30) | AA30: =IF(B30="",0,N(K30)*X30) | AB30: =IF(B30="",0,N(L30)*X30) | AC30: =IF(B30="",0,N(N30)*X30)
H31: =IF(G31="","",IF(ISNUMBER(SEARCH("CAPITA",UPPER(G31))),651110,IF(ISNUMBER(SEARCH("REFUERZO",UPPER(G31))),651110,IF(ISNUMBER(SEARCH("VACUNACION",UPPER(G31))),651110,IF(ISNUMBER(SEARCH("ENFERMERIA",UPPER(G31))),651110,IF(ISNUMBER(SEARCH("APORTES",UPPER(G31))),651110,IF(ISNUMBER(SEARCH("HONORARIOS",UPPER(G31))),702010,IF(ISNUMBER(SEARCH("ADMINISTRACION",UPPER(G31))),702010,IF(ISNUMBER(SEARCH("GERENCIAMIENTO",UPPER(G31))),702010,IF(ISNUMBER(SEARCH("ALQUILER",UPPER(G31))),702010,IF(ISNUMBER(SEARCH("AUDITORIA",UPPER(G31))),702010,IF(ISNUMBER(SEARCH("PRESTACIONAL",UPPER(G31))),702010,702010)))))))))))) | K31: =IF(N(I31)>0,ROUND(N(I31)*IVA_general,2),0) | L31: 0 | N31: =IF(SUM(I31:M31)=0,"",SUM(I31:M31)) | O31: =IF(A31="","",TEXT(A31,"yyyy-mm")) | P31: =IF(A31="","",YEAR(A31)) | Q31: =IF(A31="","",MONTH(A31)) | U31: 0 | V31: =IF(B31="","",N31-U31) | X31: =IF(B31="","",IF(LEFT(B31,2)="NC",-1,1)) | Y31: =IF(B31="",0,N(I31)*X31) | Z31: =IF(B31="",0,N(J31)*X31) | AA31: =IF(B31="",0,N(K31)*X31) | AB31: =IF(B31="",0,N(L31)*X31) | AC31: =IF(B31="",0,N(N31)*X31)
H32: =IF(G32="","",IF(ISNUMBER(SEARCH("CAPITA",UPPER(G32))),651110,IF(ISNUMBER(SEARCH("REFUERZO",UPPER(G32))),651110,IF(ISNUMBER(SEARCH("VACUNACION",UPPER(G32))),651110,IF(ISNUMBER(SEARCH("ENFERMERIA",UPPER(G32))),651110,IF(ISNUMBER(SEARCH("APORTES",UPPER(G32))),651110,IF(ISNUMBER(SEARCH("HONORARIOS",UPPER(G32))),702010,IF(ISNUMBER(SEARCH("ADMINISTRACION",UPPER(G32))),702010,IF(ISNUMBER(SEARCH("GERENCIAMIENTO",UPPER(G32))),702010,IF(ISNUMBER(SEARCH("ALQUILER",UPPER(G32))),702010,IF(ISNUMBER(SEARCH("AUDITORIA",UPPER(G32))),702010,IF(ISNUMBER(SEARCH("PRESTACIONAL",UPPER(G32))),702010,702010)))))))))))) | K32: =IF(N(I32)>0,ROUND(N(I32)*IVA_general,2),0) | L32: 0 | N32: =IF(SUM(I32:M32)=0,"",SUM(I32:M32)) | O32: =IF(A32="","",TEXT(A32,"yyyy-mm")) | P32: =IF(A32="","",YEAR(A32)) | Q32: =IF(A32="","",MONTH(A32)) | U32: 0 | V32: =IF(B32="","",N32-U32) | X32: =IF(B32="","",IF(LEFT(B32,2)="NC",-1,1)) | Y32: =IF(B32="",0,N(I32)*X32) | Z32: =IF(B32="",0,N(J32)*X32) | AA32: =IF(B32="",0,N(K32)*X32) | AB32: =IF(B32="",0,N(L32)*X32) | AC32: =IF(B32="",0,N(N32)*X32)
H33: =IF(G33="","",IF(ISNUMBER(SEARCH("CAPITA",UPPER(G33))),651110,IF(ISNUMBER(SEARCH("REFUERZO",UPPER(G33))),651110,IF(ISNUMBER(SEARCH("VACUNACION",UPPER(G33))),651110,IF(ISNUMBER(SEARCH("ENFERMERIA",UPPER(G33))),651110,IF(ISNUMBER(SEARCH("APORTES",UPPER(G33))),651110,IF(ISNUMBER(SEARCH("HONORARIOS",UPPER(G33))),702010,IF(ISNUMBER(SEARCH("ADMINISTRACION",UPPER(G33))),702010,IF(ISNUMBER(SEARCH("GERENCIAMIENTO",UPPER(G33))),702010,IF(ISNUMBER(SEARCH("ALQUILER",UPPER(G33))),702010,IF(ISNUMBER(SEARCH("AUDITORIA",UPPER(G33))),702010,IF(ISNUMBER(SEARCH("PRESTACIONAL",UPPER(G33))),702010,702010)))))))))))) | K33: =IF(N(I33)>0,ROUND(N(I33)*IVA_general,2),0) | L33: 0 | N33: =IF(SUM(I33:M33)=0,"",SUM(I33:M33)) | O33: =IF(A33="","",TEXT(A33,"yyyy-mm")) | P33: =IF(A33="","",YEAR(A33)) | Q33: =IF(A33="","",MONTH(A33)) | U33: 0 | V33: =IF(B33="","",N33-U33) | X33: =IF(B33="","",IF(LEFT(B33,2)="NC",-1,1)) | Y33: =IF(B33="",0,N(I33)*X33) | Z33: =IF(B33="",0,N(J33)*X33) | AA33: =IF(B33="",0,N(K33)*X33) | AB33: =IF(B33="",0,N(L33)*X33) | AC33: =IF(B33="",0,N(N33)*X33)
H34: =IF(G34="","",IF(ISNUMBER(SEARCH("CAPITA",UPPER(G34))),651110,IF(ISNUMBER(SEARCH("REFUERZO",UPPER(G34))),651110,IF(ISNUMBER(SEARCH("VACUNACION",UPPER(G34))),651110,IF(ISNUMBER(SEARCH("ENFERMERIA",UPPER(G34))),651110,IF(ISNUMBER(SEARCH("APORTES",UPPER(G34))),651110,IF(ISNUMBER(SEARCH("HONORARIOS",UPPER(G34))),702010,IF(ISNUMBER(SEARCH("ADMINISTRACION",UPPER(G34))),702010,IF(ISNUMBER(SEARCH("GERENCIAMIENTO",UPPER(G34))),702010,IF(ISNUMBER(SEARCH("ALQUILER",UPPER(G34))),702010,IF(ISNUMBER(SEARCH("AUDITORIA",UPPER(G34))),702010,IF(ISNUMBER(SEARCH("PRESTACIONAL",UPPER(G34))),702010,702010)))))))))))) | K34: =IF(N(I34)>0,ROUND(N(I34)*IVA_general,2),0) | L34: 0 | N34: =IF(SUM(I34:M34)=0,"",SUM(I34:M34)) | O34: =IF(A34="","",TEXT(A34,"yyyy-mm")) | P34: =IF(A34="","",YEAR(A34)) | Q34: =IF(A34="","",MONTH(A34)) | U34: 0 | V34: =IF(B34="","",N34-U34) | X34: =IF(B34="","",IF(LEFT(B34,2)="NC",-1,1)) | Y34: =IF(B34="",0,N(I34)*X34) | Z34: =IF(B34="",0,N(J34)*X34) | AA34: =IF(B34="",0,N(K34)*X34) | AB34: =IF(B34="",0,N(L34)*X34) | AC34: =IF(B34="",0,N(N34)*X34)
H35: =IF(G35="","",IF(ISNUMBER(SEARCH("CAPITA",UPPER(G35))),651110,IF(ISNUMBER(SEARCH("REFUERZO",UPPER(G35))),651110,IF(ISNUMBER(SEARCH("VACUNACION",UPPER(G35))),651110,IF(ISNUMBER(SEARCH("ENFERMERIA",UPPER(G35))),651110,IF(ISNUMBER(SEARCH("APORTES",UPPER(G35))),651110,IF(ISNUMBER(SEARCH("HONORARIOS",UPPER(G35))),702010,IF(ISNUMBER(SEARCH("ADMINISTRACION",UPPER(G35))),702010,IF(ISNUMBER(SEARCH("GERENCIAMIENTO",UPPER(G35))),702010,IF(ISNUMBER(SEARCH("ALQUILER",UPPER(G35))),702010,IF(ISNUMBER(SEARCH("AUDITORIA",UPPER(G35))),702010,IF(ISNUMBER(SEARCH("PRESTACIONAL",UPPER(G35))),702010,702010)))))))))))) | K35: =IF(N(I35)>0,ROUND(N(I35)*IVA_general,2),0) | L35: 0 | N35: =IF(SUM(I35:M35)=0,"",SUM(I35:M35)) | O35: =IF(A35="","",TEXT(A35,"yyyy-mm")) | P35: =IF(A35="","",YEAR(A35)) | Q35: =IF(A35="","",MONTH(A35)) | U35: 0 | V35: =IF(B35="","",N35-U35) | X35: =IF(B35="","",IF(LEFT(B35,2)="NC",-1,1)) | Y35: =IF(B35="",0,N(I35)*X35) | Z35: =IF(B35="",0,N(J35)*X35) | AA35: =IF(B35="",0,N(K35)*X35) | AB35: =IF(B35="",0,N(L35)*X35) | AC35: =IF(B35="",0,N(N35)*X35)
H36: =IF(G36="","",IF(ISNUMBER(SEARCH("CAPITA",UPPER(G36))),651110,IF(ISNUMBER(SEARCH("REFUERZO",UPPER(G36))),651110,IF(ISNUMBER(SEARCH("VACUNACION",UPPER(G36))),651110,IF(ISNUMBER(SEARCH("ENFERMERIA",UPPER(G36))),651110,IF(ISNUMBER(SEARCH("APORTES",UPPER(G36))),651110,IF(ISNUMBER(SEARCH("HONORARIOS",UPPER(G36))),702010,IF(ISNUMBER(SEARCH("ADMINISTRACION",UPPER(G36))),702010,IF(ISNUMBER(SEARCH("GERENCIAMIENTO",UPPER(G36))),702010,IF(ISNUMBER(SEARCH("ALQUILER",UPPER(G36))),702010,IF(ISNUMBER(SEARCH("AUDITORIA",UPPER(G36))),702010,IF(ISNUMBER(SEARCH("PRESTACIONAL",UPPER(G36))),702010,702010)))))))))))) | K36: =IF(N(I36)>0,ROUND(N(I36)*IVA_general,2),0) | L36: 0 | N36: =IF(SUM(I36:M36)=0,"",SUM(I36:M36)) | O36: =IF(A36="","",TEXT(A36,"yyyy-mm")) | P36: =IF(A36="","",YEAR(A36)) | Q36: =IF(A36="","",MONTH(A36)) | U36: 0 | V36: =IF(B36="","",N36-U36) | X36: =IF(B36="","",IF(LEFT(B36,2)="NC",-1,1)) | Y36: =IF(B36="",0,N(I36)*X36) | Z36: =IF(B36="",0,N(J36)*X36) | AA36: =IF(B36="",0,N(K36)*X36) | AB36: =IF(B36="",0,N(L36)*X36) | AC36: =IF(B36="",0,N(N36)*X36)
H37: =IF(G37="","",IF(ISNUMBER(SEARCH("CAPITA",UPPER(G37))),651110,IF(ISNUMBER(SEARCH("REFUERZO",UPPER(G37))),651110,IF(ISNUMBER(SEARCH("VACUNACION",UPPER(G37))),651110,IF(ISNUMBER(SEARCH("ENFERMERIA",UPPER(G37))),651110,IF(ISNUMBER(SEARCH("APORTES",UPPER(G37))),651110,IF(ISNUMBER(SEARCH("HONORARIOS",UPPER(G37))),702010,IF(ISNUMBER(SEARCH("ADMINISTRACION",UPPER(G37))),702010,IF(ISNUMBER(SEARCH("GERENCIAMIENTO",UPPER(G37))),702010,IF(ISNUMBER(SEARCH("ALQUILER",UPPER(G37))),702010,IF(ISNUMBER(SEARCH("AUDITORIA",UPPER(G37))),702010,IF(ISNUMBER(SEARCH("PRESTACIONAL",UPPER(G37))),702010,702010)))))))))))) | K37: =IF(N(I37)>0,ROUND(N(I37)*IVA_general,2),0) | L37: 0 | N37: =IF(SUM(I37:M37)=0,"",SUM(I37:M37)) | O37: =IF(A37="","",TEXT(A37,"yyyy-mm")) | P37: =IF(A37="","",YEAR(A37)) | Q37: =IF(A37="","",MONTH(A37)) | U37: 0 | V37: =IF(B37="","",N37-U37) | X37: =IF(B37="","",IF(LEFT(B37,2)="NC",-1,1)) | Y37: =IF(B37="",0,N(I37)*X37) | Z37: =IF(B37="",0,N(J37)*X37) | AA37: =IF(B37="",0,N(K37)*X37) | AB37: =IF(B37="",0,N(L37)*X37) | AC37: =IF(B37="",0,N(N37)*X37)
... H501: =IF(G501="","",IF(ISNUMBER(SEARCH("CAPITA",UPPER(G501))),651110,IF(ISNUMBER(SEARCH("REFUERZO",UPPER(G501))),651110,IF(ISNUMBER(SEARCH("VACUNACION",UPPER(G501))),651110,IF(ISNUMBER(SEARCH("ENFERMERIA",UPPER(G501))),651110,IF(ISNUMBER(SEARCH("APORTES",UPPER(G501))),651110,IF(ISNUMBER(SEARCH("HONORARIOS",UPPER(G501))),702010,IF(ISNUMBER(SEARCH("ADMINISTRACION",UPPER(G501))),702010,IF(ISNUMBER(SEARCH("GERENCIAMIENTO",UPPER(G501))),702010,IF(ISNUMBER(SEARCH("ALQUILER",UPPER(G501))),702010,IF(ISNUMBER(SEARCH("AUDITORIA",UPPER(G501))),702010,IF(ISNUMBER(SEARCH("PRESTACIONAL",UPPER(G501))),702010,702010)))))))))))) | K501: =IF(N(I501)>0,ROUND(N(I501)*IVA_general,2),0) | L501: 0 | N501: =IF(SUM(I501:M501)=0,"",SUM(I501:M501)) | O501: =IF(A501="","",TEXT(A501,"yyyy-mm")) | P501: =IF(A501="","",YEAR(A501)) | Q501: =IF(A501="","",MONTH(A501)) | U501: 0 | V501: =IF(B501="","",N501-U501) | X501: =IF(B501="","",IF(LEFT(B501,2)="NC",-1,1)) | Y501: =IF(B501="",0,N(I501)*X501) | Z501: =IF(B501="",0,N(J501)*X501) | AA501: =IF(B501="",0,N(K501)*X501) | AB501: =IF(B501="",0,N(L501)*X501) | AC501: =IF(B501="",0,N(N501)*X501)

Sheet Checklist
A1: CHECKLIST DE FACTURACIÓN MENSUAL - 2026
A2: Cliente | B2: Concepto | C2: Activ. | D2: Ene | E2: Feb | F2: Mar | G2: Abr | H2: May | I2: Jun | J2: Jul | K2: Ago | L2: Sep | M2: Oct | N2: Nov | O2: Dic | P2: Total Año | Q2: % Compl.
A3: OSPLYF | B3: Cápitas + Honorarios + Extras | C3: multi | D3: =SUMIFS(Fac_Total,Fac_Cliente,$A3,Fac_Mes,1,Fac_Anio,2026,Fac_EstadoAFIP,"<>Anulada") | E3: =SUMIFS(Fac_Total,Fac_Cliente,$A3,Fac_Mes,2,Fac_Anio,2026,Fac_EstadoAFIP,"<>Anulada") | F3: =SUMIFS(Fac_Total,Fac_Cliente,$A3,Fac_Mes,3,Fac_Anio,2026,Fac_EstadoAFIP,"<>Anulada") | G3: =SUMIFS(Fac_Total,Fac_Cliente,$A3,Fac_Mes,4,Fac_Anio,2026,Fac_EstadoAFIP,"<>Anulada") | H3: =SUMIFS(Fac_Total,Fac_Cliente,$A3,Fac_Mes,5,Fac_Anio,2026,Fac_EstadoAFIP,"<>Anulada") | I3: =SUMIFS(Fac_Total,Fac_Cliente,$A3,Fac_Mes,6,Fac_Anio,2026,Fac_EstadoAFIP,"<>Anulada") | J3: =SUMIFS(Fac_Total,Fac_Cliente,$A3,Fac_Mes,7,Fac_Anio,2026,Fac_EstadoAFIP,"<>Anulada") | K3: =SUMIFS(Fac_Total,Fac_Cliente,$A3,Fac_Mes,8,Fac_Anio,2026,Fac_EstadoAFIP,"<>Anulada") | L3: =SUMIFS(Fac_Total,Fac_Cliente,$A3,Fac_Mes,9,Fac_Anio,2026,Fac_EstadoAFIP,"<>Anulada") | M3: =SUMIFS(Fac_Total,Fac_Cliente,$A3,Fac_Mes,10,Fac_Anio,2026,Fac_EstadoAFIP,"<>Anulada") | N3: =SUMIFS(Fac_Total,Fac_Cliente,$A3,Fac_Mes,11,Fac_Anio,2026,Fac_EstadoAFIP,"<>Anulada") | O3: =SUMIFS(Fac_Total,Fac_Cliente,$A3,Fac_Mes,12,Fac_Anio,2026,Fac_EstadoAFIP,"<>Anulada") | P3: =SUM(D3:O3) | Q3: =COUNTIF(D3:O3,">0")/12
A4: OSSURRBAC | B4: Cápita + Alquiler ecógrafo + Servicios | C4: multi | D4: =SUMIFS(Fac_Total,Fac_Cliente,$A4,Fac_Mes,1,Fac_Anio,2026,Fac_EstadoAFIP,"<>Anulada") | E4: =SUMIFS(Fac_Total,Fac_Cliente,$A4,Fac_Mes,2,Fac_Anio,2026,Fac_EstadoAFIP,"<>Anulada") | F4: =SUMIFS(Fac_Total,Fac_Cliente,$A4,Fac_Mes,3,Fac_Anio,2026,Fac_EstadoAFIP,"<>Anulada") | G4: =SUMIFS(Fac_Total,Fac_Cliente,$A4,Fac_Mes,4,Fac_Anio,2026,Fac_EstadoAFIP,"<>Anulada") | H4: =SUMIFS(Fac_Total,Fac_Cliente,$A4,Fac_Mes,5,Fac_Anio,2026,Fac_EstadoAFIP,"<>Anulada") | I4: =SUMIFS(Fac_Total,Fac_Cliente,$A4,Fac_Mes,6,Fac_Anio,2026,Fac_EstadoAFIP,"<>Anulada") | J4: =SUMIFS(Fac_Total,Fac_Cliente,$A4,Fac_Mes,7,Fac_Anio,2026,Fac_EstadoAFIP,"<>Anulada") | K4: =SUMIFS(Fac_Total,Fac_Cliente,$A4,Fac_Mes,8,Fac_Anio,2026,Fac_EstadoAFIP,"<>Anulada") | L4: =SUMIFS(Fac_Total,Fac_Cliente,$A4,Fac_Mes,9,Fac_Anio,2026,Fac_EstadoAFIP,"<>Anulada") | M4: =SUMIFS(Fac_Total,Fac_Cliente,$A4,Fac_Mes,10,Fac_Anio,2026,Fac_EstadoAFIP,"<>Anulada") | N4: =SUMIFS(Fac_Total,Fac_Cliente,$A4,Fac_Mes,11,Fac_Anio,2026,Fac_EstadoAFIP,"<>Anulada") | O4: =SUMIFS(Fac_Total,Fac_Cliente,$A4,Fac_Mes,12,Fac_Anio,2026,Fac_EstadoAFIP,"<>Anulada") | P4: =SUM(D4:O4) | Q4: =COUNTIF(D4:O4,">0")/12
A5: AMSURRBAC | B5: Cápitas vacunación + enfermería | C5: multi | D5: =SUMIFS(Fac_Total,Fac_Cliente,$A5,Fac_Mes,1,Fac_Anio,2026,Fac_EstadoAFIP,"<>Anulada") | E5: =SUMIFS(Fac_Total,Fac_Cliente,$A5,Fac_Mes,2,Fac_Anio,2026,Fac_EstadoAFIP,"<>Anulada") | F5: =SUMIFS(Fac_Total,Fac_Cliente,$A5,Fac_Mes,3,Fac_Anio,2026,Fac_EstadoAFIP,"<>Anulada") | G5: =SUMIFS(Fac_Total,Fac_Cliente,$A5,Fac_Mes,4,Fac_Anio,2026,Fac_EstadoAFIP,"<>Anulada") | H5: =SUMIFS(Fac_Total,Fac_Cliente,$A5,Fac_Mes,5,Fac_Anio,2026,Fac_EstadoAFIP,"<>Anulada") | I5: =SUMIFS(Fac_Total,Fac_Cliente,$A5,Fac_Mes,6,Fac_Anio,2026,Fac_EstadoAFIP,"<>Anulada") | J5: =SUMIFS(Fac_Total,Fac_Cliente,$A5,Fac_Mes,7,Fac_Anio,2026,Fac_EstadoAFIP,"<>Anulada") | K5: =SUMIFS(Fac_Total,Fac_Cliente,$A5,Fac_Mes,8,Fac_Anio,2026,Fac_EstadoAFIP,"<>Anulada") | L5: =SUMIFS(Fac_Total,Fac_Cliente,$A5,Fac_Mes,9,Fac_Anio,2026,Fac_EstadoAFIP,"<>Anulada") | M5: =SUMIFS(Fac_Total,Fac_Cliente,$A5,Fac_Mes,10,Fac_Anio,2026,Fac_EstadoAFIP,"<>Anulada") | N5: =SUMIFS(Fac_Total,Fac_Cliente,$A5,Fac_Mes,11,Fac_Anio,2026,Fac_EstadoAFIP,"<>Anulada") | O5: =SUMIFS(Fac_Total,Fac_Cliente,$A5,Fac_Mes,12,Fac_Anio,2026,Fac_EstadoAFIP,"<>Anulada") | P5: =SUM(D5:O5) | Q5: =COUNTIF(D5:O5,">0")/12
A6: OSPEVIC | B6: Cápita + Extra cápita | C6: multi | D6: =SUMIFS(Fac_Total,Fac_Cliente,$A6,Fac_Mes,1,Fac_Anio,2026,Fac_EstadoAFIP,"<>Anulada") | E6: =SUMIFS(Fac_Total,Fac_Cliente,$A6,Fac_Mes,2,Fac_Anio,2026,Fac_EstadoAFIP,"<>Anulada") | F6: =SUMIFS(Fac_Total,Fac_Cliente,$A6,Fac_Mes,3,Fac_Anio,2026,Fac_EstadoAFIP,"<>Anulada") | G6: =SUMIFS(Fac_Total,Fac_Cliente,$A6,Fac_Mes,4,Fac_Anio,2026,Fac_EstadoAFIP,"<>Anulada") | H6: =SUMIFS(Fac_Total,Fac_Cliente,$A6,Fac_Mes,5,Fac_Anio,2026,Fac_EstadoAFIP,"<>Anulada") | I6: =SUMIFS(Fac_Total,Fac_Cliente,$A6,Fac_Mes,6,Fac_Anio,2026,Fac_EstadoAFIP,"<>Anulada") | J6: =SUMIFS(Fac_Total,Fac_Cliente,$A6,Fac_Mes,7,Fac_Anio,2026,Fac_EstadoAFIP,"<>Anulada") | K6: =SUMIFS(Fac_Total,Fac_Cliente,$A6,Fac_Mes,8,Fac_Anio,2026,Fac_EstadoAFIP,"<>Anulada") | L6: =SUMIFS(Fac_Total,Fac_Cliente,$A6,Fac_Mes,9,Fac_Anio,2026,Fac_EstadoAFIP,"<>Anulada") | M6: =SUMIFS(Fac_Total,Fac_Cliente,$A6,Fac_Mes,10,Fac_Anio,2026,Fac_EstadoAFIP,"<>Anulada") | N6: =SUMIFS(Fac_Total,Fac_Cliente,$A6,Fac_Mes,11,Fac_Anio,2026,Fac_EstadoAFIP,"<>Anulada") | O6: =SUMIFS(Fac_Total,Fac_Cliente,$A6,Fac_Mes,12,Fac_Anio,2026,Fac_EstadoAFIP,"<>Anulada") | P6: =SUM(D6:O6) | Q6: =COUNTIF(D6:O6,">0")/12
A7: OSPIF | B7: Cápita + Honorarios + Aportes | C7: multi | D7: =SUMIFS(Fac_Total,Fac_Cliente,$A7,Fac_Mes,1,Fac_Anio,2026,Fac_EstadoAFIP,"<>Anulada") | E7: =SUMIFS(Fac_Total,Fac_Cliente,$A7,Fac_Mes,2,Fac_Anio,2026,Fac_EstadoAFIP,"<>Anulada") | F7: =SUMIFS(Fac_Total,Fac_Cliente,$A7,Fac_Mes,3,Fac_Anio,2026,Fac_EstadoAFIP,"<>Anulada") | G7: =SUMIFS(Fac_Total,Fac_Cliente,$A7,Fac_Mes,4,Fac_Anio,2026,Fac_EstadoAFIP,"<>Anulada") | H7: =SUMIFS(Fac_Total,Fac_Cliente,$A7,Fac_Mes,5,Fac_Anio,2026,Fac_EstadoAFIP,"<>Anulada") | I7: =SUMIFS(Fac_Total,Fac_Cliente,$A7,Fac_Mes,6,Fac_Anio,2026,Fac_EstadoAFIP,"<>Anulada") | J7: =SUMIFS(Fac_Total,Fac_Cliente,$A7,Fac_Mes,7,Fac_Anio,2026,Fac_EstadoAFIP,"<>Anulada") | K7: =SUMIFS(Fac_Total,Fac_Cliente,$A7,Fac_Mes,8,Fac_Anio,2026,Fac_EstadoAFIP,"<>Anulada") | L7: =SUMIFS(Fac_Total,Fac_Cliente,$A7,Fac_Mes,9,Fac_Anio,2026,Fac_EstadoAFIP,"<>Anulada") | M7: =SUMIFS(Fac_Total,Fac_Cliente,$A7,Fac_Mes,10,Fac_Anio,2026,Fac_EstadoAFIP,"<>Anulada") | N7: =SUMIFS(Fac_Total,Fac_Cliente,$A7,Fac_Mes,11,Fac_Anio,2026,Fac_EstadoAFIP,"<>Anulada") | O7: =SUMIFS(Fac_Total,Fac_Cliente,$A7,Fac_Mes,12,Fac_Anio,2026,Fac_EstadoAFIP,"<>Anulada") | P7: =SUM(D7:O7) | Q7: =COUNTIF(D7:O7,">0")/12
A8: UOM | B8: Servicios médicos prestacionales | C8: multi | D8: =SUMIFS(Fac_Total,Fac_Cliente,$A8,Fac_Mes,1,Fac_Anio,2026,Fac_EstadoAFIP,"<>Anulada") | E8: =SUMIFS(Fac_Total,Fac_Cliente,$A8,Fac_Mes,2,Fac_Anio,2026,Fac_EstadoAFIP,"<>Anulada") | F8: =SUMIFS(Fac_Total,Fac_Cliente,$A8,Fac_Mes,3,Fac_Anio,2026,Fac_EstadoAFIP,"<>Anulada") | G8: =SUMIFS(Fac_Total,Fac_Cliente,$A8,Fac_Mes,4,Fac_Anio,2026,Fac_EstadoAFIP,"<>Anulada") | H8: =SUMIFS(Fac_Total,Fac_Cliente,$A8,Fac_Mes,5,Fac_Anio,2026,Fac_EstadoAFIP,"<>Anulada") | I8: =SUMIFS(Fac_Total,Fac_Cliente,$A8,Fac_Mes,6,Fac_Anio,2026,Fac_EstadoAFIP,"<>Anulada") | J8: =SUMIFS(Fac_Total,Fac_Cliente,$A8,Fac_Mes,7,Fac_Anio,2026,Fac_EstadoAFIP,"<>Anulada") | K8: =SUMIFS(Fac_Total,Fac_Cliente,$A8,Fac_Mes,8,Fac_Anio,2026,Fac_EstadoAFIP,"<>Anulada") | L8: =SUMIFS(Fac_Total,Fac_Cliente,$A8,Fac_Mes,9,Fac_Anio,2026,Fac_EstadoAFIP,"<>Anulada") | M8: =SUMIFS(Fac_Total,Fac_Cliente,$A8,Fac_Mes,10,Fac_Anio,2026,Fac_EstadoAFIP,"<>Anulada") | N8: =SUMIFS(Fac_Total,Fac_Cliente,$A8,Fac_Mes,11,Fac_Anio,2026,Fac_EstadoAFIP,"<>Anulada") | O8: =SUMIFS(Fac_Total,Fac_Cliente,$A8,Fac_Mes,12,Fac_Anio,2026,Fac_EstadoAFIP,"<>Anulada") | P8: =SUM(D8:O8) | Q8: =COUNTIF(D8:O8,">0")/12
A9: MOSAISTAS | B9: Honorarios | C9: multi | D9: =SUMIFS(Fac_Total,Fac_Cliente,$A9,Fac_Mes,1,Fac_Anio,2026,Fac_EstadoAFIP,"<>Anulada") | E9: =SUMIFS(Fac_Total,Fac_Cliente,$A9,Fac_Mes,2,Fac_Anio,2026,Fac_EstadoAFIP,"<>Anulada") | F9: =SUMIFS(Fac_Total,Fac_Cliente,$A9,Fac_Mes,3,Fac_Anio,2026,Fac_EstadoAFIP,"<>Anulada") | G9: =SUMIFS(Fac_Total,Fac_Cliente,$A9,Fac_Mes,4,Fac_Anio,2026,Fac_EstadoAFIP,"<>Anulada") | H9: =SUMIFS(Fac_Total,Fac_Cliente,$A9,Fac_Mes,5,Fac_Anio,2026,Fac_EstadoAFIP,"<>Anulada") | I9: =SUMIFS(Fac_Total,Fac_Cliente,$A9,Fac_Mes,6,Fac_Anio,2026,Fac_EstadoAFIP,"<>Anulada") | J9: =SUMIFS(Fac_Total,Fac_Cliente,$A9,Fac_Mes,7,Fac_Anio,2026,Fac_EstadoAFIP,"<>Anulada") | K9: =SUMIFS(Fac_Total,Fac_Cliente,$A9,Fac_Mes,8,Fac_Anio,2026,Fac_EstadoAFIP,"<>Anulada") | L9: =SUMIFS(Fac_Total,Fac_Cliente,$A9,Fac_Mes,9,Fac_Anio,2026,Fac_EstadoAFIP,"<>Anulada") | M9: =SUMIFS(Fac_Total,Fac_Cliente,$A9,Fac_Mes,10,Fac_Anio,2026,Fac_EstadoAFIP,"<>Anulada") | N9: =SUMIFS(Fac_Total,Fac_Cliente,$A9,Fac_Mes,11,Fac_Anio,2026,Fac_EstadoAFIP,"<>Anulada") | O9: =SUMIFS(Fac_Total,Fac_Cliente,$A9,Fac_Mes,12,Fac_Anio,2026,Fac_EstadoAFIP,"<>Anulada") | P9: =SUM(D9:O9) | Q9: =COUNTIF(D9:O9,">0")/12
A10: FUNDACION BIENESTAR SIRELYF | B10: Servicios prestacionales | C10: multi | D10: =SUMIFS(Fac_Total,Fac_Cliente,$A10,Fac_Mes,1,Fac_Anio,2026,Fac_EstadoAFIP,"<>Anulada") | E10: =SUMIFS(Fac_Total,Fac_Cliente,$A10,Fac_Mes,2,Fac_Anio,2026,Fac_EstadoAFIP,"<>Anulada") | F10: =SUMIFS(Fac_Total,Fac_Cliente,$A10,Fac_Mes,3,Fac_Anio,2026,Fac_EstadoAFIP,"<>Anulada") | G10: =SUMIFS(Fac_Total,Fac_Cliente,$A10,Fac_Mes,4,Fac_Anio,2026,Fac_EstadoAFIP,"<>Anulada") | H10: =SUMIFS(Fac_Total,Fac_Cliente,$A10,Fac_Mes,5,Fac_Anio,2026,Fac_EstadoAFIP,"<>Anulada") | I10: =SUMIFS(Fac_Total,Fac_Cliente,$A10,Fac_Mes,6,Fac_Anio,2026,Fac_EstadoAFIP,"<>Anulada") | J10: =SUMIFS(Fac_Total,Fac_Cliente,$A10,Fac_Mes,7,Fac_Anio,2026,Fac_EstadoAFIP,"<>Anulada") | K10: =SUMIFS(Fac_Total,Fac_Cliente,$A10,Fac_Mes,8,Fac_Anio,2026,Fac_EstadoAFIP,"<>Anulada") | L10: =SUMIFS(Fac_Total,Fac_Cliente,$A10,Fac_Mes,9,Fac_Anio,2026,Fac_EstadoAFIP,"<>Anulada") | M10: =SUMIFS(Fac_Total,Fac_Cliente,$A10,Fac_Mes,10,Fac_Anio,2026,Fac_EstadoAFIP,"<>Anulada") | N10: =SUMIFS(Fac_Total,Fac_Cliente,$A10,Fac_Mes,11,Fac_Anio,2026,Fac_EstadoAFIP,"<>Anulada") | O10: =SUMIFS(Fac_Total,Fac_Cliente,$A10,Fac_Mes,12,Fac_Anio,2026,Fac_EstadoAFIP,"<>Anulada") | P10: =SUM(D10:O10) | Q10: =COUNTIF(D10:O10,">0")/12
A11: CFC | B11: Servicios prestacionales | C11: multi | D11: =SUMIFS(Fac_Total,Fac_Cliente,$A11,Fac_Mes,1,Fac_Anio,2026,Fac_EstadoAFIP,"<>Anulada") | E11: =SUMIFS(Fac_Total,Fac_Cliente,$A11,Fac_Mes,2,Fac_Anio,2026,Fac_EstadoAFIP,"<>Anulada") | F11: =SUMIFS(Fac_Total,Fac_Cliente,$A11,Fac_Mes,3,Fac_Anio,2026,Fac_EstadoAFIP,"<>Anulada") | G11: =SUMIFS(Fac_Total,Fac_Cliente,$A11,Fac_Mes,4,Fac_Anio,2026,Fac_EstadoAFIP,"<>Anulada") | H11: =SUMIFS(Fac_Total,Fac_Cliente,$A11,Fac_Mes,5,Fac_Anio,2026,Fac_EstadoAFIP,"<>Anulada") | I11: =SUMIFS(Fac_Total,Fac_Cliente,$A11,Fac_Mes,6,Fac_Anio,2026,Fac_EstadoAFIP,"<>Anulada") | J11: =SUMIFS(Fac_Total,Fac_Cliente,$A11,Fac_Mes,7,Fac_Anio,2026,Fac_EstadoAFIP,"<>Anulada") | K11: =SUMIFS(Fac_Total,Fac_Cliente,$A11,Fac_Mes,8,Fac_Anio,2026,Fac_EstadoAFIP,"<>Anulada") | L11: =SUMIFS(Fac_Total,Fac_Cliente,$A11,Fac_Mes,9,Fac_Anio,2026,Fac_EstadoAFIP,"<>Anulada") | M11: =SUMIFS(Fac_Total,Fac_Cliente,$A11,Fac_Mes,10,Fac_Anio,2026,Fac_EstadoAFIP,"<>Anulada") | N11: =SUMIFS(Fac_Total,Fac_Cliente,$A11,Fac_Mes,11,Fac_Anio,2026,Fac_EstadoAFIP,"<>Anulada") | O11: =SUMIFS(Fac_Total,Fac_Cliente,$A11,Fac_Mes,12,Fac_Anio,2026,Fac_EstadoAFIP,"<>Anulada") | P11: =SUM(D11:O11) | Q11: =COUNTIF(D11:O11,">0")/12
A13: TOTAL MENSUAL | D13: =SUM(D3:D11) | E13: =SUM(E3:E11) | F13: =SUM(F3:F11) | G13: =SUM(G3:G11) | H13: =SUM(H3:H11) | I13: =SUM(I3:I11) | J13: =SUM(J3:J11) | K13: =SUM(K3:K11) | ... P13: =SUM(P3:P11)
A15: CLIENTES EVENTUALES (mes a mes)
A16: Suma de facturas a clientes que NO están en la lista de fijos arriba.
A17: EVENTUALES | D17: =SUMIFS(Fac_Total,Fac_Mes,1,Fac_Anio,2026,Fac_EstadoAFIP,"<>Anulada")-D13 | E17: =SUMIFS(Fac_Total,Fac_Mes,2,Fac_Anio,2026,Fac_EstadoAFIP,"<>Anulada")-E13 | F17: =SUMIFS(Fac_Total,Fac_Mes,3,Fac_Anio,2026,Fac_EstadoAFIP,"<>Anulada")-F13 | G17: =SUMIFS(Fac_Total,Fac_Mes,4,Fac_Anio,2026,Fac_EstadoAFIP,"<>Anulada")-G13 | H17: =SUMIFS(Fac_Total,Fac_Mes,5,Fac_Anio,2026,Fac_EstadoAFIP,"<>Anulada")-H13 | I17: =SUMIFS(Fac_Total,Fac_Mes,6,Fac_Anio,2026,Fac_EstadoAFIP,"<>Anulada")-I13 | J17: =SUMIFS(Fac_Total,Fac_Mes,7,Fac_Anio,2026,Fac_EstadoAFIP,"<>Anulada")-J13 | K17: =SUMIFS(Fac_Total,Fac_Mes,8,Fac_Anio,2026,Fac_EstadoAFIP,"<>Anulada")-K13 | L17: =SUMIFS(Fac_Total,Fac_Mes,9,Fac_Anio,2026,Fac_EstadoAFIP,"<>Anulada")-L13 | M17: =SUMIFS(Fac_Total,Fac_Mes,10,Fac_Anio,2026,Fac_EstadoAFIP,"<>Anulada")-M13 | N17: =SUMIFS(Fac_Total,Fac_Mes,11,Fac_Anio,2026,Fac_EstadoAFIP,"<>Anulada")-N13 | O17: =SUMIFS(Fac_Total,Fac_Mes,12,Fac_Anio,2026,Fac_EstadoAFIP,"<>Anulada")-O13 | P17: =SUM(D17:O17)

Sheet Cobranzas
A1: ESTADO DE COBRANZAS
A2: Fecha Factura | B2: Cliente | C2: Concepto | D2: Total Factura | E2: Estado Cobro | F2: Fecha Cobro | G2: Días desde emisión | H2: Período Devengamiento | I2: Observaciones | K2: RESUMEN COBRANZAS
A3: =IF(Facturacion!A2="","",Facturacion!A2) | B3: =IF(Facturacion!E2="","",Facturacion!E2) | C3: =IF(Facturacion!G2="","",Facturacion!G2) | D3: =IF(Facturacion!N2="","",Facturacion!N2) | E3: =IF(Facturacion!S2="","",Facturacion!S2) | F3: =IF(Facturacion!T2="","",Facturacion!T2) | G3: =IF(Facturacion!A2="","",IF(Facturacion!T2<>"",Facturacion!T2-Facturacion!A2,TODAY()-Facturacion!A2)) | H3: =IF(Facturacion!O2="","",Facturacion!O2) | I3: =IF(Facturacion!U2="","",Facturacion!U2) | K3: Total Facturado | L3: =SUM(D3:D502)
A4: =IF(Facturacion!A3="","",Facturacion!A3) | B4: =IF(Facturacion!E3="","",Facturacion!E3) | C4: =IF(Facturacion!G3="","",Facturacion!G3) | D4: =IF(Facturacion!N3="","",Facturacion!N3) | E4: =IF(Facturacion!S3="","",Facturacion!S3) | F4: =IF(Facturacion!T3="","",Facturacion!T3) | G4: =IF(Facturacion!A3="","",IF(Facturacion!T3<>"",Facturacion!T3-Facturacion!A3,TODAY()-Facturacion!A3)) | H4: =IF(Facturacion!O3="","",Facturacion!O3) | I4: =IF(Facturacion!U3="","",Facturacion!U3) | K4: Total Cobrado | L4: =SUMIF(E3:E502,"Cobrada",D3:D502)
A5: =IF(Facturacion!A4="","",Facturacion!A4) | B5: =IF(Facturacion!E4="","",Facturacion!E4) | C5: =IF(Facturacion!G4="","",Facturacion!G4) | D5: =IF(Facturacion!N4="","",Facturacion!N4) | E5: =IF(Facturacion!S4="","",Facturacion!S4) | F5: =IF(Facturacion!T4="","",Facturacion!T4) | G5: =IF(Facturacion!A4="","",IF(Facturacion!T4<>"",Facturacion!T4-Facturacion!A4,TODAY()-Facturacion!A4)) | H5: =IF(Facturacion!O4="","",Facturacion!O4) | I5: =IF(Facturacion!U4="","",Facturacion!U4) | K5: Total Pendiente | L5: =SUMIF(E3:E502,"Pendiente",D3:D502)
A6: =IF(Facturacion!A5="","",Facturacion!A5) | B6: =IF(Facturacion!E5="","",Facturacion!E5) | C6: =IF(Facturacion!G5="","",Facturacion!G5) | D6: =IF(Facturacion!N5="","",Facturacion!N5) | E6: =IF(Facturacion!S5="","",Facturacion!S5) | F6: =IF(Facturacion!T5="","",Facturacion!T5) | G6: =IF(Facturacion!A5="","",IF(Facturacion!T5<>"",Facturacion!T5-Facturacion!A5,TODAY()-Facturacion!A5)) | H6: =IF(Facturacion!O5="","",Facturacion!O5) | I6: =IF(Facturacion!U5="","",Facturacion!U5) | K6: Total Vencido | L6: =SUMIF(E3:E502,"Vencida",D3:D502)
A7: =IF(Facturacion!A6="","",Facturacion!A6) | B7: =IF(Facturacion!E6="","",Facturacion!E6) | C7: =IF(Facturacion!G6="","",Facturacion!G6) | D7: =IF(Facturacion!N6="","",Facturacion!N6) | E7: =IF(Facturacion!S6="","",Facturacion!S6) | F7: =IF(Facturacion!T6="","",Facturacion!T6) | G7: =IF(Facturacion!A6="","",IF(Facturacion!T6<>"",Facturacion!T6-Facturacion!A6,TODAY()-Facturacion!A6)) | H7: =IF(Facturacion!O6="","",Facturacion!O6) | I7: =IF(Facturacion!U6="","",Facturacion!U6) | K7: % Cobrado | L7: =IFERROR(L4/L3,0)
A8: =IF(Facturacion!A7="","",Facturacion!A7) | B8: =IF(Facturacion!E7="","",Facturacion!E7) | C8: =IF(Facturacion!G7="","",Facturacion!G7) | D8: =IF(Facturacion!N7="","",Facturacion!N7) | E8: =IF(Facturacion!S7="","",Facturacion!S7) | F8: =IF(Facturacion!T7="","",Facturacion!T7) | G8: =IF(Facturacion!A7="","",IF(Facturacion!T7<>"",Facturacion!T7-Facturacion!A7,TODAY()-Facturacion!A7)) | H8: =IF(Facturacion!O7="","",Facturacion!O7) | I8: =IF(Facturacion!U7="","",Facturacion!U7)
A9: =IF(Facturacion!A8="","",Facturacion!A8) | B9: =IF(Facturacion!E8="","",Facturacion!E8) | C9: =IF(Facturacion!G8="","",Facturacion!G8) | D9: =IF(Facturacion!N8="","",Facturacion!N8) | E9: =IF(Facturacion!S8="","",Facturacion!S8) | F9: =IF(Facturacion!T8="","",Facturacion!T8) | G9: =IF(Facturacion!A8="","",IF(Facturacion!T8<>"",Facturacion!T8-Facturacion!A8,TODAY()-Facturacion!A8)) | H9: =IF(Facturacion!O8="","",Facturacion!O8) | I9: =IF(Facturacion!U8="","",Facturacion!U8)
A10: =IF(Facturacion!A9="","",Facturacion!A9) | B10: =IF(Facturacion!E9="","",Facturacion!E9) | C10: =IF(Facturacion!G9="","",Facturacion!G9) | D10: =IF(Facturacion!N9="","",Facturacion!N9) | E10: =IF(Facturacion!S9="","",Facturacion!S9) | F10: =IF(Facturacion!T9="","",Facturacion!T9) | G10: =IF(Facturacion!A9="","",IF(Facturacion!T9<>"",Facturacion!T9-Facturacion!A9,TODAY()-Facturacion!A9)) | H10: =IF(Facturacion!O9="","",Facturacion!O9) | I10: =IF(Facturacion!U9="","",Facturacion!U9)
A11: =IF(Facturacion!A10="","",Facturacion!A10) | B11: =IF(Facturacion!E10="","",Facturacion!E10) | C11: =IF(Facturacion!G10="","",Facturacion!G10) | D11: =IF(Facturacion!N10="","",Facturacion!N10) | E11: =IF(Facturacion!S10="","",Facturacion!S10) | F11: =IF(Facturacion!T10="","",Facturacion!T10) | G11: =IF(Facturacion!A10="","",IF(Facturacion!T10<>"",Facturacion!T10-Facturacion!A10,TODAY()-Facturacion!A10)) | H11: =IF(Facturacion!O10="","",Facturacion!O10) | I11: =IF(Facturacion!U10="","",Facturacion!U10)
A12: =IF(Facturacion!A11="","",Facturacion!A11) | B12: =IF(Facturacion!E11="","",Facturacion!E11) | C12: =IF(Facturacion!G11="","",Facturacion!G11) | D12: =IF(Facturacion!N11="","",Facturacion!N11) | E12: =IF(Facturacion!S11="","",Facturacion!S11) | F12: =IF(Facturacion!T11="","",Facturacion!T11) | G12: =IF(Facturacion!A11="","",IF(Facturacion!T11<>"",Facturacion!T11-Facturacion!A11,TODAY()-Facturacion!A11)) | H12: =IF(Facturacion!O11="","",Facturacion!O11) | I12: =IF(Facturacion!U11="","",Facturacion!U11)
A13: =IF(Facturacion!A12="","",Facturacion!A12) | B13: =IF(Facturacion!E12="","",Facturacion!E12) | C13: =IF(Facturacion!G12="","",Facturacion!G12) | D13: =IF(Facturacion!N12="","",Facturacion!N12) | E13: =IF(Facturacion!S12="","",Facturacion!S12) | F13: =IF(Facturacion!T12="","",Facturacion!T12) | G13: =IF(Facturacion!A12="","",IF(Facturacion!T12<>"",Facturacion!T12-Facturacion!A12,TODAY()-Facturacion!A12)) | H13: =IF(Facturacion!O12="","",Facturacion!O12) | I13: =IF(Facturacion!U12="","",Facturacion!U12)
A14: =IF(Facturacion!A13="","",Facturacion!A13) | B14: =IF(Facturacion!E13="","",Facturacion!E13) | C14: =IF(Facturacion!G13="","",Facturacion!G13) | D14: =IF(Facturacion!N13="","",Facturacion!N13) | E14: =IF(Facturacion!S13="","",Facturacion!S13) | F14: =IF(Facturacion!T13="","",Facturacion!T13) | G14: =IF(Facturacion!A13="","",IF(Facturacion!T13<>"",Facturacion!T13-Facturacion!A13,TODAY()-Facturacion!A13)) | H14: =IF(Facturacion!O13="","",Facturacion!O13) | I14: =IF(Facturacion!U13="","",Facturacion!U13)
A15: =IF(Facturacion!A14="","",Facturacion!A14) | B15: =IF(Facturacion!E14="","",Facturacion!E14) | C15: =IF(Facturacion!G14="","",Facturacion!G14) | D15: =IF(Facturacion!N14="","",Facturacion!N14) | E15: =IF(Facturacion!S14="","",Facturacion!S14) | F15: =IF(Facturacion!T14="","",Facturacion!T14) | G15: =IF(Facturacion!A14="","",IF(Facturacion!T14<>"",Facturacion!T14-Facturacion!A14,TODAY()-Facturacion!A14)) | H15: =IF(Facturacion!O14="","",Facturacion!O14) | I15: =IF(Facturacion!U14="","",Facturacion!U14)
A16: =IF(Facturacion!A15="","",Facturacion!A15) | B16: =IF(Facturacion!E15="","",Facturacion!E15) | C16: =IF(Facturacion!G15="","",Facturacion!G15) | D16: =IF(Facturacion!N15="","",Facturacion!N15) | E16: =IF(Facturacion!S15="","",Facturacion!S15) | F16: =IF(Facturacion!T15="","",Facturacion!T15) | G16: =IF(Facturacion!A15="","",IF(Facturacion!T15<>"",Facturacion!T15-Facturacion!A15,TODAY()-Facturacion!A15)) | H16: =IF(Facturacion!O15="","",Facturacion!O15) | I16: =IF(Facturacion!U15="","",Facturacion!U15)
A17: =IF(Facturacion!A16="","",Facturacion!A16) | B17: =IF(Facturacion!E16="","",Facturacion!E16) | C17: =IF(Facturacion!G16="","",Facturacion!G16) | D17: =IF(Facturacion!N16="","",Facturacion!N16) | E17: =IF(Facturacion!S16="","",Facturacion!S16) | F17: =IF(Facturacion!T16="","",Facturacion!T16) | G17: =IF(Facturacion!A16="","",IF(Facturacion!T16<>"",Facturacion!T16-Facturacion!A16,TODAY()-Facturacion!A16)) | H17: =IF(Facturacion!O16="","",Facturacion!O16) | I17: =IF(Facturacion!U16="","",Facturacion!U16)
A18: =IF(Facturacion!A17="","",Facturacion!A17) | B18: =IF(Facturacion!E17="","",Facturacion!E17) | C18: =IF(Facturacion!G17="","",Facturacion!G17) | D18: =IF(Facturacion!N17="","",Facturacion!N17) | E18: =IF(Facturacion!S17="","",Facturacion!S17) | F18: =IF(Facturacion!T17="","",Facturacion!T17) | G18: =IF(Facturacion!A17="","",IF(Facturacion!T17<>"",Facturacion!T17-Facturacion!A17,TODAY()-Facturacion!A17)) | H18: =IF(Facturacion!O17="","",Facturacion!O17) | I18: =IF(Facturacion!U17="","",Facturacion!U17)
A19: =IF(Facturacion!A18="","",Facturacion!A18) | B19: =IF(Facturacion!E18="","",Facturacion!E18) | C19: =IF(Facturacion!G18="","",Facturacion!G18) | D19: =IF(Facturacion!N18="","",Facturacion!N18) | E19: =IF(Facturacion!S18="","",Facturacion!S18) | F19: =IF(Facturacion!T18="","",Facturacion!T18) | G19: =IF(Facturacion!A18="","",IF(Facturacion!T18<>"",Facturacion!T18-Facturacion!A18,TODAY()-Facturacion!A18)) | H19: =IF(Facturacion!O18="","",Facturacion!O18) | I19: =IF(Facturacion!U18="","",Facturacion!U18)
... A502: =IF(Facturacion!A501="","",Facturacion!A501) | B502: =IF(Facturacion!E501="","",Facturacion!E501) | C502: =IF(Facturacion!G501="","",Facturacion!G501) | D502: =IF(Facturacion!N501="","",Facturacion!N501) | E502: =IF(Facturacion!S501="","",Facturacion!S501) | F502: =IF(Facturacion!T501="","",Facturacion!T501) | G502: =IF(Facturacion!A501="","",IF(Facturacion!T501<>"",Facturacion!T501-Facturacion!A501,TODAY()-Facturacion!A501)) | H502: =IF(Facturacion!O501="","",Facturacion!O501) | I502: =IF(Facturacion!U501="","",Facturacion!U501)

Sheet Impuestos
A1: CÁLCULO DE IMPUESTOS APROXIMADO - 2026
A2: Concepto | B2: Ene | C2: Feb | D2: Mar | E2: Abr | F2: May | G2: Jun | H2: Jul | I2: Ago | J2: Sep | K2: Oct | L2: Nov | M2: Dic | N2: Total Año | O2: Notas
A3: BASE: Facturación mensual
A4: Total Facturado (Neto + Exento) | B4: =SUMIFS(Fac_Neto,Fac_Mes,1,Fac_Anio,2026,Fac_EstadoAFIP,"<>Anulada")+SUMIFS(Fac_NoGrav,Fac_Mes,1,Fac_Anio,2026,Fac_EstadoAFIP,"<>Anulada") | C4: =SUMIFS(Fac_Neto,Fac_Mes,2,Fac_Anio,2026,Fac_EstadoAFIP,"<>Anulada")+SUMIFS(Fac_NoGrav,Fac_Mes,2,Fac_Anio,2026,Fac_EstadoAFIP,"<>Anulada") | D4: =SUMIFS(Fac_Neto,Fac_Mes,3,Fac_Anio,2026,Fac_EstadoAFIP,"<>Anulada")+SUMIFS(Fac_NoGrav,Fac_Mes,3,Fac_Anio,2026,Fac_EstadoAFIP,"<>Anulada") | E4: =SUMIFS(Fac_Neto,Fac_Mes,4,Fac_Anio,2026,Fac_EstadoAFIP,"<>Anulada")+SUMIFS(Fac_NoGrav,Fac_Mes,4,Fac_Anio,2026,Fac_EstadoAFIP,"<>Anulada") | F4: =SUMIFS(Fac_Neto,Fac_Mes,5,Fac_Anio,2026,Fac_EstadoAFIP,"<>Anulada")+SUMIFS(Fac_NoGrav,Fac_Mes,5,Fac_Anio,2026,Fac_EstadoAFIP,"<>Anulada") | G4: =SUMIFS(Fac_Neto,Fac_Mes,6,Fac_Anio,2026,Fac_EstadoAFIP,"<>Anulada")+SUMIFS(Fac_NoGrav,Fac_Mes,6,Fac_Anio,2026,Fac_EstadoAFIP,"<>Anulada") | H4: =SUMIFS(Fac_Neto,Fac_Mes,7,Fac_Anio,2026,Fac_EstadoAFIP,"<>Anulada")+SUMIFS(Fac_NoGrav,Fac_Mes,7,Fac_Anio,2026,Fac_EstadoAFIP,"<>Anulada") | I4: =SUMIFS(Fac_Neto,Fac_Mes,8,Fac_Anio,2026,Fac_EstadoAFIP,"<>Anulada")+SUMIFS(Fac_NoGrav,Fac_Mes,8,Fac_Anio,2026,Fac_EstadoAFIP,"<>Anulada") | J4: =SUMIFS(Fac_Neto,Fac_Mes,9,Fac_Anio,2026,Fac_EstadoAFIP,"<>Anulada")+SUMIFS(Fac_NoGrav,Fac_Mes,9,Fac_Anio,2026,Fac_EstadoAFIP,"<>Anulada") | K4: =SUMIFS(Fac_Neto,Fac_Mes,10,Fac_Anio,2026,Fac_EstadoAFIP,"<>Anulada")+SUMIFS(Fac_NoGrav,Fac_Mes,10,Fac_Anio,2026,Fac_EstadoAFIP,"<>Anulada") | L4: =SUMIFS(Fac_Neto,Fac_Mes,11,Fac_Anio,2026,Fac_EstadoAFIP,"<>Anulada")+SUMIFS(Fac_NoGrav,Fac_Mes,11,Fac_Anio,2026,Fac_EstadoAFIP,"<>Anulada") | M4: =SUMIFS(Fac_Neto,Fac_Mes,12,Fac_Anio,2026,Fac_EstadoAFIP,"<>Anulada")+SUMIFS(Fac_NoGrav,Fac_Mes,12,Fac_Anio,2026,Fac_EstadoAFIP,"<>Anulada") | N4: =SUM(B4:M4) | O4: Suma de Neto Gravado + No Gravado/Exento
A5: → Actividad 702010 (Gerenciamiento) | B5: =SUMIFS(Fac_Neto,Fac_Mes,1,Fac_Anio,2026,Fac_EstadoAFIP,"<>Anulada",Fac_Actividad,702010)+SUMIFS(Fac_NoGrav,Fac_Mes,1,Fac_Anio,2026,Fac_EstadoAFIP,"<>Anulada",Fac_Actividad,702010) | C5: =SUMIFS(Fac_Neto,Fac_Mes,2,Fac_Anio,2026,Fac_EstadoAFIP,"<>Anulada",Fac_Actividad,702010)+SUMIFS(Fac_NoGrav,Fac_Mes,2,Fac_Anio,2026,Fac_EstadoAFIP,"<>Anulada",Fac_Actividad,702010) | D5: =SUMIFS(Fac_Neto,Fac_Mes,3,Fac_Anio,2026,Fac_EstadoAFIP,"<>Anulada",Fac_Actividad,702010)+SUMIFS(Fac_NoGrav,Fac_Mes,3,Fac_Anio,2026,Fac_EstadoAFIP,"<>Anulada",Fac_Actividad,702010) | E5: =SUMIFS(Fac_Neto,Fac_Mes,4,Fac_Anio,2026,Fac_EstadoAFIP,"<>Anulada",Fac_Actividad,702010)+SUMIFS(Fac_NoGrav,Fac_Mes,4,Fac_Anio,2026,Fac_EstadoAFIP,"<>Anulada",Fac_Actividad,702010) | F5: =SUMIFS(Fac_Neto,Fac_Mes,5,Fac_Anio,2026,Fac_EstadoAFIP,"<>Anulada",Fac_Actividad,702010)+SUMIFS(Fac_NoGrav,Fac_Mes,5,Fac_Anio,2026,Fac_EstadoAFIP,"<>Anulada",Fac_Actividad,702010) | G5: =SUMIFS(Fac_Neto,Fac_Mes,6,Fac_Anio,2026,Fac_EstadoAFIP,"<>Anulada",Fac_Actividad,702010)+SUMIFS(Fac_NoGrav,Fac_Mes,6,Fac_Anio,2026,Fac_EstadoAFIP,"<>Anulada",Fac_Actividad,702010) | H5: =SUMIFS(Fac_Neto,Fac_Mes,7,Fac_Anio,2026,Fac_EstadoAFIP,"<>Anulada",Fac_Actividad,702010)+SUMIFS(Fac_NoGrav,Fac_Mes,7,Fac_Anio,2026,Fac_EstadoAFIP,"<>Anulada",Fac_Actividad,702010) | I5: =SUMIFS(Fac_Neto,Fac_Mes,8,Fac_Anio,2026,Fac_EstadoAFIP,"<>Anulada",Fac_Actividad,702010)+SUMIFS(Fac_NoGrav,Fac_Mes,8,Fac_Anio,2026,Fac_EstadoAFIP,"<>Anulada",Fac_Actividad,702010) | J5: =SUMIFS(Fac_Neto,Fac_Mes,9,Fac_Anio,2026,Fac_EstadoAFIP,"<>Anulada",Fac_Actividad,702010)+SUMIFS(Fac_NoGrav,Fac_Mes,9,Fac_Anio,2026,Fac_EstadoAFIP,"<>Anulada",Fac_Actividad,702010) | K5: =SUMIFS(Fac_Neto,Fac_Mes,10,Fac_Anio,2026,Fac_EstadoAFIP,"<>Anulada",Fac_Actividad,702010)+SUMIFS(Fac_NoGrav,Fac_Mes,10,Fac_Anio,2026,Fac_EstadoAFIP,"<>Anulada",Fac_Actividad,702010) | L5: =SUMIFS(Fac_Neto,Fac_Mes,11,Fac_Anio,2026,Fac_EstadoAFIP,"<>Anulada",Fac_Actividad,702010)+SUMIFS(Fac_NoGrav,Fac_Mes,11,Fac_Anio,2026,Fac_EstadoAFIP,"<>Anulada",Fac_Actividad,702010) | M5: =SUMIFS(Fac_Neto,Fac_Mes,12,Fac_Anio,2026,Fac_EstadoAFIP,"<>Anulada",Fac_Actividad,702010)+SUMIFS(Fac_NoGrav,Fac_Mes,12,Fac_Anio,2026,Fac_EstadoAFIP,"<>Anulada",Fac_Actividad,702010) | N5: =SUM(B5:M5)
A6: → Actividad 651110 (Seguros) | B6: =SUMIFS(Fac_Neto,Fac_Mes,1,Fac_Anio,2026,Fac_EstadoAFIP,"<>Anulada",Fac_Actividad,651110)+SUMIFS(Fac_NoGrav,Fac_Mes,1,Fac_Anio,2026,Fac_EstadoAFIP,"<>Anulada",Fac_Actividad,651110) | C6: =SUMIFS(Fac_Neto,Fac_Mes,2,Fac_Anio,2026,Fac_EstadoAFIP,"<>Anulada",Fac_Actividad,651110)+SUMIFS(Fac_NoGrav,Fac_Mes,2,Fac_Anio,2026,Fac_EstadoAFIP,"<>Anulada",Fac_Actividad,651110) | D6: =SUMIFS(Fac_Neto,Fac_Mes,3,Fac_Anio,2026,Fac_EstadoAFIP,"<>Anulada",Fac_Actividad,651110)+SUMIFS(Fac_NoGrav,Fac_Mes,3,Fac_Anio,2026,Fac_EstadoAFIP,"<>Anulada",Fac_Actividad,651110) | E6: =SUMIFS(Fac_Neto,Fac_Mes,4,Fac_Anio,2026,Fac_EstadoAFIP,"<>Anulada",Fac_Actividad,651110)+SUMIFS(Fac_NoGrav,Fac_Mes,4,Fac_Anio,2026,Fac_EstadoAFIP,"<>Anulada",Fac_Actividad,651110) | F6: =SUMIFS(Fac_Neto,Fac_Mes,5,Fac_Anio,2026,Fac_EstadoAFIP,"<>Anulada",Fac_Actividad,651110)+SUMIFS(Fac_NoGrav,Fac_Mes,5,Fac_Anio,2026,Fac_EstadoAFIP,"<>Anulada",Fac_Actividad,651110) | G6: =SUMIFS(Fac_Neto,Fac_Mes,6,Fac_Anio,2026,Fac_EstadoAFIP,"<>Anulada",Fac_Actividad,651110)+SUMIFS(Fac_NoGrav,Fac_Mes,6,Fac_Anio,2026,Fac_EstadoAFIP,"<>Anulada",Fac_Actividad,651110) | H6: =SUMIFS(Fac_Neto,Fac_Mes,7,Fac_Anio,2026,Fac_EstadoAFIP,"<>Anulada",Fac_Actividad,651110)+SUMIFS(Fac_NoGrav,Fac_Mes,7,Fac_Anio,2026,Fac_EstadoAFIP,"<>Anulada",Fac_Actividad,651110) | I6: =SUMIFS(Fac_Neto,Fac_Mes,8,Fac_Anio,2026,Fac_EstadoAFIP,"<>Anulada",Fac_Actividad,651110)+SUMIFS(Fac_NoGrav,Fac_Mes,8,Fac_Anio,2026,Fac_EstadoAFIP,"<>Anulada",Fac_Actividad,651110) | J6: =SUMIFS(Fac_Neto,Fac_Mes,9,Fac_Anio,2026,Fac_EstadoAFIP,"<>Anulada",Fac_Actividad,651110)+SUMIFS(Fac_NoGrav,Fac_Mes,9,Fac_Anio,2026,Fac_EstadoAFIP,"<>Anulada",Fac_Actividad,651110) | K6: =SUMIFS(Fac_Neto,Fac_Mes,10,Fac_Anio,2026,Fac_EstadoAFIP,"<>Anulada",Fac_Actividad,651110)+SUMIFS(Fac_NoGrav,Fac_Mes,10,Fac_Anio,2026,Fac_EstadoAFIP,"<>Anulada",Fac_Actividad,651110) | L6: =SUMIFS(Fac_Neto,Fac_Mes,11,Fac_Anio,2026,Fac_EstadoAFIP,"<>Anulada",Fac_Actividad,651110)+SUMIFS(Fac_NoGrav,Fac_Mes,11,Fac_Anio,2026,Fac_EstadoAFIP,"<>Anulada",Fac_Actividad,651110) | M6: =SUMIFS(Fac_Neto,Fac_Mes,12,Fac_Anio,2026,Fac_EstadoAFIP,"<>Anulada",Fac_Actividad,651110)+SUMIFS(Fac_NoGrav,Fac_Mes,12,Fac_Anio,2026,Fac_EstadoAFIP,"<>Anulada",Fac_Actividad,651110) | N6: =SUM(B6:M6)
A8: IVA
A9: Neto Gravado 21% | B9: =SUMIFS(Fac_Neto,Fac_Mes,1,Fac_Anio,2026,Fac_EstadoAFIP,"<>Anulada") | C9: =SUMIFS(Fac_Neto,Fac_Mes,2,Fac_Anio,2026,Fac_EstadoAFIP,"<>Anulada") | D9: =SUMIFS(Fac_Neto,Fac_Mes,3,Fac_Anio,2026,Fac_EstadoAFIP,"<>Anulada") | E9: =SUMIFS(Fac_Neto,Fac_Mes,4,Fac_Anio,2026,Fac_EstadoAFIP,"<>Anulada") | F9: =SUMIFS(Fac_Neto,Fac_Mes,5,Fac_Anio,2026,Fac_EstadoAFIP,"<>Anulada") | G9: =SUMIFS(Fac_Neto,Fac_Mes,6,Fac_Anio,2026,Fac_EstadoAFIP,"<>Anulada") | H9: =SUMIFS(Fac_Neto,Fac_Mes,7,Fac_Anio,2026,Fac_EstadoAFIP,"<>Anulada") | I9: =SUMIFS(Fac_Neto,Fac_Mes,8,Fac_Anio,2026,Fac_EstadoAFIP,"<>Anulada") | J9: =SUMIFS(Fac_Neto,Fac_Mes,9,Fac_Anio,2026,Fac_EstadoAFIP,"<>Anulada") | K9: =SUMIFS(Fac_Neto,Fac_Mes,10,Fac_Anio,2026,Fac_EstadoAFIP,"<>Anulada") | L9: =SUMIFS(Fac_Neto,Fac_Mes,11,Fac_Anio,2026,Fac_EstadoAFIP,"<>Anulada") | M9: =SUMIFS(Fac_Neto,Fac_Mes,12,Fac_Anio,2026,Fac_EstadoAFIP,"<>Anulada") | N9: =SUM(B9:M9)
A10: IVA Débito Fiscal (21%) | B10: =SUMIFS(Fac_IVA21,Fac_Mes,1,Fac_Anio,2026,Fac_EstadoAFIP,"<>Anulada")+SUMIFS(Fac_IVA105,Fac_Mes,1,Fac_Anio,2026,Fac_EstadoAFIP,"<>Anulada") | C10: =SUMIFS(Fac_IVA21,Fac_Mes,2,Fac_Anio,2026,Fac_EstadoAFIP,"<>Anulada")+SUMIFS(Fac_IVA105,Fac_Mes,2,Fac_Anio,2026,Fac_EstadoAFIP,"<>Anulada") | D10: =SUMIFS(Fac_IVA21,Fac_Mes,3,Fac_Anio,2026,Fac_EstadoAFIP,"<>Anulada")+SUMIFS(Fac_IVA105,Fac_Mes,3,Fac_Anio,2026,Fac_EstadoAFIP,"<>Anulada") | E10: =SUMIFS(Fac_IVA21,Fac_Mes,4,Fac_Anio,2026,Fac_EstadoAFIP,"<>Anulada")+SUMIFS(Fac_IVA105,Fac_Mes,4,Fac_Anio,2026,Fac_EstadoAFIP,"<>Anulada") | F10: =SUMIFS(Fac_IVA21,Fac_Mes,5,Fac_Anio,2026,Fac_EstadoAFIP,"<>Anulada")+SUMIFS(Fac_IVA105,Fac_Mes,5,Fac_Anio,2026,Fac_EstadoAFIP,"<>Anulada") | G10: =SUMIFS(Fac_IVA21,Fac_Mes,6,Fac_Anio,2026,Fac_EstadoAFIP,"<>Anulada")+SUMIFS(Fac_IVA105,Fac_Mes,6,Fac_Anio,2026,Fac_EstadoAFIP,"<>Anulada") | H10: =SUMIFS(Fac_IVA21,Fac_Mes,7,Fac_Anio,2026,Fac_EstadoAFIP,"<>Anulada")+SUMIFS(Fac_IVA105,Fac_Mes,7,Fac_Anio,2026,Fac_EstadoAFIP,"<>Anulada") | I10: =SUMIFS(Fac_IVA21,Fac_Mes,8,Fac_Anio,2026,Fac_EstadoAFIP,"<>Anulada")+SUMIFS(Fac_IVA105,Fac_Mes,8,Fac_Anio,2026,Fac_EstadoAFIP,"<>Anulada") | J10: =SUMIFS(Fac_IVA21,Fac_Mes,9,Fac_Anio,2026,Fac_EstadoAFIP,"<>Anulada")+SUMIFS(Fac_IVA105,Fac_Mes,9,Fac_Anio,2026,Fac_EstadoAFIP,"<>Anulada") | K10: =SUMIFS(Fac_IVA21,Fac_Mes,10,Fac_Anio,2026,Fac_EstadoAFIP,"<>Anulada")+SUMIFS(Fac_IVA105,Fac_Mes,10,Fac_Anio,2026,Fac_EstadoAFIP,"<>Anulada") | L10: =SUMIFS(Fac_IVA21,Fac_Mes,11,Fac_Anio,2026,Fac_EstadoAFIP,"<>Anulada")+SUMIFS(Fac_IVA105,Fac_Mes,11,Fac_Anio,2026,Fac_EstadoAFIP,"<>Anulada") | M10: =SUMIFS(Fac_IVA21,Fac_Mes,12,Fac_Anio,2026,Fac_EstadoAFIP,"<>Anulada")+SUMIFS(Fac_IVA105,Fac_Mes,12,Fac_Anio,2026,Fac_EstadoAFIP,"<>Anulada") | N10: =SUM(B10:M10) | O10: Suma IVA 21% + IVA 10,5% de facturas no anuladas
A11: IVA Crédito Fiscal estimado (prorrateo) | B11: =B10*Pct_credito | C11: =C10*Pct_credito | D11: =D10*Pct_credito | E11: =E10*Pct_credito | F11: =F10*Pct_credito | G11: =G10*Pct_credito | H11: =H10*Pct_credito | I11: =I10*Pct_credito | ... M11: =M10*Pct_credito | N11: =SUM(B11:M11) | O11: Débito × % crédito (definido en Reglas)
A12: IVA Saldo a pagar (estimado) | B12: =MAX(0,B10-B11) | C12: =MAX(0,C10-C11) | D12: =MAX(0,D10-D11) | E12: =MAX(0,E10-E11) | F12: =MAX(0,F10-F11) | G12: =MAX(0,G10-G11) | H12: =MAX(0,H10-H11) | I12: =MAX(0,I10-I11) | ... M12: =MAX(0,M10-M11) | N12: =SUM(B12:M12) | O12: MAX(Débito - Crédito; 0)
A13: Vencimiento IVA (mes siguiente) | B13: =DATE(2026,2,Reglas!$C$49) | C13: =DATE(2026,3,Reglas!$C$49) | D13: =DATE(2026,4,Reglas!$C$49) | E13: =DATE(2026,5,Reglas!$C$49) | F13: =DATE(2026,6,Reglas!$C$49) | G13: =DATE(2026,7,Reglas!$C$49) | H13: =DATE(2026,8,Reglas!$C$49) | I13: =DATE(2026,9,Reglas!$C$49) | J13: =DATE(2026,10,Reglas!$C$49) | K13: =DATE(2026,11,Reglas!$C$49) | L13: =DATE(2026,12,Reglas!$C$49) | M13: =DATE(2027,1,Reglas!$C$49) | O13: Día configurable en hoja Reglas
A15: IIBB - CABA (901)
A16: Base distribuida CABA - 702010 | B16: =B5*Coef_CABA | C16: =C5*Coef_CABA | D16: =D5*Coef_CABA | E16: =E5*Coef_CABA | F16: =F5*Coef_CABA | G16: =G5*Coef_CABA | H16: =H5*Coef_CABA | I16: =I5*Coef_CABA | ... M16: =M5*Coef_CABA | N16: =SUM(B16:M16)
A17: Base distribuida CABA - 651110 | B17: =B6*Coef_CABA | C17: =C6*Coef_CABA | D17: =D6*Coef_CABA | E17: =E6*Coef_CABA | F17: =F6*Coef_CABA | G17: =G6*Coef_CABA | H17: =H6*Coef_CABA | I17: =I6*Coef_CABA | ... M17: =M6*Coef_CABA | N17: =SUM(B17:M17)
A18: Impuesto IIBB CABA - 702010 (3%) | B18: =B16*Alic_702_CABA | C18: =C16*Alic_702_CABA | D18: =D16*Alic_702_CABA | E18: =E16*Alic_702_CABA | F18: =F16*Alic_702_CABA | G18: =G16*Alic_702_CABA | H18: =H16*Alic_702_CABA | I18: =I16*Alic_702_CABA | ... M18: =M16*Alic_702_CABA | N18: =SUM(B18:M18)
A19: Impuesto IIBB CABA - 651110 (5,5%) | B19: =B17*Alic_651_CABA | C19: =C17*Alic_651_CABA | D19: =D17*Alic_651_CABA | E19: =E17*Alic_651_CABA | F19: =F17*Alic_651_CABA | G19: =G17*Alic_651_CABA | H19: =H17*Alic_651_CABA | I19: =I17*Alic_651_CABA | ... M19: =M17*Alic_651_CABA | N19: =SUM(B19:M19)
A20: IIBB CABA - Total Determinado | B20: =B18+B19 | C20: =C18+C19 | D20: =D18+D19 | E20: =E18+E19 | F20: =F18+F19 | G20: =G18+G19 | H20: =H18+H19 | I20: =I18+I19 | ... M20: =M18+M19 | N20: =SUM(B20:M20)
A21: (-) Retenciones / Percepciones / Recaudaciones CABA | B21: 0 | C21: 0 | D21: 0 | E21: 0 | F21: 0 | G21: 0 | H21: 0 | I21: 0 | J21: 0 | K21: 0 | L21: 0 | M21: 0 | N21: =SUM(B21:M21) | O21: Cargar manual cuando lleguen los certificados
A22: IIBB CABA - A pagar (estimado) | B22: =MAX(0,B20-B21) | C22: =MAX(0,C20-C21) | D22: =MAX(0,D20-D21) | E22: =MAX(0,E20-E21) | F22: =MAX(0,F20-F21) | G22: =MAX(0,G20-G21) | H22: =MAX(0,H20-H21) | I22: =MAX(0,I20-I21) | ... M22: =MAX(0,M20-M21) | N22: =SUM(B22:M22)
A24: IIBB - CÓRDOBA (904)
A25: Base distribuida Córdoba - 702010 | B25: =B5*Coef_Cba | C25: =C5*Coef_Cba | D25: =D5*Coef_Cba | E25: =E5*Coef_Cba | F25: =F5*Coef_Cba | G25: =G5*Coef_Cba | H25: =H5*Coef_Cba | I25: =I5*Coef_Cba | ... M25: =M5*Coef_Cba | N25: =SUM(B25:M25)
A26: Base distribuida Córdoba - 651110 | B26: =B6*Coef_Cba | C26: =C6*Coef_Cba | D26: =D6*Coef_Cba | E26: =E6*Coef_Cba | F26: =F6*Coef_Cba | G26: =G6*Coef_Cba | H26: =H6*Coef_Cba | I26: =I6*Coef_Cba | ... M26: =M6*Coef_Cba | N26: =SUM(B26:M26)
A27: Impuesto IIBB Cba - 702010 (5,5%) | B27: =B25*Alic_702_Cba | C27: =C25*Alic_702_Cba | D27: =D25*Alic_702_Cba | E27: =E25*Alic_702_Cba | F27: =F25*Alic_702_Cba | G27: =G25*Alic_702_Cba | H27: =H25*Alic_702_Cba | I27: =I25*Alic_702_Cba | ... M27: =M25*Alic_702_Cba | N27: =SUM(B27:M27)
A28: Impuesto IIBB Cba - 651110 (3%) | B28: =B26*Alic_651_Cba | C28: =C26*Alic_651_Cba | D28: =D26*Alic_651_Cba | E28: =E26*Alic_651_Cba | F28: =F26*Alic_651_Cba | G28: =G26*Alic_651_Cba | H28: =H26*Alic_651_Cba | I28: =I26*Alic_651_Cba | ... M28: =M26*Alic_651_Cba | N28: =SUM(B28:M28)
A29: IIBB Cba - Total Determinado | B29: =B27+B28 | C29: =C27+C28 | D29: =D27+D28 | E29: =E27+E28 | F29: =F27+F28 | G29: =G27+G28 | H29: =H27+H28 | I29: =I27+I28 | ... M29: =M27+M28 | N29: =SUM(B29:M29)
A30: (-) Retenciones / Percepciones / Recaudaciones Cba | B30: 0 | C30: 0 | D30: 0 | E30: 0 | F30: 0 | G30: 0 | H30: 0 | I30: 0 | J30: 0 | K30: 0 | L30: 0 | M30: 0 | N30: =SUM(B30:M30) | O30: Cargar manual cuando lleguen los certificados
A31: IIBB Cba - A pagar (estimado) | B31: =MAX(0,B29-B30) | C31: =MAX(0,C29-C30) | D31: =MAX(0,D29-D30) | E31: =MAX(0,E29-E30) | F31: =MAX(0,F29-F30) | G31: =MAX(0,G29-G30) | H31: =MAX(0,H29-H30) | I31: =MAX(0,I29-I30) | ... M31: =MAX(0,M29-M30) | N31: =SUM(B31:M31)
A33: Tasa Comercio e Industria - Municipalidad de Córdoba
A34: Base imponible (Facturación Cba) | B34: =B25+B26 | C34: =C25+C26 | D34: =D25+D26 | E34: =E25+E26 | F34: =F25+F26 | G34: =G25+G26 | H34: =H25+H26 | I34: =I25+I26 | ... M34: =M25+M26 | N34: =SUM(B34:M34) | O34: Solo la porción atribuida a Córdoba (CM)
A35: Tasa Comercio - Determinado | B35: =B34*Tasa_2026 | C35: =C34*Tasa_2026 | D35: =D34*Tasa_2026 | E35: =E34*Tasa_2026 | F35: =F34*Tasa_2026 | G35: =G34*Tasa_2026 | H35: =H34*Tasa_2026 | I35: =I34*Tasa_2026 | ... M35: =M34*Tasa_2026 | N35: =SUM(B35:M35) | O35: Base × Alícuota 2026 (definido en Reglas)
A36: (-) Retenciones / Recaudaciones Cba | B36: 0 | C36: 0 | D36: 0 | E36: 0 | F36: 0 | G36: 0 | H36: 0 | I36: 0 | J36: 0 | K36: 0 | L36: 0 | M36: 0 | N36: =SUM(B36:M36) | O36: Cargar manual cuando lleguen los certificados
A37: Tasa Comercio - A pagar (estimado) | B37: =MAX(0,B35-B36) | C37: =MAX(0,C35-C36) | D37: =MAX(0,D35-D36) | E37: =MAX(0,E35-E36) | F37: =MAX(0,F35-F36) | G37: =MAX(0,G35-G36) | H37: =MAX(0,H35-H36) | I37: =MAX(0,I35-I36) | ... M37: =MAX(0,M35-M36) | N37: =SUM(B37:M37)
A39: RESUMEN MENSUAL - TOTAL A PAGAR
A40: IVA | B40: =B12 | C40: =C12 | D40: =D12 | E40: =E12 | F40: =F12 | G40: =G12 | H40: =H12 | I40: =I12 | ... M40: =M12 | N40: =SUM(B40:M40)
A41: IIBB CABA | B41: =B22 | C41: =C22 | D41: =D22 | E41: =E22 | F41: =F22 | G41: =G22 | H41: =H22 | I41: =I22 | ... M41: =M22 | N41: =SUM(B41:M41)
A42: IIBB Córdoba | B42: =B31 | C42: =C31 | D42: =D31 | E42: =E31 | F42: =F31 | G42: =G31 | H42: =H31 | I42: =I31 | ... M42: =M31 | N42: =SUM(B42:M42)
A43: Tasa Comercio Cba | B43: =B37 | C43: =C37 | D43: =D37 | E43: =E37 | F43: =F37 | G43: =G37 | H43: =H37 | I43: =I37 | ... M43: =M37 | N43: =SUM(B43:M43)
A44: TOTAL IMPUESTOS DEL MES | B44: =B40+B41+B42+B43 | C44: =C40+C41+C42+C43 | D44: =D40+D41+D42+D43 | E44: =E40+E41+E42+E43 | F44: =F40+F41+F42+F43 | G44: =G40+G41+G42+G43 | H44: =H40+H41+H42+H43 | I44: =I40+I41+I42+I43 | ... M44: =M40+M41+M42+M43 | N44: =SUM(B44:M44)
A45: % Impuestos / Facturación | B45: =IFERROR(B44/B4,0) | C45: =IFERROR(C44/C4,0) | D45: =IFERROR(D44/D4,0) | E45: =IFERROR(E44/E4,0) | F45: =IFERROR(F44/F4,0) | G45: =IFERROR(G44/G4,0) | H45: =IFERROR(H44/H4,0) | I45: =IFERROR(I44/I4,0) | ... N45: =IFERROR(N44/N4,0)

Sheet Detalle IVA
A1: GRIFF SALUD SA
A2: IMPUESTO AL VALOR AGREGADO · Liquidación mensual
A3: Año 2026
A5: Concepto | B5: Ene | C5: Feb | D5: Mar | E5: Abr | F5: May | G5: Jun | H5: Jul | I5: Ago | J5: Sep | K5: Oct | L5: Nov | M5: Dic | N5: Total Año
A6: Operaciones del período
A7: Neto Gravado 21% | B7: =Impuestos!B9 | C7: =Impuestos!C9 | D7: =Impuestos!D9 | E7: =Impuestos!E9 | F7: =Impuestos!F9 | G7: =Impuestos!G9 | H7: =Impuestos!H9 | I7: =Impuestos!I9 | ... M7: =Impuestos!M9 | N7: =SUM(B7:M7)
A8: Neto Gravado 10,5% | B8: =SUMIFS(Fac_IVA105,Fac_Mes,1,Fac_Anio,2026,Fac_EstadoAFIP,"<>Anulada")/0.105 | C8: =SUMIFS(Fac_IVA105,Fac_Mes,2,Fac_Anio,2026,Fac_EstadoAFIP,"<>Anulada")/0.105 | D8: =SUMIFS(Fac_IVA105,Fac_Mes,3,Fac_Anio,2026,Fac_EstadoAFIP,"<>Anulada")/0.105 | E8: =SUMIFS(Fac_IVA105,Fac_Mes,4,Fac_Anio,2026,Fac_EstadoAFIP,"<>Anulada")/0.105 | F8: =SUMIFS(Fac_IVA105,Fac_Mes,5,Fac_Anio,2026,Fac_EstadoAFIP,"<>Anulada")/0.105 | G8: =SUMIFS(Fac_IVA105,Fac_Mes,6,Fac_Anio,2026,Fac_EstadoAFIP,"<>Anulada")/0.105 | H8: =SUMIFS(Fac_IVA105,Fac_Mes,7,Fac_Anio,2026,Fac_EstadoAFIP,"<>Anulada")/0.105 | I8: =SUMIFS(Fac_IVA105,Fac_Mes,8,Fac_Anio,2026,Fac_EstadoAFIP,"<>Anulada")/0.105 | J8: =SUMIFS(Fac_IVA105,Fac_Mes,9,Fac_Anio,2026,Fac_EstadoAFIP,"<>Anulada")/0.105 | K8: =SUMIFS(Fac_IVA105,Fac_Mes,10,Fac_Anio,2026,Fac_EstadoAFIP,"<>Anulada")/0.105 | L8: =SUMIFS(Fac_IVA105,Fac_Mes,11,Fac_Anio,2026,Fac_EstadoAFIP,"<>Anulada")/0.105 | M8: =SUMIFS(Fac_IVA105,Fac_Mes,12,Fac_Anio,2026,Fac_EstadoAFIP,"<>Anulada")/0.105 | N8: =SUM(B8:M8)
A9: No Gravado / Exento | B9: =SUMIFS(Fac_NoGrav,Fac_Mes,1,Fac_Anio,2026,Fac_EstadoAFIP,"<>Anulada") | C9: =SUMIFS(Fac_NoGrav,Fac_Mes,2,Fac_Anio,2026,Fac_EstadoAFIP,"<>Anulada") | D9: =SUMIFS(Fac_NoGrav,Fac_Mes,3,Fac_Anio,2026,Fac_EstadoAFIP,"<>Anulada") | E9: =SUMIFS(Fac_NoGrav,Fac_Mes,4,Fac_Anio,2026,Fac_EstadoAFIP,"<>Anulada") | F9: =SUMIFS(Fac_NoGrav,Fac_Mes,5,Fac_Anio,2026,Fac_EstadoAFIP,"<>Anulada") | G9: =SUMIFS(Fac_NoGrav,Fac_Mes,6,Fac_Anio,2026,Fac_EstadoAFIP,"<>Anulada") | H9: =SUMIFS(Fac_NoGrav,Fac_Mes,7,Fac_Anio,2026,Fac_EstadoAFIP,"<>Anulada") | I9: =SUMIFS(Fac_NoGrav,Fac_Mes,8,Fac_Anio,2026,Fac_EstadoAFIP,"<>Anulada") | J9: =SUMIFS(Fac_NoGrav,Fac_Mes,9,Fac_Anio,2026,Fac_EstadoAFIP,"<>Anulada") | K9: =SUMIFS(Fac_NoGrav,Fac_Mes,10,Fac_Anio,2026,Fac_EstadoAFIP,"<>Anulada") | L9: =SUMIFS(Fac_NoGrav,Fac_Mes,11,Fac_Anio,2026,Fac_EstadoAFIP,"<>Anulada") | M9: =SUMIFS(Fac_NoGrav,Fac_Mes,12,Fac_Anio,2026,Fac_EstadoAFIP,"<>Anulada") | N9: =SUM(B9:M9)
A10: Total Facturado (neto) | B10: =B7+B8+B9 | C10: =C7+C8+C9 | D10: =D7+D8+D9 | E10: =E7+E8+E9 | F10: =F7+F8+F9 | G10: =G7+G8+G9 | H10: =H7+H8+H9 | I10: =I7+I8+I9 | ... M10: =M7+M8+M9 | N10: =SUM(B10:M10)
A12: IVA Débito Fiscal
A13: IVA Débito 21% | B13: =B7*IVA_general | C13: =C7*IVA_general | D13: =D7*IVA_general | E13: =E7*IVA_general | F13: =F7*IVA_general | G13: =G7*IVA_general | H13: =H7*IVA_general | I13: =I7*IVA_general | ... M13: =M7*IVA_general | N13: =SUM(B13:M13)
A14: IVA Débito 10,5% | B14: =B8*IVA_reducida | C14: =C8*IVA_reducida | D14: =D8*IVA_reducida | E14: =E8*IVA_reducida | F14: =F8*IVA_reducida | G14: =G8*IVA_reducida | H14: =H8*IVA_reducida | I14: =I8*IVA_reducida | ... M14: =M8*IVA_reducida | N14: =SUM(B14:M14)
A15: Total IVA Débito | B15: =B13+B14 | C15: =C13+C14 | D15: =D13+D14 | E15: =E13+E14 | F15: =F13+F14 | G15: =G13+G14 | H15: =H13+H14 | I15: =I13+I14 | ... M15: =M13+M14 | N15: =SUM(B15:M15)
A17: IVA Crédito Fiscal
A18: % Crédito estimado (prorrateo) (Reglas) | B18: =Pct_credito | C18: =Pct_credito | D18: =Pct_credito | E18: =Pct_credito | F18: =Pct_credito | G18: =Pct_credito | H18: =Pct_credito | I18: =Pct_credito | ... M18: =Pct_credito
A19: IVA Crédito estimado (Débito × %) | B19: =B15*B18 | C19: =C15*C18 | D19: =D15*D18 | E19: =E15*E18 | F19: =F15*F18 | G19: =G15*G18 | H19: =H15*H18 | I19: =I15*I18 | ... M19: =M15*M18 | N19: =SUM(B19:M19)
A20: IVA Crédito real (cargar manual si tenés) | B20: 0 | C20: 0 | D20: 0 | E20: 0 | F20: 0 | G20: 0 | H20: 0 | I20: 0 | J20: 0 | K20: 0 | L20: 0 | M20: 0 | N20: =SUM(B20:M20)
A21: Total IVA Crédito (usa real si > 0, sino estimado) | B21: =IF(B20>0,B20,B19) | C21: =IF(C20>0,C20,C19) | D21: =IF(D20>0,D20,D19) | E21: =IF(E20>0,E20,E19) | F21: =IF(F20>0,F20,F19) | G21: =IF(G20>0,G20,G19) | H21: =IF(H20>0,H20,H19) | I21: =IF(I20>0,I20,I19) | ... M21: =IF(M20>0,M20,M19) | N21: =SUM(B21:M21)
A23: Liquidación
A24: Saldo Técnico (Débito - Crédito) | B24: =B15-B21 | C24: =C15-C21 | D24: =D15-D21 | E24: =E15-E21 | F24: =F15-F21 | G24: =G15-G21 | H24: =H15-H21 | I24: =I15-I21 | ... M24: =M15-M21 | N24: =SUM(B24:M24)
A25: (-) Saldo a favor anterior | B25: 0 | C25: 0 | D25: 0 | E25: 0 | F25: 0 | G25: 0 | H25: 0 | I25: 0 | J25: 0 | K25: 0 | L25: 0 | M25: 0 | N25: =SUM(B25:M25)
A26: (-) Retenciones IVA sufridas | B26: 0 | C26: 0 | D26: 0 | E26: 0 | F26: 0 | G26: 0 | H26: 0 | I26: 0 | J26: 0 | K26: 0 | L26: 0 | M26: 0 | N26: =SUM(B26:M26)
A27: (-) Percepciones IVA sufridas | B27: 0 | C27: 0 | D27: 0 | E27: 0 | F27: 0 | G27: 0 | H27: 0 | I27: 0 | J27: 0 | K27: 0 | L27: 0 | M27: 0 | N27: =SUM(B27:M27)
A28: Saldo del Período | B28: =B24-B25-B26-B27 | C28: =C24-C25-C26-C27 | D28: =D24-D25-D26-D27 | E28: =E24-E25-E26-E27 | F28: =F24-F25-F26-F27 | G28: =G24-G25-G26-G27 | H28: =H24-H25-H26-H27 | I28: =I24-I25-I26-I27 | ... M28: =M24-M25-M26-M27 | N28: =SUM(B28:M28)
A29: A favor (si saldo negativo) | B29: =MAX(0,-B28) | C29: =MAX(0,-C28) | D29: =MAX(0,-D28) | E29: =MAX(0,-E28) | F29: =MAX(0,-F28) | G29: =MAX(0,-G28) | H29: =MAX(0,-H28) | I29: =MAX(0,-I28) | ... M29: =MAX(0,-M28) | N29: =SUM(B29:M29)
A30: A pagar (si saldo positivo) | B30: =MAX(0,B28) | C30: =MAX(0,C28) | D30: =MAX(0,D28) | E30: =MAX(0,E28) | F30: =MAX(0,F28) | G30: =MAX(0,G28) | H30: =MAX(0,H28) | I30: =MAX(0,I28) | ... M30: =MAX(0,M28) | N30: =SUM(B30:M30)
A32: Vencimientos y pagos
A33: Vencimiento DDJJ + pago | B33: =DATE(2026,2,20) | C33: =DATE(2026,3,20) | D33: =DATE(2026,4,20) | E33: =DATE(2026,5,20) | F33: =DATE(2026,6,20) | G33: =DATE(2026,7,20) | H33: =DATE(2026,8,20) | I33: =DATE(2026,9,20) | J33: =DATE(2026,10,20) | K33: =DATE(2026,11,20) | L33: =DATE(2026,12,20) | M33: =DATE(2027,1,20)
A34: Fecha de pago efectivo

Sheet Detalle Tasa Cba
A1: GRIFF SALUD SA
A2: TASA COMERCIO E INDUSTRIA · Municipalidad de Córdoba
A3: Año 2026
A5: Concepto | B5: Ene | C5: Feb | D5: Mar | E5: Abr | F5: May | G5: Jun | H5: Jul | I5: Ago | J5: Sep | K5: Oct | L5: Nov | M5: Dic | N5: Total Año
A6: Alícuota aplicable
A7: Alícuota 2026 | B7: =Tasa_2026 | C7: =Tasa_2026 | D7: =Tasa_2026 | E7: =Tasa_2026 | F7: =Tasa_2026 | G7: =Tasa_2026 | H7: =Tasa_2026 | I7: =Tasa_2026 | ... M7: =Tasa_2026
A9: Liquidación mensual
A10: 1. Base Imponible (Facturación Cba) | B10: =Impuestos!B34 | C10: =Impuestos!C34 | D10: =Impuestos!D34 | E10: =Impuestos!E34 | F10: =Impuestos!F34 | G10: =Impuestos!G34 | H10: =Impuestos!H34 | I10: =Impuestos!I34 | ... M10: =Impuestos!M34 | N10: =SUM(B10:M10)
A11: 2. Impuesto Determinado (Base × Alícuota) | B11: =B10*B7 | C11: =C10*C7 | D11: =D10*D7 | E11: =E10*E7 | F11: =F10*F7 | G11: =G10*G7 | H11: =H10*H7 | I11: =I10*I7 | ... M11: =M10*M7 | N11: =SUM(B11:M11)
A12: 3. (-) Retenciones | B12: 0 | C12: 0 | D12: 0 | E12: 0 | F12: 0 | G12: 0 | H12: 0 | I12: 0 | J12: 0 | K12: 0 | L12: 0 | M12: 0 | N12: =SUM(B12:M12)
A13: 4. (-) Recaudaciones | B13: 0 | C13: 0 | D13: 0 | E13: 0 | F13: 0 | G13: 0 | H13: 0 | I13: 0 | J13: 0 | K13: 0 | L13: 0 | M13: 0 | N13: =SUM(B13:M13)
A14: 5. (-) Anticipos / Pagos a cuenta | B14: 0 | C14: 0 | D14: 0 | E14: 0 | F14: 0 | G14: 0 | H14: 0 | I14: 0 | J14: 0 | K14: 0 | L14: 0 | M14: 0 | N14: =SUM(B14:M14)
A15: 6. A pagar (estimado) | B15: =MAX(0,B11-B12-B13-B14) | C15: =MAX(0,C11-C12-C13-C14) | D15: =MAX(0,D11-D12-D13-D14) | E15: =MAX(0,E11-E12-E13-E14) | F15: =MAX(0,F11-F12-F13-F14) | G15: =MAX(0,G11-G12-G13-G14) | H15: =MAX(0,H11-H12-H13-H14) | I15: =MAX(0,I11-I12-I13-I14) | ... M15: =MAX(0,M11-M12-M13-M14) | N15: =SUM(B15:M15)
A16: 7. (+) Intereses | B16: 0 | C16: 0 | D16: 0 | E16: 0 | F16: 0 | G16: 0 | H16: 0 | I16: 0 | J16: 0 | K16: 0 | L16: 0 | M16: 0 | N16: =SUM(B16:M16)
A17: 8. Total a pagar (con intereses) | B17: =B15+B16 | C17: =C15+C16 | D17: =D15+D16 | E17: =E15+E16 | F17: =F15+F16 | G17: =G15+G16 | H17: =H15+H16 | I17: =I15+I16 | ... M17: =M15+M16 | N17: =SUM(B17:M17)
A19: Vencimientos y pagos
A20: Vencimiento (15 del mes siguiente) | B20: =DATE(2026,2,15) | C20: =DATE(2026,3,15) | D20: =DATE(2026,4,15) | E20: =DATE(2026,5,15) | F20: =DATE(2026,6,15) | G20: =DATE(2026,7,15) | H20: =DATE(2026,8,15) | I20: =DATE(2026,9,15) | J20: =DATE(2026,10,15) | K20: =DATE(2026,11,15) | L20: =DATE(2026,12,15) | M20: =DATE(2027,1,15)
A21: Fecha de pago
A22: Fecha de pago Anticipo
A24: ℹ️ Las celdas azules son inputs - cargá retenciones, recaudaciones, anticipos y fechas de pago al recibir los certificados.

Sheet Detalle IIBB CABA
A1: GRIFF SALUD SA
A2: INGRESOS BRUTOS - CONVENIO MULTILATERAL · 901 - CABA
A3: Año 2026
A5: Concepto | B5: Ene | C5: Feb | D5: Mar | E5: Abr | F5: May | G5: Jun | H5: Jul | I5: Ago | J5: Sep | K5: Oct | L5: Nov | M5: Dic | N5: Total Año
A6: Coeficiente Unificado
A7: Coeficiente Unificado | B7: =Coef_CABA | C7: =Coef_CABA | D7: =Coef_CABA | E7: =Coef_CABA | F7: =Coef_CABA | G7: =Coef_CABA | H7: =Coef_CABA | I7: =Coef_CABA | ... M7: =Coef_CABA
A9: Bases Imponibles TOTALES (toda la actividad)
A10: 702010 - Servicios Gerenciamiento (total) | B10: =Impuestos!B5 | C10: =Impuestos!C5 | D10: =Impuestos!D5 | E10: =Impuestos!E5 | F10: =Impuestos!F5 | G10: =Impuestos!G5 | H10: =Impuestos!H5 | I10: =Impuestos!I5 | ... M10: =Impuestos!M5 | N10: =SUM(B10:M10)
A11: 651110 - Servicios Seguros (total) | B11: =Impuestos!B6 | C11: =Impuestos!C6 | D11: =Impuestos!D6 | E11: =Impuestos!E6 | F11: =Impuestos!F6 | G11: =Impuestos!G6 | H11: =Impuestos!H6 | I11: =Impuestos!I6 | ... M11: =Impuestos!M6 | N11: =SUM(B11:M11)
A13: Bases Imponibles DISTRIBUIDAS a CABA (× coef)
A14: 702010 - Servicios Gerenciamiento | B14: =Impuestos!B16 | C14: =Impuestos!C16 | D14: =Impuestos!D16 | E14: =Impuestos!E16 | F14: =Impuestos!F16 | G14: =Impuestos!G16 | H14: =Impuestos!H16 | I14: =Impuestos!I16 | ... M14: =Impuestos!M16 | N14: =SUM(B14:M14)
A15: 651110 - Servicios Seguros | B15: =Impuestos!B17 | C15: =Impuestos!C17 | D15: =Impuestos!D17 | E15: =Impuestos!E17 | F15: =Impuestos!F17 | G15: =Impuestos!G17 | H15: =Impuestos!H17 | I15: =Impuestos!I17 | ... M15: =Impuestos!M17 | N15: =SUM(B15:M15)
A16: TOTAL Base Imponible Jurisdiccional | B16: =B14+B15 | C16: =C14+C15 | D16: =D14+D15 | E16: =E14+E15 | F16: =F14+F15 | G16: =G14+G15 | H16: =H14+H15 | I16: =I14+I15 | ... M16: =M14+M15 | N16: =SUM(B16:M16)
A17: CONTROL (Total Jurisdiccional vs Total × Coef) | B17: =ROUND(B16-(B10+B11)*Coef_CABA,2) | C17: =ROUND(C16-(C10+C11)*Coef_CABA,2) | D17: =ROUND(D16-(D10+D11)*Coef_CABA,2) | E17: =ROUND(E16-(E10+E11)*Coef_CABA,2) | F17: =ROUND(F16-(F10+F11)*Coef_CABA,2) | G17: =ROUND(G16-(G10+G11)*Coef_CABA,2) | H17: =ROUND(H16-(H10+H11)*Coef_CABA,2) | I17: =ROUND(I16-(I10+I11)*Coef_CABA,2) | ... M17: =ROUND(M16-(M10+M11)*Coef_CABA,2)
A19: Alícuotas
A20: 702010 - Servicios Gerenciamiento | B20: =Alic_702_CABA | C20: =Alic_702_CABA | D20: =Alic_702_CABA | E20: =Alic_702_CABA | F20: =Alic_702_CABA | G20: =Alic_702_CABA | H20: =Alic_702_CABA | I20: =Alic_702_CABA | ... M20: =Alic_702_CABA
A21: 651110 - Servicios Seguros | B21: =Alic_651_CABA | C21: =Alic_651_CABA | D21: =Alic_651_CABA | E21: =Alic_651_CABA | F21: =Alic_651_CABA | G21: =Alic_651_CABA | H21: =Alic_651_CABA | I21: =Alic_651_CABA | ... M21: =Alic_651_CABA
A23: Impuesto Determinado
A24: Impuesto 702010 (= base × alícuota) | B24: =B14*B20 | C24: =C14*C20 | D24: =D14*D20 | E24: =E14*E20 | F24: =F14*F20 | G24: =G14*G20 | H24: =H14*H20 | I24: =I14*I20 | ... M24: =M14*M20 | N24: =SUM(B24:M24)
A25: Impuesto 651110 (= base × alícuota) | B25: =B15*B21 | C25: =C15*C21 | D25: =D15*D21 | E25: =E15*E21 | F25: =F15*F21 | G25: =G15*G21 | H25: =H15*H21 | I25: =I15*I21 | ... M25: =M15*M21 | N25: =SUM(B25:M25)
A26: Sub-total Impuesto | B26: =B24+B25 | C26: =C24+C25 | D26: =D24+D25 | E26: =E24+E25 | F26: =F24+F25 | G26: =G24+G25 | H26: =H24+H25 | I26: =I24+I25 | ... M26: =M24+M25 | N26: =SUM(B26:M26)
A27: (+) Adicional Fofise | B27: 0 | C27: 0 | D27: 0 | E27: 0 | F27: 0 | G27: 0 | H27: 0 | I27: 0 | J27: 0 | K27: 0 | L27: 0 | M27: 0 | N27: =SUM(B27:M27)
A28: (+) Adicional FFOI | B28: 0 | C28: 0 | D28: 0 | E28: 0 | F28: 0 | G28: 0 | H28: 0 | I28: 0 | J28: 0 | K28: 0 | L28: 0 | M28: 0 | N28: =SUM(B28:M28)
A29: Total Determinado | B29: =B26+B27+B28 | C29: =C26+C27+C28 | D29: =D26+D27+D28 | E29: =E26+E27+E28 | F29: =F26+F27+F28 | G29: =G26+G27+G28 | H29: =H26+H27+H28 | I29: =I26+I27+I28 | ... M29: =M26+M27+M28 | N29: =SUM(B29:M29)
A31: Deducciones
A32: (-) Recaudaciones | B32: 0 | C32: 0 | D32: 0 | E32: 0 | F32: 0 | G32: 0 | H32: 0 | I32: 0 | J32: 0 | K32: 0 | L32: 0 | M32: 0 | N32: =SUM(B32:M32)
A33: (-) Retenciones | B33: 0 | C33: 0 | D33: 0 | E33: 0 | F33: 0 | G33: 0 | H33: 0 | I33: 0 | J33: 0 | K33: 0 | L33: 0 | M33: 0 | N33: =SUM(B33:M33)
A34: (-) Percepciones | B34: 0 | C34: 0 | D34: 0 | E34: 0 | F34: 0 | G34: 0 | H34: 0 | I34: 0 | J34: 0 | K34: 0 | L34: 0 | M34: 0 | N34: =SUM(B34:M34)
A35: (-) Saldo a favor anterior | B35: 0 | C35: 0 | D35: 0 | E35: 0 | F35: 0 | G35: 0 | H35: 0 | I35: 0 | J35: 0 | K35: 0 | L35: 0 | M35: 0 | N35: =SUM(B35:M35)
A36: (-) Pagos a cuenta | B36: 0 | C36: 0 | D36: 0 | E36: 0 | F36: 0 | G36: 0 | H36: 0 | I36: 0 | J36: 0 | K36: 0 | L36: 0 | M36: 0 | N36: =SUM(B36:M36)
A38: Resultado
A39: Saldo Período | B39: =B29-B32-B33-B34-B35-B36 | C39: =C29-C32-C33-C34-C35-C36 | D39: =D29-D32-D33-D34-D35-D36 | E39: =E29-E32-E33-E34-E35-E36 | F39: =F29-F32-F33-F34-F35-F36 | G39: =G29-G32-G33-G34-G35-G36 | H39: =H29-H32-H33-H34-H35-H36 | I39: =I29-I32-I33-I34-I35-I36 | ... M39: =M29-M32-M33-M34-M35-M36 | N39: =SUM(B39:M39)
A40: A favor (si saldo negativo) | B40: =MAX(0,-B39) | C40: =MAX(0,-C39) | D40: =MAX(0,-D39) | E40: =MAX(0,-E39) | F40: =MAX(0,-F39) | G40: =MAX(0,-G39) | H40: =MAX(0,-H39) | I40: =MAX(0,-I39) | ... M40: =MAX(0,-M39) | N40: =SUM(B40:M40)
A41: A pagar (si saldo positivo) | B41: =MAX(0,B39) | C41: =MAX(0,C39) | D41: =MAX(0,D39) | E41: =MAX(0,E39) | F41: =MAX(0,F39) | G41: =MAX(0,G39) | H41: =MAX(0,H39) | I41: =MAX(0,I39) | ... M41: =MAX(0,M39) | N41: =SUM(B41:M41)
A43: Vencimientos y pagos
A44: Vencimiento (cronograma CM) | B44: =DATE(2026,2,18) | C44: =DATE(2026,3,18) | D44: =DATE(2026,4,18) | E44: =DATE(2026,5,18) | F44: =DATE(2026,6,18) | G44: =DATE(2026,7,18) | H44: =DATE(2026,8,18) | I44: =DATE(2026,9,18) | J44: =DATE(2026,10,18) | K44: =DATE(2026,11,18) | L44: =DATE(2026,12,18) | M44: =DATE(2027,1,18)
A45: Fecha de pago
A47: ℹ️ Celdas azules = inputs (cargá retenciones, percepciones, saldo a favor anterior, pagos a cuenta y fechas de pago).

Sheet Detalle IIBB Cba
A1: GRIFF SALUD SA
A2: INGRESOS BRUTOS - CONVENIO MULTILATERAL · 904 - Cordoba
A3: Año 2026
A5: Concepto | B5: Ene | C5: Feb | D5: Mar | E5: Abr | F5: May | G5: Jun | H5: Jul | I5: Ago | J5: Sep | K5: Oct | L5: Nov | M5: Dic | N5: Total Año
A6: Coeficiente Unificado
A7: Coeficiente Unificado | B7: =Coef_Cba | C7: =Coef_Cba | D7: =Coef_Cba | E7: =Coef_Cba | F7: =Coef_Cba | G7: =Coef_Cba | H7: =Coef_Cba | I7: =Coef_Cba | ... M7: =Coef_Cba
A9: Bases Imponibles TOTALES (toda la actividad)
A10: 702010 - Servicios Gerenciamiento (total) | B10: =Impuestos!B5 | C10: =Impuestos!C5 | D10: =Impuestos!D5 | E10: =Impuestos!E5 | F10: =Impuestos!F5 | G10: =Impuestos!G5 | H10: =Impuestos!H5 | I10: =Impuestos!I5 | ... M10: =Impuestos!M5 | N10: =SUM(B10:M10)
A11: 651110 - Servicios Seguros (total) | B11: =Impuestos!B6 | C11: =Impuestos!C6 | D11: =Impuestos!D6 | E11: =Impuestos!E6 | F11: =Impuestos!F6 | G11: =Impuestos!G6 | H11: =Impuestos!H6 | I11: =Impuestos!I6 | ... M11: =Impuestos!M6 | N11: =SUM(B11:M11)
A13: Bases Imponibles DISTRIBUIDAS a Cordoba (× coef)
A14: 702010 - Servicios Gerenciamiento | B14: =Impuestos!B25 | C14: =Impuestos!C25 | D14: =Impuestos!D25 | E14: =Impuestos!E25 | F14: =Impuestos!F25 | G14: =Impuestos!G25 | H14: =Impuestos!H25 | I14: =Impuestos!I25 | ... M14: =Impuestos!M25 | N14: =SUM(B14:M14)
A15: 651110 - Servicios Seguros | B15: =Impuestos!B26 | C15: =Impuestos!C26 | D15: =Impuestos!D26 | E15: =Impuestos!E26 | F15: =Impuestos!F26 | G15: =Impuestos!G26 | H15: =Impuestos!H26 | I15: =Impuestos!I26 | ... M15: =Impuestos!M26 | N15: =SUM(B15:M15)
A16: TOTAL Base Imponible Jurisdiccional | B16: =B14+B15 | C16: =C14+C15 | D16: =D14+D15 | E16: =E14+E15 | F16: =F14+F15 | G16: =G14+G15 | H16: =H14+H15 | I16: =I14+I15 | ... M16: =M14+M15 | N16: =SUM(B16:M16)
A17: CONTROL (Total Jurisdiccional vs Total × Coef) | B17: =ROUND(B16-(B10+B11)*Coef_Cba,2) | C17: =ROUND(C16-(C10+C11)*Coef_Cba,2) | D17: =ROUND(D16-(D10+D11)*Coef_Cba,2) | E17: =ROUND(E16-(E10+E11)*Coef_Cba,2) | F17: =ROUND(F16-(F10+F11)*Coef_Cba,2) | G17: =ROUND(G16-(G10+G11)*Coef_Cba,2) | H17: =ROUND(H16-(H10+H11)*Coef_Cba,2) | I17: =ROUND(I16-(I10+I11)*Coef_Cba,2) | ... M17: =ROUND(M16-(M10+M11)*Coef_Cba,2)
A19: Alícuotas
A20: 702010 - Servicios Gerenciamiento | B20: =Alic_702_Cba | C20: =Alic_702_Cba | D20: =Alic_702_Cba | E20: =Alic_702_Cba | F20: =Alic_702_Cba | G20: =Alic_702_Cba | H20: =Alic_702_Cba | I20: =Alic_702_Cba | ... M20: =Alic_702_Cba
A21: 651110 - Servicios Seguros | B21: =Alic_651_Cba | C21: =Alic_651_Cba | D21: =Alic_651_Cba | E21: =Alic_651_Cba | F21: =Alic_651_Cba | G21: =Alic_651_Cba | H21: =Alic_651_Cba | I21: =Alic_651_Cba | ... M21: =Alic_651_Cba
A23: Impuesto Determinado
A24: Impuesto 702010 (= base × alícuota) | B24: =B14*B20 | C24: =C14*C20 | D24: =D14*D20 | E24: =E14*E20 | F24: =F14*F20 | G24: =G14*G20 | H24: =H14*H20 | I24: =I14*I20 | ... M24: =M14*M20 | N24: =SUM(B24:M24)
A25: Impuesto 651110 (= base × alícuota) | B25: =B15*B21 | C25: =C15*C21 | D25: =D15*D21 | E25: =E15*E21 | F25: =F15*F21 | G25: =G15*G21 | H25: =H15*H21 | I25: =I15*I21 | ... M25: =M15*M21 | N25: =SUM(B25:M25)
A26: Sub-total Impuesto | B26: =B24+B25 | C26: =C24+C25 | D26: =D24+D25 | E26: =E24+E25 | F26: =F24+F25 | G26: =G24+G25 | H26: =H24+H25 | I26: =I24+I25 | ... M26: =M24+M25 | N26: =SUM(B26:M26)
A27: (+) Adicional Fofise | B27: 0 | C27: 0 | D27: 0 | E27: 0 | F27: 0 | G27: 0 | H27: 0 | I27: 0 | J27: 0 | K27: 0 | L27: 0 | M27: 0 | N27: =SUM(B27:M27)
A28: (+) Adicional FFOI | B28: 0 | C28: 0 | D28: 0 | E28: 0 | F28: 0 | G28: 0 | H28: 0 | I28: 0 | J28: 0 | K28: 0 | L28: 0 | M28: 0 | N28: =SUM(B28:M28)
A29: Total Determinado | B29: =B26+B27+B28 | C29: =C26+C27+C28 | D29: =D26+D27+D28 | E29: =E26+E27+E28 | F29: =F26+F27+F28 | G29: =G26+G27+G28 | H29: =H26+H27+H28 | I29: =I26+I27+I28 | ... M29: =M26+M27+M28 | N29: =SUM(B29:M29)
A31: Deducciones
A32: (-) Recaudaciones | B32: 0 | C32: 0 | D32: 0 | E32: 0 | F32: 0 | G32: 0 | H32: 0 | I32: 0 | J32: 0 | K32: 0 | L32: 0 | M32: 0 | N32: =SUM(B32:M32)
A33: (-) Retenciones | B33: 0 | C33: 0 | D33: 0 | E33: 0 | F33: 0 | G33: 0 | H33: 0 | I33: 0 | J33: 0 | K33: 0 | L33: 0 | M33: 0 | N33: =SUM(B33:M33)
A34: (-) Percepciones | B34: 0 | C34: 0 | D34: 0 | E34: 0 | F34: 0 | G34: 0 | H34: 0 | I34: 0 | J34: 0 | K34: 0 | L34: 0 | M34: 0 | N34: =SUM(B34:M34)
A35: (-) Saldo a favor anterior | B35: 0 | C35: 0 | D35: 0 | E35: 0 | F35: 0 | G35: 0 | H35: 0 | I35: 0 | J35: 0 | K35: 0 | L35: 0 | M35: 0 | N35: =SUM(B35:M35)
A36: (-) Pagos a cuenta | B36: 0 | C36: 0 | D36: 0 | E36: 0 | F36: 0 | G36: 0 | H36: 0 | I36: 0 | J36: 0 | K36: 0 | L36: 0 | M36: 0 | N36: =SUM(B36:M36)
A38: Resultado
A39: Saldo Período | B39: =B29-B32-B33-B34-B35-B36 | C39: =C29-C32-C33-C34-C35-C36 | D39: =D29-D32-D33-D34-D35-D36 | E39: =E29-E32-E33-E34-E35-E36 | F39: =F29-F32-F33-F34-F35-F36 | G39: =G29-G32-G33-G34-G35-G36 | H39: =H29-H32-H33-H34-H35-H36 | I39: =I29-I32-I33-I34-I35-I36 | ... M39: =M29-M32-M33-M34-M35-M36 | N39: =SUM(B39:M39)
A40: A favor (si saldo negativo) | B40: =MAX(0,-B39) | C40: =MAX(0,-C39) | D40: =MAX(0,-D39) | E40: =MAX(0,-E39) | F40: =MAX(0,-F39) | G40: =MAX(0,-G39) | H40: =MAX(0,-H39) | I40: =MAX(0,-I39) | ... M40: =MAX(0,-M39) | N40: =SUM(B40:M40)
A41: A pagar (si saldo positivo) | B41: =MAX(0,B39) | C41: =MAX(0,C39) | D41: =MAX(0,D39) | E41: =MAX(0,E39) | F41: =MAX(0,F39) | G41: =MAX(0,G39) | H41: =MAX(0,H39) | I41: =MAX(0,I39) | ... M41: =MAX(0,M39) | N41: =SUM(B41:M41)
A43: Vencimientos y pagos
A44: Vencimiento (cronograma CM) | B44: =DATE(2026,2,18) | C44: =DATE(2026,3,18) | D44: =DATE(2026,4,18) | E44: =DATE(2026,5,18) | F44: =DATE(2026,6,18) | G44: =DATE(2026,7,18) | H44: =DATE(2026,8,18) | I44: =DATE(2026,9,18) | J44: =DATE(2026,10,18) | K44: =DATE(2026,11,18) | L44: =DATE(2026,12,18) | M44: =DATE(2027,1,18)
A45: Fecha de pago
A47: ℹ️ Celdas azules = inputs (cargá retenciones, percepciones, saldo a favor anterior, pagos a cuenta y fechas de pago).

Sheet Resumen
B2: RESUMEN EJECUTIVO 2026
B4: 📊 FACTURACIÓN AÑO 2026 | E4: 💰 COBRANZAS | H4: 📑 IMPUESTOS 2026 (estim.)
B5: Total facturado (Neto) | C5: =SUMIFS(Fac_Neto,Fac_Anio,2026,Fac_EstadoAFIP,"<>Anulada")+SUMIFS(Fac_NoGrav,Fac_Anio,2026,Fac_EstadoAFIP,"<>Anulada") | E5: Total cobrado | F5: =Cobranzas!L4 | H5: IVA total año | I5: =Impuestos!N40
B6: Total IVA débito | C6: =SUMIFS(Fac_IVA21,Fac_Anio,2026,Fac_EstadoAFIP,"<>Anulada")+SUMIFS(Fac_IVA105,Fac_Anio,2026,Fac_EstadoAFIP,"<>Anulada") | E6: Total pendiente | F6: =Cobranzas!L5 | H6: IIBB CABA total | I6: =Impuestos!N41
B7: Total facturado (con IVA) | C7: =SUMIFS(Fac_Total,Fac_Anio,2026,Fac_EstadoAFIP,"<>Anulada") | E7: Total vencido | F7: =Cobranzas!L6 | H7: IIBB Córdoba total | I7: =Impuestos!N42
B8: Cantidad de facturas emitidas | C8: =COUNTIFS(Fac_Anio,2026,Fac_EstadoAFIP,"<>Anulada") | E8: % Cobrado | F8: =Cobranzas!L7 | H8: Tasa Comercio Cba | I8: =Impuestos!N43
B9: Promedio mensual | C9: =IFERROR(C5/MAX(1,COUNTA(Facturacion!P:P)-1)*COUNTA(Facturacion!P:P)/12,0) | H9: TOTAL IMPUESTOS | I9: =Impuestos!N44
B12: 📅 Impuestos a pagar mes a mes
B13: Mes | C13: IVA | D13: IIBB CABA | E13: IIBB Cba | F13: Tasa Cba | G13: Total Mes | H13: Vence aprox.
B14: Ene | C14: =Impuestos!B40 | D14: =Impuestos!B41 | E14: =Impuestos!B42 | F14: =Impuestos!B43 | G14: =SUM(C14:F14) | H14: =DATE(2026,2,20)
B15: Feb | C15: =Impuestos!C40 | D15: =Impuestos!C41 | E15: =Impuestos!C42 | F15: =Impuestos!C43 | G15: =SUM(C15:F15) | H15: =DATE(2026,3,20)
B16: Mar | C16: =Impuestos!D40 | D16: =Impuestos!D41 | E16: =Impuestos!D42 | F16: =Impuestos!D43 | G16: =SUM(C16:F16) | H16: =DATE(2026,4,20)
B17: Abr | C17: =Impuestos!E40 | D17: =Impuestos!E41 | E17: =Impuestos!E42 | F17: =Impuestos!E43 | G17: =SUM(C17:F17) | H17: =DATE(2026,5,20)
B18: May | C18: =Impuestos!F40 | D18: =Impuestos!F41 | E18: =Impuestos!F42 | F18: =Impuestos!F43 | G18: =SUM(C18:F18) | H18: =DATE(2026,6,20)
B19: Jun | C19: =Impuestos!G40 | D19: =Impuestos!G41 | E19: =Impuestos!G42 | F19: =Impuestos!G43 | G19: =SUM(C19:F19) | H19: =DATE(2026,7,20)
B20: Jul | C20: =Impuestos!H40 | D20: =Impuestos!H41 | E20: =Impuestos!H42 | F20: =Impuestos!H43 | G20: =SUM(C20:F20) | H20: =DATE(2026,8,20)
B21: Ago | C21: =Impuestos!I40 | D21: =Impuestos!I41 | E21: =Impuestos!I42 | F21: =Impuestos!I43 | G21: =SUM(C21:F21) | H21: =DATE(2026,9,20)
B22: Sep | C22: =Impuestos!J40 | D22: =Impuestos!J41 | E22: =Impuestos!J42 | F22: =Impuestos!J43 | G22: =SUM(C22:F22) | H22: =DATE(2026,10,20)
B23: Oct | C23: =Impuestos!K40 | D23: =Impuestos!K41 | E23: =Impuestos!K42 | F23: =Impuestos!K43 | G23: =SUM(C23:F23) | H23: =DATE(2026,11,20)
B24: Nov | C24: =Impuestos!L40 | D24: =Impuestos!L41 | E24: =Impuestos!L42 | F24: =Impuestos!L43 | G24: =SUM(C24:F24) | H24: =DATE(2026,12,20)
B25: Dic | C25: =Impuestos!M40 | D25: =Impuestos!M41 | E25: =Impuestos!M42 | F25: =Impuestos!M43 | G25: =SUM(C25:F25) | H25: =DATE(2027,1,20)
B26: TOTAL | C26: =SUM(C14:C25) | D26: =SUM(D14:D25) | E26: =SUM(E14:E25) | F26: =SUM(F14:F25) | G26: =SUM(G14:G25)
