Workbook

Sheet INSTRUCCIONES
B2: PLANILLA MAESTRA DE PRESTADORES
B3: Como usar esta planilla - GRIFF SALUD
B5: QUE ES | C5: Una sola tabla con TODAS las facturas de prestadores. Cada fila es una factura (o una cuota). La columna ESTADO indica en que etapa esta. Los 4 tableros leen de aca.
B7: EL CICLO DE VIDA
B8: 1. PENDIENTE | C8: La factura llego pero todavia no se audito. Se completan los datos de identificacion y el TOTAL.
B9: 2. AUDITADA | C9: Ya pasaron auditoria medica (DEBITO_MEDICO) y facturista (DEBITO_ADMINISTRATIVO). El A_PAGAR quedo firme.
B10: 3. PROYECTADA | C10: Se le asigno una FECHA_PAGO_PROYECTADA. Es un estimativo, se puede mover. Flujo Bancario la cuenta como cheque a emitir.
B11: 4. EMITIDA | C11: Ya se genero el cheque / OP / transferencia. Se cargan NRO_CHEQUE o NRO_OP y FECHA_EMISION_PAGO.
B12: 5. PAGADA | C12: El cheque se deposito o la transferencia se ejecuto. Se carga FECHA_PAGO_REAL.
B14: COMO SE COMPLETA
B15: Columnas fondo gris | C15: Son CALCULADAS (A_PAGAR, FECHA_PAGO_SUGERIDA, KPIs). No se tocan: se llenan solas.
B16: Columnas con lista | C16: TIPO_COMPROBANTE, TIPO_PRESTACION, OBRA_SOCIAL, ESTADO, ETAPA_AUDITORIA, METODO_PAGO y ESTADO_CHEQUE_BANCO tienen lista desplegable.
B17: Filas amarillas | C17: Son 2 filas de EJEMPLO. Borralas antes de cargar datos reales.
B18: Celda K1 (amarilla) | C18: Escribir el periodo de la planilla, formato MM-AAAA (ej. 03-2026).
B20: BLOQUES DE COLUMNAS
B21: IDENTIFICACION (azul) | C21: PRESTADOR, CUIT, TIPO_COMPROBANTE (FAC/NC/ND), NUMERO_COMPROBANTE, FECHA, PERIODO, TIPO_PRESTACION, OBRA_SOCIAL, PLAZO.
B22: MONTOS (verde) | C22: TOTAL_COMPROBANTE lo carga quien arma la planilla. DEBITO_MEDICO lo carga la medica auditora. DEBITO_ADMINISTRATIVO lo carga la facturista. A_PAGAR se calcula solo.
B23: CICLO (violeta) | C23: ESTADO, ETAPA_AUDITORIA y METODO_PAGO.
B24: HITOS (ambar) | C24: Las 4 fechas del circuito de auditoria. Cada persona anota la fecha cuando recibe / entrega la factura. De aca salen los KPIs.
B25: PROYECCION (lila) | C25: FECHA_PAGO_SUGERIDA = FECHA + PLAZO (calculada). FECHA_PAGO_PROYECTADA es editable. MONTO_PROYECTADO: el monto de esa cuota.
B26: EMISION (azul claro) | C26: NRO_OP, NRO_CHEQUE, FECHA_EMISION_PAGO, BANCO_EMISOR. Varias se autocompletan al cruzar con Galicia / Colppy.
B27: PAGO (gris) | C27: FECHA_PAGO_REAL y ESTADO_CHEQUE_BANCO (lo que dice Galicia).
B28: KPI (naranja) | C28: 6 indicadores de tiempo, todos calculados. Miden cuantos dias tarda cada etapa del proceso.
B29: SEGUIMIENTO (gris) | C29: USUARIO_MODIFICO, FECHA_ULTIMA_MODIFICACION y NOTAS.
B31: CUOTAS MULTIPLES | C31: Si una factura se paga en varias cuotas: una fila por cuota. Todas con el mismo NUMERO_COMPROBANTE, distinto MONTO_PROYECTADO y FECHA_PAGO_PROYECTADA. La columna NRO_CUOTA muestra 1 de 2, 2 de 2, etc.
B33: KPIs DEL PROCESO
B34: KPI_DEMORA_A_AUDITORIA | C34: Dias desde que llego la doc hasta que entro a auditoria medica.
B35: KPI_DIAS_AUD_MEDICA | C35: Dias que la factura estuvo en la medica auditora.
B36: KPI_DIAS_FACTURISTA | C36: Dias que la factura estuvo en la facturista.
B37: KPI_LEADTIME_AUDITORIA | C37: Dias totales de auditoria: recepcion hasta fin auditoria.
B38: KPI_DEMORA_AUD_A_PAGO | C38: Dias entre fin de auditoria y emision del pago.
B39: KPI_LEADTIME_TOTAL | C39: Dias totales: recepcion hasta pago real.

Sheet PANEL
B2: PANEL DE CONTROL
B3: Se actualiza solo a partir de la hoja PRESTADORES
B5: FACTURAS POR ESTADO | F5: MONTO A_PAGAR POR OBRA SOCIAL
B6: ESTADO | C6: CANTIDAD | D6: MONTO A_PAGAR | F6: OBRA SOCIAL | G6: CANTIDAD | H6: MONTO A_PAGAR
B7: PENDIENTE | C7: =COUNTIF(PRESTADORES!$O$4:$O$503,"PENDIENTE") -> 0 | D7: =SUMIF(PRESTADORES!$O$4:$O$503,"PENDIENTE",PRESTADORES!$N$4:$N$503) -> 0 | F7: OSPEVIC | G7: =COUNTIF(PRESTADORES!$I$4:$I$503,"OSPEVIC") -> 92 | H7: =SUMIF(PRESTADORES!$I$4:$I$503,"OSPEVIC",PRESTADORES!$N$4:$N$503) -> 1.945367e+08
B8: AUDITADA | C8: =COUNTIF(PRESTADORES!$O$4:$O$503,"AUDITADA") -> 211 | D8: =SUMIF(PRESTADORES!$O$4:$O$503,"AUDITADA",PRESTADORES!$N$4:$N$503) -> 2.7250785e+08 | F8: OSPIF | G8: =COUNTIF(PRESTADORES!$I$4:$I$503,"OSPIF") -> 64 | H8: =SUMIF(PRESTADORES!$I$4:$I$503,"OSPIF",PRESTADORES!$N$4:$N$503) -> 53726268
B9: PROYECTADA | C9: =COUNTIF(PRESTADORES!$O$4:$O$503,"PROYECTADA") -> 0 | D9: =SUMIF(PRESTADORES!$O$4:$O$503,"PROYECTADA",PRESTADORES!$N$4:$N$503) -> 0 | F9: OSPLYFC | G9: =COUNTIF(PRESTADORES!$I$4:$I$503,"OSPLYFC") -> 36 | H9: =SUMIF(PRESTADORES!$I$4:$I$503,"OSPLYFC",PRESTADORES!$N$4:$N$503) -> 13977107
B10: EMITIDA | C10: =COUNTIF(PRESTADORES!$O$4:$O$503,"EMITIDA") -> 0 | D10: =SUMIF(PRESTADORES!$O$4:$O$503,"EMITIDA",PRESTADORES!$N$4:$N$503) -> 0 | F10: OSPM | G10: =COUNTIF(PRESTADORES!$I$4:$I$503,"OSPM") -> 4 | H10: =SUMIF(PRESTADORES!$I$4:$I$503,"OSPM",PRESTADORES!$N$4:$N$503) -> 1729983.5
B11: PAGADA | C11: =COUNTIF(PRESTADORES!$O$4:$O$503,"PAGADA") -> 0 | D11: =SUMIF(PRESTADORES!$O$4:$O$503,"PAGADA",PRESTADORES!$N$4:$N$503) -> 0 | F11: OSSURRBAC | G11: =COUNTIF(PRESTADORES!$I$4:$I$503,"OSSURRBAC") -> 15 | H11: =SUMIF(PRESTADORES!$I$4:$I$503,"OSSURRBAC",PRESTADORES!$N$4:$N$503) -> 8537787.1
B12: TOTAL | C12: =SUM(C7:C11) -> 211 | D12: =SUM(D7:D11) -> 2.7250785e+08 | F12: AMSURRBAC | G12: =COUNTIF(PRESTADORES!$I$4:$I$503,"AMSURRBAC") -> 0 | H12: =SUMIF(PRESTADORES!$I$4:$I$503,"AMSURRBAC",PRESTADORES!$N$4:$N$503) -> 0
F13: UOM | G13: =COUNTIF(PRESTADORES!$I$4:$I$503,"UOM") -> 0 | H13: =SUMIF(PRESTADORES!$I$4:$I$503,"UOM",PRESTADORES!$N$4:$N$503) -> 0
B14: FACTURAS EN AUDITORIA (sub-etapa) | F14: SIN ASIGNACION | G14: =COUNTIF(PRESTADORES!$I$4:$I$503,"SIN ASIGNACION") -> 0 | H14: =SUMIF(PRESTADORES!$I$4:$I$503,"SIN ASIGNACION",PRESTADORES!$N$4:$N$503) -> 0
B15: ETAPA_AUDITORIA | C15: CANTIDAD | F15: TOTAL | G15: =SUM(G7:G14) -> 211 | H15: =SUM(H7:H14) -> 2.7250785e+08
B16: RECIBIDA | C16: =COUNTIF(PRESTADORES!$P$4:$P$503,"RECIBIDA") -> 0
B17: EN_AUD_MEDICA | C17: =COUNTIF(PRESTADORES!$P$4:$P$503,"EN_AUD_MEDICA") -> 0
B18: EN_FACTURISTA | C18: =COUNTIF(PRESTADORES!$P$4:$P$503,"EN_FACTURISTA") -> 0
B19: AUDITADA | C19: =COUNTIF(PRESTADORES!$P$4:$P$503,"AUDITADA") -> 211
B21: KPIs PROMEDIO (dias)
B22: INDICADOR | C22: PROMEDIO DIAS
B23: Demora a auditoria | C23: =IFERROR(AVERAGE(PRESTADORES!$AF$4:$AF$503),"-") -> -
B24: Dias en aud. medica | C24: =IFERROR(AVERAGE(PRESTADORES!$AG$4:$AG$503),"-") -> -
B25: Dias en facturista | C25: =IFERROR(AVERAGE(PRESTADORES!$AH$4:$AH$503),"-") -> -
B26: Lead time auditoria | C26: =IFERROR(AVERAGE(PRESTADORES!$AI$4:$AI$503),"-") -> -
B27: Demora aud. a pago | C27: =IFERROR(AVERAGE(PRESTADORES!$AJ$4:$AJ$503),"-") -> -
B28: Lead time total | C28: =IFERROR(AVERAGE(PRESTADORES!$AK$4:$AK$503),"-") -> -

Sheet PRESTADORES
A1: PLANILLA MAESTRA DE PRESTADORES - GRIFF SALUD | J1: Periodo: | K1: 02-2026
A3: ID | B3: PRESTADOR | C3: CUIT | D3: TIPO_COMPROBANTE | E3: NUMERO_COMPROBANTE | F3: FECHA_COMPROBANTE | G3: PERIODO_PRESTACION | H3: TIPO_PRESTACION | I3: OBRA_SOCIAL | J3: PLAZO | K3: TOTAL_COMPROBANTE | L3: DEBITO_ADMINISTRATIVO | M3: DEBITO_MEDICO | N3: A_PAGAR | O3: ESTADO | P3: ETAPA_AUDITORIA | Q3: METODO_PAGO | R3: FECHA_RECEPCION | S3: FECHA_A_AUD_MEDICA | T3: FECHA_A_FACTURISTA | U3: FECHA_FIN_AUDITORIA | V3: NRO_CUOTA | W3: FECHA_PAGO_SUGERIDA | X3: FECHA_PAGO_PROYECTADA | Y3: MONTO_PROYECTADO | Z3: NRO_OP | AA3: NRO_CHEQUE | AB3: FECHA_EMISION_PAGO | AC3: BANCO_EMISOR | AD3: FECHA_PAGO_REAL | AE3: ESTADO_CHEQUE_BANCO | AF3: KPI_DEMORA_A_AUDITORIA | AG3: KPI_DIAS_AUD_MEDICA | AH3: KPI_DIAS_FACTURISTA | AI3: KPI_LEADTIME_AUDITORIA | AJ3: KPI_DEMORA_AUD_A_PAGO | AK3: KPI_LEADTIME_TOTAL | AL3: USUARIO_MODIFICO | AM3: FECHA_ULTIMA_MODIFICACION | AN3: NOTAS
A4: =IF($B4="","",ROW()-3) -> 1 | B4: AMPARAR S.R.L | C4: 30708686499 | D4: FAC | E4: 00008-00001805 | F4: 46083 | H4: CAPITAS | I4: OSSURRBAC | J4: 30 | K4: 314997.76 | L4: 0 | M4: 0 | N4: =IF($K4="","",$K4-N($L4)-N($M4)) -> 314997.76 | O4: AUDITADA | P4: AUDITADA | V4: 1 de 1 | W4: =IF(OR($F4="",$J4=""),"",$F4+$J4) -> 46113 | AF4: =IF(OR($R4="",$S4=""),"",$S4-$R4) | AG4: =IF(OR($S4="",$T4=""),"",$T4-$S4) | AH4: =IF(OR($T4="",$U4=""),"",$U4-$T4) | AI4: =IF(OR($R4="",$U4=""),"",$U4-$R4) | AJ4: =IF(OR($U4="",$AB4=""),"",$AB4-$U4) | AK4: =IF(OR($R4="",$AD4=""),"",$AD4-$R4) | AN4: Migrado (02-2026)
A5: =IF($B5="","",ROW()-3) -> 2 | B5: AMPARAR S.R.L | C5: 30708686499 | D5: FAC | E5: 00008-00001803 | F5: 46083 | H5: CAPITAS | I5: OSPLYFC | J5: 30 | K5: 726056.45 | L5: 0 | M5: 0 | N5: =IF($K5="","",$K5-N($L5)-N($M5)) -> 726056.45 | O5: AUDITADA | P5: AUDITADA | V5: 1 de 1 | W5: =IF(OR($F5="",$J5=""),"",$F5+$J5) -> 46113 | AF5: =IF(OR($R5="",$S5=""),"",$S5-$R5) | AG5: =IF(OR($S5="",$T5=""),"",$T5-$S5) | AH5: =IF(OR($T5="",$U5=""),"",$U5-$T5) | AI5: =IF(OR($R5="",$U5=""),"",$U5-$R5) | AJ5: =IF(OR($U5="",$AB5=""),"",$AB5-$U5) | AK5: =IF(OR($R5="",$AD5=""),"",$AD5-$R5) | AN5: Migrado (02-2026)
A6: =IF($B6="","",ROW()-3) -> 3 | B6: AMPARAR S.R.L | C6: 30708686499 | D6: FAC | E6: 00008-00001806 | F6: 46083 | H6: CAPITAS | I6: OSPIF | J6: 30 | K6: 2955934.5 | L6: 0 | M6: 0 | N6: =IF($K6="","",$K6-N($L6)-N($M6)) -> 2955934.5 | O6: AUDITADA | P6: AUDITADA | V6: 1 de 1 | W6: =IF(OR($F6="",$J6=""),"",$F6+$J6) -> 46113 | AF6: =IF(OR($R6="",$S6=""),"",$S6-$R6) | AG6: =IF(OR($S6="",$T6=""),"",$T6-$S6) | AH6: =IF(OR($T6="",$U6=""),"",$U6-$T6) | AI6: =IF(OR($R6="",$U6=""),"",$U6-$R6) | AJ6: =IF(OR($U6="",$AB6=""),"",$AB6-$U6) | AK6: =IF(OR($R6="",$AD6=""),"",$AD6-$R6) | AN6: Migrado (02-2026)
A7: =IF($B7="","",ROW()-3) -> 4 | B7: AMPARAR S.R.L | C7: 30708686499 | D7: FAC | E7: 00008-00001807 | F7: 46083 | H7: AMBULATORIO | I7: OSPEVIC | J7: 30 | K7: 14374.8 | L7: 0 | M7: 0 | N7: =IF($K7="","",$K7-N($L7)-N($M7)) -> 14374.8 | O7: AUDITADA | P7: AUDITADA | V7: 1 de 1 | W7: =IF(OR($F7="",$J7=""),"",$F7+$J7) -> 46113 | AF7: =IF(OR($R7="",$S7=""),"",$S7-$R7) | AG7: =IF(OR($S7="",$T7=""),"",$T7-$S7) | AH7: =IF(OR($T7="",$U7=""),"",$U7-$T7) | AI7: =IF(OR($R7="",$U7=""),"",$U7-$R7) | AJ7: =IF(OR($U7="",$AB7=""),"",$AB7-$U7) | AK7: =IF(OR($R7="",$AD7=""),"",$AD7-$R7) | AN7: Migrado (02-2026)
A8: =IF($B8="","",ROW()-3) -> 5 | B8: AMPARAR S.R.L | C8: 30708686499 | D8: FAC | E8: 00008-00001466 | F8: 46143 | H8: AMBULATORIO | I8: OSPEVIC | J8: 30 | K8: 14374.8 | L8: 2494.8 | M8: 0 | N8: =IF($K8="","",$K8-N($L8)-N($M8)) -> 11880 | O8: AUDITADA | P8: AUDITADA | V8: 1 de 1 | W8: =IF(OR($F8="",$J8=""),"",$F8+$J8) -> 46173 | AF8: =IF(OR($R8="",$S8=""),"",$S8-$R8) | AG8: =IF(OR($S8="",$T8=""),"",$T8-$S8) | AH8: =IF(OR($T8="",$U8=""),"",$U8-$T8) | AI8: =IF(OR($R8="",$U8=""),"",$U8-$R8) | AJ8: =IF(OR($U8="",$AB8=""),"",$AB8-$U8) | AK8: =IF(OR($R8="",$AD8=""),"",$AD8-$R8) | AN8: Migrado (02-2026)
A9: =IF($B9="","",ROW()-3) -> 6 | B9: AMPARAR S.R.L | C9: 30708686499 | D9: FAC | E9: 00008-00001824 | F9: 46083 | H9: TRASLADOS | I9: OSPEVIC | J9: 30 | K9: 1034649.6 | L9: 98600.81 | M9: 0 | N9: =IF($K9="","",$K9-N($L9)-N($M9)) -> 936048.76 | O9: AUDITADA | P9: AUDITADA | V9: 1 de 1 | W9: =IF(OR($F9="",$J9=""),"",$F9+$J9) -> 46113 | AF9: =IF(OR($R9="",$S9=""),"",$S9-$R9) | AG9: =IF(OR($S9="",$T9=""),"",$T9-$S9) | AH9: =IF(OR($T9="",$U9=""),"",$U9-$T9) | AI9: =IF(OR($R9="",$U9=""),"",$U9-$R9) | AJ9: =IF(OR($U9="",$AB9=""),"",$AB9-$U9) | AK9: =IF(OR($R9="",$AD9=""),"",$AD9-$R9) | AN9: Migrado (02-2026)
A10: =IF($B10="","",ROW()-3) -> 7 | B10: AMPARAR S.R.L | C10: 30708686499 | D10: FAC | E10: 00008-00001792 | F10: 46083 | H10: TRASLADOS | I10: OSPEVIC | J10: 30 | K10: 2028447.3 | L10: 562560.09 | M10: 0 | N10: =IF($K10="","",$K10-N($L10)-N($M10)) -> 1465887.2 | O10: AUDITADA | P10: AUDITADA | V10: 1 de 1 | W10: =IF(OR($F10="",$J10=""),"",$F10+$J10) -> 46113 | AF10: =IF(OR($R10="",$S10=""),"",$S10-$R10) | AG10: =IF(OR($S10="",$T10=""),"",$T10-$S10) | AH10: =IF(OR($T10="",$U10=""),"",$U10-$T10) | AI10: =IF(OR($R10="",$U10=""),"",$U10-$R10) | AJ10: =IF(OR($U10="",$AB10=""),"",$AB10-$U10) | AK10: =IF(OR($R10="",$AD10=""),"",$AD10-$R10) | AN10: Migrado (02-2026)
A11: =IF($B11="","",ROW()-3) -> 8 | B11: ASOCIACION DE BIOQUIMICOS DEL DEPARTAMENTO SAN MARTIN | C11: 30582058608 | D11: FAC | E11: 00005-00006083 | F11: 46087 | H11: AMBULATORIO | I11: OSPIF | J11: 30 | K11: 2993255.5 | L11: 2993255.5 | M11: 0 | N11: =IF($K11="","",$K11-N($L11)-N($M11)) -> 0 | O11: AUDITADA | P11: AUDITADA | V11: 1 de 1 | W11: =IF(OR($F11="",$J11=""),"",$F11+$J11) -> 46117 | AF11: =IF(OR($R11="",$S11=""),"",$S11-$R11) | AG11: =IF(OR($S11="",$T11=""),"",$T11-$S11) | AH11: =IF(OR($T11="",$U11=""),"",$U11-$T11) | AI11: =IF(OR($R11="",$U11=""),"",$U11-$R11) | AJ11: =IF(OR($U11="",$AB11=""),"",$AB11-$U11) | AK11: =IF(OR($R11="",$AD11=""),"",$AD11-$R11) | AN11: Migrado (02-2026)
A12: =IF($B12="","",ROW()-3) -> 9 | B12: ASOCIACION DE CLINICAS DEL NORTE DE LA PROVINCIA DE CORDOBA A C L I N O R | C12: 30678724447 | D12: FAC | E12: 00004-00018691 | F12: 46090 | H12: AMBULATORIO | I12: OSPLYFC | J12: 45 | K12: 113487.37 | L12: 8400 | M12: 0 | N12: =IF($K12="","",$K12-N($L12)-N($M12)) -> 105087.37 | O12: AUDITADA | P12: AUDITADA | V12: 1 de 1 | W12: =IF(OR($F12="",$J12=""),"",$F12+$J12) -> 46135 | AF12: =IF(OR($R12="",$S12=""),"",$S12-$R12) | AG12: =IF(OR($S12="",$T12=""),"",$T12-$S12) | AH12: =IF(OR($T12="",$U12=""),"",$U12-$T12) | AI12: =IF(OR($R12="",$U12=""),"",$U12-$R12) | AJ12: =IF(OR($U12="",$AB12=""),"",$AB12-$U12) | AK12: =IF(OR($R12="",$AD12=""),"",$AD12-$R12) | AN12: Migrado (02-2026)
A13: =IF($B13="","",ROW()-3) -> 10 | B13: ASOCIACION DE CLINICAS DEL NORTE DE LA PROVINCIA DE CORDOBA A C L I N O R | C13: 30678724447 | D13: FAC | E13: 00004-00018692 | F13: 46090 | H13: AMBULATORIO | I13: OSPIF | J13: 45 | K13: 1296612.8 | L13: 518860.75 | M13: 0 | N13: =IF($K13="","",$K13-N($L13)-N($M13)) -> 777752.09 | O13: AUDITADA | P13: AUDITADA | V13: 1 de 1 | W13: =IF(OR($F13="",$J13=""),"",$F13+$J13) -> 46135 | AF13: =IF(OR($R13="",$S13=""),"",$S13-$R13) | AG13: =IF(OR($S13="",$T13=""),"",$T13-$S13) | AH13: =IF(OR($T13="",$U13=""),"",$U13-$T13) | AI13: =IF(OR($R13="",$U13=""),"",$U13-$R13) | AJ13: =IF(OR($U13="",$AB13=""),"",$AB13-$U13) | AK13: =IF(OR($R13="",$AD13=""),"",$AD13-$R13) | AN13: Migrado (02-2026)
A14: =IF($B14="","",ROW()-3) -> 11 | B14: ASOCIACION DE CLINICAS DEL NORTE DE LA PROVINCIA DE CORDOBA A C L I N O R | C14: 30678724447 | D14: FAC | E14: 00004-00018694 | F14: 46090 | H14: AMBULATORIO | I14: OSPEVIC | J14: 45 | K14: 4854948.2 | L14: 247299.75 | M14: 0 | N14: =IF($K14="","",$K14-N($L14)-N($M14)) -> 4607648.5 | O14: AUDITADA | P14: AUDITADA | V14: 1 de 1 | W14: =IF(OR($F14="",$J14=""),"",$F14+$J14) -> 46135 | AF14: =IF(OR($R14="",$S14=""),"",$S14-$R14) | AG14: =IF(OR($S14="",$T14=""),"",$T14-$S14) | AH14: =IF(OR($T14="",$U14=""),"",$U14-$T14) | AI14: =IF(OR($R14="",$U14=""),"",$U14-$R14) | AJ14: =IF(OR($U14="",$AB14=""),"",$AB14-$U14) | AK14: =IF(OR($R14="",$AD14=""),"",$AD14-$R14) | AN14: Migrado (02-2026)
A15: =IF($B15="","",ROW()-3) -> 12 | B15: ASOCIACION DE CLINICAS DEL NORTE DE LA PROVINCIA DE CORDOBA A C L I N O R | C15: 30678724447 | D15: FAC | E15: 00004-00018693 | F15: 46090 | H15: AMBULATORIO | I15: OSSURRBAC | J15: 45 | K15: 125892.02 | L15: 5600 | M15: 0 | N15: =IF($K15="","",$K15-N($L15)-N($M15)) -> 120292.02 | O15: AUDITADA | P15: AUDITADA | V15: 1 de 1 | W15: =IF(OR($F15="",$J15=""),"",$F15+$J15) -> 46135 | AF15: =IF(OR($R15="",$S15=""),"",$S15-$R15) | AG15: =IF(OR($S15="",$T15=""),"",$T15-$S15) | AH15: =IF(OR($T15="",$U15=""),"",$U15-$T15) | AI15: =IF(OR($R15="",$U15=""),"",$U15-$R15) | AJ15: =IF(OR($U15="",$AB15=""),"",$AB15-$U15) | AK15: =IF(OR($R15="",$AD15=""),"",$AD15-$R15) | AN15: Migrado (02-2026)
... A49: =IF($B49="","",ROW()-3) -> 46 | B49: CLINICA FUSAVIM PRIVADA SRL | C49: 30708409185 | D49: FAC | E49: 6-4506 | F49: 46086 | H49: AMBULATORIO | I49: OSPEVIC | J49: 60 | K49: 92109.63 | L49: 0 | M49: 0 | N49: =IF($K49="","",$K49-N($L49)-N($M49)) -> 92109.63 | O49: AUDITADA | P49: AUDITADA | V49: 1 de 1 | W49: =IF(OR($F49="",$J49=""),"",$F49+$J49) -> 46146 | AF49: =IF(OR($R49="",$S49=""),"",$S49-$R49) | AG49: =IF(OR($S49="",$T49=""),"",$T49-$S49) | AH49: =IF(OR($T49="",$U49=""),"",$U49-$T49) | AI49: =IF(OR($R49="",$U49=""),"",$U49-$R49) | AJ49: =IF(OR($U49="",$AB49=""),"",$AB49-$U49) | AK49: =IF(OR($R49="",$AD49=""),"",$AD49-$R49) | AN49: Migrado (02-2026)
A50: =IF($B50="","",ROW()-3) -> 47 | B50: CLINICA MEDITERRANEA SALUD S A | C50: 30708069791 | D50: FAC | E50: 00003-00022326 | F50: 46083 | I50: OSPIF | K50: 132240 | L50: 0 | M50: 0 | N50: =IF($K50="","",$K50-N($L50)-N($M50)) -> 132240 | O50: AUDITADA | P50: AUDITADA | V50: 1 de 1 | W50: =IF(OR($F50="",$J50=""),"",$F50+$J50) | AF50: =IF(OR($R50="",$S50=""),"",$S50-$R50) | AG50: =IF(OR($S50="",$T50=""),"",$T50-$S50) | AH50: =IF(OR($T50="",$U50=""),"",$U50-$T50) | AI50: =IF(OR($R50="",$U50=""),"",$U50-$R50) | AJ50: =IF(OR($U50="",$AB50=""),"",$AB50-$U50) | AK50: =IF(OR($R50="",$AD50=""),"",$AD50-$R50) | AN50: Migrado (02-2026)
A51: =IF($B51="","",ROW()-3) -> 48 | B51: CLINICA MEDITERRANEA SALUD S A | C51: 30708069791 | D51: FAC | E51: 00003-00022327 | F51: 46083 | I51: OSPIF | K51: 92102 | L51: 0 | M51: 0 | N51: =IF($K51="","",$K51-N($L51)-N($M51)) -> 92102 | O51: AUDITADA | P51: AUDITADA | V51: 1 de 1 | W51: =IF(OR($F51="",$J51=""),"",$F51+$J51) | AF51: =IF(OR($R51="",$S51=""),"",$S51-$R51) | AG51: =IF(OR($S51="",$T51=""),"",$T51-$S51) | AH51: =IF(OR($T51="",$U51=""),"",$U51-$T51) | AI51: =IF(OR($R51="",$U51=""),"",$U51-$R51) | AJ51: =IF(OR($U51="",$AB51=""),"",$AB51-$U51) | AK51: =IF(OR($R51="",$AD51=""),"",$AD51-$R51) | AN51: Migrado (02-2026)
A52: =IF($B52="","",ROW()-3) -> 49 | B52: CLINICA PRIVADA CARAFFA SRL | C52: 30596272165 | D52: FAC | E52: 00015-00001189 | F52: 46083 | H52: AMBULATORIO | I52: OSPEVIC | J52: 60 | K52: 31748.4 | L52: 0 | M52: 0 | N52: =IF($K52="","",$K52-N($L52)-N($M52)) -> 31748.4 | O52: AUDITADA | P52: AUDITADA | V52: 1 de 1 | W52: =IF(OR($F52="",$J52=""),"",$F52+$J52) -> 46143 | AF52: =IF(OR($R52="",$S52=""),"",$S52-$R52) | AG52: =IF(OR($S52="",$T52=""),"",$T52-$S52) | AH52: =IF(OR($T52="",$U52=""),"",$U52-$T52) | AI52: =IF(OR($R52="",$U52=""),"",$U52-$R52) | AJ52: =IF(OR($U52="",$AB52=""),"",$AB52-$U52) | AK52: =IF(OR($R52="",$AD52=""),"",$AD52-$R52) | AN52: Migrado (02-2026)
A53: =IF($B53="","",ROW()-3) -> 50 | B53: CLINICA PRIVADA CARAFFA SRL | C53: 30596272165 | D53: FAC | E53: 00009-00003851 | F53: 46086 | H53: AMBULATORIO | I53: OSPEVIC | J53: 60 | K53: 317307.52 | L53: 0 | M53: 0 | N53: =IF($K53="","",$K53-N($L53)-N($M53)) -> 317307.52 | O53: AUDITADA | P53: AUDITADA | V53: 1 de 1 | W53: =IF(OR($F53="",$J53=""),"",$F53+$J53) -> 46146 | AF53: =IF(OR($R53="",$S53=""),"",$S53-$R53) | AG53: =IF(OR($S53="",$T53=""),"",$T53-$S53) | AH53: =IF(OR($T53="",$U53=""),"",$U53-$T53) | AI53: =IF(OR($R53="",$U53=""),"",$U53-$R53) | AJ53: =IF(OR($U53="",$AB53=""),"",$AB53-$U53) | AK53: =IF(OR($R53="",$AD53=""),"",$AD53-$R53) | AN53: Migrado (02-2026)
A54: =IF($B54="","",ROW()-3) -> 51 | B54: CLINICA PRIVADA CARAFFA SRL | C54: 30596272165 | D54: FAC | E54: 00009-00003852 | F54: 46086 | H54: AMBULATORIO | I54: OSPIF | J54: 60 | K54: 70037.5 | L54: 0 | M54: 0 | N54: =IF($K54="","",$K54-N($L54)-N($M54)) -> 70037.5 | O54: AUDITADA | P54: AUDITADA | V54: 1 de 1 | W54: =IF(OR($F54="",$J54=""),"",$F54+$J54) -> 46146 | AF54: =IF(OR($R54="",$S54=""),"",$S54-$R54) | AG54: =IF(OR($S54="",$T54=""),"",$T54-$S54) | AH54: =IF(OR($T54="",$U54=""),"",$U54-$T54) | AI54: =IF(OR($R54="",$U54=""),"",$U54-$R54) | AJ54: =IF(OR($U54="",$AB54=""),"",$AB54-$U54) | AK54: =IF(OR($R54="",$AD54=""),"",$AD54-$R54) | AN54: Migrado (02-2026)
A55: =IF($B55="","",ROW()-3) -> 52 | B55: CLINICA PRIVADA CARAFFA SRL | C55: 30596272165 | D55: FAC | E55: 00020-00000009 | F55: 46087 | H55: INTERNADO | I55: OSPEVIC | J55: 60 | K55: 80904.1 | L55: 0 | M55: 0 | N55: =IF($K55="","",$K55-N($L55)-N($M55)) -> 80904.1 | O55: AUDITADA | P55: AUDITADA | V55: 1 de 1 | W55: =IF(OR($F55="",$J55=""),"",$F55+$J55) -> 46147 | AF55: =IF(OR($R55="",$S55=""),"",$S55-$R55) | AG55: =IF(OR($S55="",$T55=""),"",$T55-$S55) | AH55: =IF(OR($T55="",$U55=""),"",$U55-$T55) | AI55: =IF(OR($R55="",$U55=""),"",$U55-$R55) | AJ55: =IF(OR($U55="",$AB55=""),"",$AB55-$U55) | AK55: =IF(OR($R55="",$AD55=""),"",$AD55-$R55) | AN55: Migrado (02-2026)
A56: =IF($B56="","",ROW()-3) -> 53 | B56: CLINICA PRIVADA CARAFFA SRL | C56: 30596272165 | D56: FAC | E56: 00020-00000017 | F56: 46090 | H56: INTERNADO | I56: OSPIF | J56: 60 | K56: 1219587.1 | L56: 0 | M56: 449183.02 | N56: =IF($K56="","",$K56-N($L56)-N($M56)) -> 770404.05 | O56: AUDITADA | P56: AUDITADA | V56: 1 de 1 | W56: =IF(OR($F56="",$J56=""),"",$F56+$J56) -> 46150 | AF56: =IF(OR($R56="",$S56=""),"",$S56-$R56) | AG56: =IF(OR($S56="",$T56=""),"",$T56-$S56) | AH56: =IF(OR($T56="",$U56=""),"",$U56-$T56) | AI56: =IF(OR($R56="",$U56=""),"",$U56-$R56) | AJ56: =IF(OR($U56="",$AB56=""),"",$AB56-$U56) | AK56: =IF(OR($R56="",$AD56=""),"",$AD56-$R56) | AN56: Migrado (02-2026)
A57: =IF($B57="","",ROW()-3) -> 54 | B57: CLINICA PRIVADA COAT S. R. L. | C57: 30682285431 | D57: FAC | E57: 00005-00005100 | F57: 46087 | H57: AMBULATORIO | I57: OSPIF | J57: 60 | K57: 50290 | L57: 0 | M57: 0 | N57: =IF($K57="","",$K57-N($L57)-N($M57)) -> 50290 | O57: AUDITADA | P57: AUDITADA | V57: 1 de 1 | W57: =IF(OR($F57="",$J57=""),"",$F57+$J57) -> 46147 | AF57: =IF(OR($R57="",$S57=""),"",$S57-$R57) | AG57: =IF(OR($S57="",$T57=""),"",$T57-$S57) | AH57: =IF(OR($T57="",$U57=""),"",$U57-$T57) | AI57: =IF(OR($R57="",$U57=""),"",$U57-$R57) | AJ57: =IF(OR($U57="",$AB57=""),"",$AB57-$U57) | AK57: =IF(OR($R57="",$AD57=""),"",$AD57-$R57) | AN57: Migrado (02-2026)
A58: =IF($B58="","",ROW()-3) -> 55 | B58: CLINICA PRIVADA COAT S. R. L. | C58: 30682285431 | D58: FAC | E58: 00005-00005105 | F58: 46087 | H58: AMBULATORIO | I58: OSPIF | J58: 60 | K58: 192600 | L58: 0 | M58: 0 | N58: =IF($K58="","",$K58-N($L58)-N($M58)) -> 192600 | O58: AUDITADA | P58: AUDITADA | V58: 1 de 1 | W58: =IF(OR($F58="",$J58=""),"",$F58+$J58) -> 46147 | AF58: =IF(OR($R58="",$S58=""),"",$S58-$R58) | AG58: =IF(OR($S58="",$T58=""),"",$T58-$S58) | AH58: =IF(OR($T58="",$U58=""),"",$U58-$T58) | AI58: =IF(OR($R58="",$U58=""),"",$U58-$R58) | AJ58: =IF(OR($U58="",$AB58=""),"",$AB58-$U58) | AK58: =IF(OR($R58="",$AD58=""),"",$AD58-$R58) | AN58: Migrado (02-2026)
A59: =IF($B59="","",ROW()-3) -> 56 | B59: CLINICA PRIVADA COAT S. R. L. | C59: 30682285431 | D59: FAC | E59: 00005-00005103 | F59: 46087 | H59: AMBULATORIO | I59: OSPEVIC | J59: 60 | K59: 25000 | L59: 0 | M59: 0 | N59: =IF($K59="","",$K59-N($L59)-N($M59)) -> 25000 | O59: AUDITADA | P59: AUDITADA | V59: 1 de 1 | W59: =IF(OR($F59="",$J59=""),"",$F59+$J59) -> 46147 | AF59: =IF(OR($R59="",$S59=""),"",$S59-$R59) | AG59: =IF(OR($S59="",$T59=""),"",$T59-$S59) | AH59: =IF(OR($T59="",$U59=""),"",$U59-$T59) | AI59: =IF(OR($R59="",$U59=""),"",$U59-$R59) | AJ59: =IF(OR($U59="",$AB59=""),"",$AB59-$U59) | AK59: =IF(OR($R59="",$AD59=""),"",$AD59-$R59) | AN59: Migrado (02-2026)
A60: =IF($B60="","",ROW()-3) -> 57 | B60: CLINICA PRIVADA DE LA CIUDAD SOC RESP LTDA | C60: 30660567840 | D60: FAC | E60: 00010-00003960 | F60: 46085 | I60: OSPEVIC | K60: 12541.71 | L60: 0 | M60: 0 | N60: =IF($K60="","",$K60-N($L60)-N($M60)) -> 12541.71 | O60: AUDITADA | P60: AUDITADA | V60: 1 de 1 | W60: =IF(OR($F60="",$J60=""),"",$F60+$J60) | AF60: =IF(OR($R60="",$S60=""),"",$S60-$R60) | AG60: =IF(OR($S60="",$T60=""),"",$T60-$S60) | AH60: =IF(OR($T60="",$U60=""),"",$U60-$T60) | AI60: =IF(OR($R60="",$U60=""),"",$U60-$R60) | AJ60: =IF(OR($U60="",$AB60=""),"",$AB60-$U60) | AK60: =IF(OR($R60="",$AD60=""),"",$AD60-$R60) | AN60: Migrado (02-2026)
A61: =IF($B61="","",ROW()-3) -> 58 | B61: CLINICA PRIVADA DE LA CIUDAD SOC RESP LTDA | C61: 30660567840 | D61: FAC | E61: 00010-00003961 | F61: 46085 | I61: OSPEVIC | K61: 327908.54 | L61: 0 | M61: 0 | N61: =IF($K61="","",$K61-N($L61)-N($M61)) -> 327908.54 | O61: AUDITADA | P61: AUDITADA | V61: 1 de 1 | W61: =IF(OR($F61="",$J61=""),"",$F61+$J61) | AF61: =IF(OR($R61="",$S61=""),"",$S61-$R61) | AG61: =IF(OR($S61="",$T61=""),"",$T61-$S61) | AH61: =IF(OR($T61="",$U61=""),"",$U61-$T61) | AI61: =IF(OR($R61="",$U61=""),"",$U61-$R61) | AJ61: =IF(OR($U61="",$AB61=""),"",$AB61-$U61) | AK61: =IF(OR($R61="",$AD61=""),"",$AD61-$R61) | AN61: Migrado (02-2026)
A62: =IF($B62="","",ROW()-3) -> 59 | B62: CLINICA PRIVADA DE LA CIUDAD SOC RESP LTDA | C62: 30660567840 | D62: FAC | E62: 00010-00003984 | F62: 46086 | I62: OSPIF | K62: 14161.71 | L62: 0 | M62: 0 | N62: =IF($K62="","",$K62-N($L62)-N($M62)) -> 14161.71 | O62: AUDITADA | P62: AUDITADA | V62: 1 de 1 | W62: =IF(OR($F62="",$J62=""),"",$F62+$J62) | AF62: =IF(OR($R62="",$S62=""),"",$S62-$R62) | AG62: =IF(OR($S62="",$T62=""),"",$T62-$S62) | AH62: =IF(OR($T62="",$U62=""),"",$U62-$T62) | AI62: =IF(OR($R62="",$U62=""),"",$U62-$R62) | AJ62: =IF(OR($U62="",$AB62=""),"",$AB62-$U62) | AK62: =IF(OR($R62="",$AD62=""),"",$AD62-$R62) | AN62: Migrado (02-2026)
A63: =IF($B63="","",ROW()-3) -> 60 | B63: CLINICA PRIVADA DE LA CIUDAD SOC RESP LTDA | C63: 30660567840 | D63: FAC | E63: 00010-00003979 | F63: 46086 | I63: OSPLYFC | K63: 286230.12 | L63: 0 | M63: 0 | N63: =IF($K63="","",$K63-N($L63)-N($M63)) -> 286230.12 | O63: AUDITADA | P63: AUDITADA | V63: 1 de 1 | W63: =IF(OR($F63="",$J63=""),"",$F63+$J63) | AF63: =IF(OR($R63="",$S63=""),"",$S63-$R63) | AG63: =IF(OR($S63="",$T63=""),"",$T63-$S63) | AH63: =IF(OR($T63="",$U63=""),"",$U63-$T63) | AI63: =IF(OR($R63="",$U63=""),"",$U63-$R63) | AJ63: =IF(OR($U63="",$AB63=""),"",$AB63-$U63) | AK63: =IF(OR($R63="",$AD63=""),"",$AD63-$R63) | AN63: Migrado (02-2026)
A64: =IF($B64="","",ROW()-3) -> 61 | B64: CLINICA PRIVADA DEAN FUNES SRL | C64: 30708237791 | D64: FAC | E64: 00004-00000912 | F64: 46081 | H64: AMBULATORIO | I64: OSPEVIC | J64: 60 | K64: 24028 | L64: 0 | M64: 0 | N64: =IF($K64="","",$K64-N($L64)-N($M64)) -> 24028 | O64: AUDITADA | P64: AUDITADA | V64: 1 de 1 | W64: =IF(OR($F64="",$J64=""),"",$F64+$J64) -> 46141 | AF64: =IF(OR($R64="",$S64=""),"",$S64-$R64) | AG64: =IF(OR($S64="",$T64=""),"",$T64-$S64) | AH64: =IF(OR($T64="",$U64=""),"",$U64-$T64) | AI64: =IF(OR($R64="",$U64=""),"",$U64-$R64) | AJ64: =IF(OR($U64="",$AB64=""),"",$AB64-$U64) | AK64: =IF(OR($R64="",$AD64=""),"",$AD64-$R64) | AN64: Migrado (02-2026)
A65: =IF($B65="","",ROW()-3) -> 62 | B65: CLINICA PRIVADA DEAN FUNES SRL | C65: 30708237791 | D65: FAC | E65: 0004-00000845 | F65: 45991 | H65: AMBULATORIO | I65: OSPLYFC | J65: 60 | K65: 86139 | L65: 39863 | M65: 0 | N65: =IF($K65="","",$K65-N($L65)-N($M65)) -> 46276 | O65: AUDITADA | P65: AUDITADA | V65: 1 de 1 | W65: =IF(OR($F65="",$J65=""),"",$F65+$J65) -> 46051 | AF65: =IF(OR($R65="",$S65=""),"",$S65-$R65) | AG65: =IF(OR($S65="",$T65=""),"",$T65-$S65) | AH65: =IF(OR($T65="",$U65=""),"",$U65-$T65) | AI65: =IF(OR($R65="",$U65=""),"",$U65-$R65) | AJ65: =IF(OR($U65="",$AB65=""),"",$AB65-$U65) | AK65: =IF(OR($R65="",$AD65=""),"",$AD65-$R65) | AN65: Migrado (02-2026)
A66: =IF($B66="","",ROW()-3) -> 63 | B66: CLINICA PRIVADA DEL SOL S.A. | C66: 30615571454 | D66: FAC | E66: 00008-00020376 | F66: 46087 | H66: INTERNADO | I66: OSPEVIC | J66: 45 | K66: 2837156.9 | L66: 396948.13 | M66: 116008.04 | N66: =IF($K66="","",$K66-N($L66)-N($M66)) -> 2324200.8 | O66: AUDITADA | P66: AUDITADA | V66: 1 de 1 | W66: =IF(OR($F66="",$J66=""),"",$F66+$J66) -> 46132 | AF66: =IF(OR($R66="",$S66=""),"",$S66-$R66) | AG66: =IF(OR($S66="",$T66=""),"",$T66-$S66) | AH66: =IF(OR($T66="",$U66=""),"",$U66-$T66) | AI66: =IF(OR($R66="",$U66=""),"",$U66-$R66) | AJ66: =IF(OR($U66="",$AB66=""),"",$AB66-$U66) | AK66: =IF(OR($R66="",$AD66=""),"",$AD66-$R66) | AN66: Migrado (02-2026)
A67: =IF($B67="","",ROW()-3) -> 64 | B67: CLINICA PRIVADA DEL SOL S.A. | C67: 30615571454 | D67: FAC | E67: 008-00020469 | F67: 46091 | H67: INTERNADO | I67: OSPEVIC | J67: 45 | K67: 378451.43 | L67: 5919.84 | M67: 0 | N67: =IF($K67="","",$K67-N($L67)-N($M67)) -> 372531.59 | O67: AUDITADA | P67: AUDITADA | V67: 1 de 1 | W67: =IF(OR($F67="",$J67=""),"",$F67+$J67) -> 46136 | AF67: =IF(OR($R67="",$S67=""),"",$S67-$R67) | AG67: =IF(OR($S67="",$T67=""),"",$T67-$S67) | AH67: =IF(OR($T67="",$U67=""),"",$U67-$T67) | AI67: =IF(OR($R67="",$U67=""),"",$U67-$R67) | AJ67: =IF(OR($U67="",$AB67=""),"",$AB67-$U67) | AK67: =IF(OR($R67="",$AD67=""),"",$AD67-$R67) | AN67: Migrado (02-2026)
A68: =IF($B68="","",ROW()-3) -> 65 | B68: CLINICA PRIVADA INTEGRAL DE PSIQUIATRIA SAN NICOLAS SRL S. R. L. | C68: 30608875227 | D68: FAC | E68: 00003-00000246 | F68: 46083 | H68: INTERNADO | I68: OSPIF | J68: 60 | K68: 495000 | L68: 0 | M68: 165000 | N68: =IF($K68="","",$K68-N($L68)-N($M68)) -> 330000 | O68: AUDITADA | P68: AUDITADA | V68: 1 de 1 | W68: =IF(OR($F68="",$J68=""),"",$F68+$J68) -> 46143 | AF68: =IF(OR($R68="",$S68=""),"",$S68-$R68) | AG68: =IF(OR($S68="",$T68=""),"",$T68-$S68) | AH68: =IF(OR($T68="",$U68=""),"",$U68-$T68) | AI68: =IF(OR($R68="",$U68=""),"",$U68-$R68) | AJ68: =IF(OR($U68="",$AB68=""),"",$AB68-$U68) | AK68: =IF(OR($R68="",$AD68=""),"",$AD68-$R68) | AN68: Migrado (02-2026)
A69: =IF($B69="","",ROW()-3) -> 66 | B69: CLINICA PRIVADA INTEGRAL DE PSIQUIATRIA SAN NICOLAS SRL S. R. L. | C69: 30608875227 | D69: FAC | E69: 00003-00000245 | F69: 46083 | H69: INTERNADO | I69: OSPEVIC | J69: 60 | K69: 2464000 | L69: 0 | M69: 0 | N69: =IF($K69="","",$K69-N($L69)-N($M69)) -> 2464000 | O69: AUDITADA | P69: AUDITADA | V69: 1 de 1 | W69: =IF(OR($F69="",$J69=""),"",$F69+$J69) -> 46143 | AF69: =IF(OR($R69="",$S69=""),"",$S69-$R69) | AG69: =IF(OR($S69="",$T69=""),"",$T69-$S69) | AH69: =IF(OR($T69="",$U69=""),"",$U69-$T69) | AI69: =IF(OR($R69="",$U69=""),"",$U69-$R69) | AJ69: =IF(OR($U69="",$AB69=""),"",$AB69-$U69) | AK69: =IF(OR($R69="",$AD69=""),"",$AD69-$R69) | AN69: Migrado (02-2026)
A70: =IF($B70="","",ROW()-3) -> 67 | B70: CLINICA PRIVADA INTEGRAL DE PSIQUIATRIA SAN NICOLAS SRL S. R. L. | C70: 30608875227 | D70: FAC | E70: 00003-00000251 | F70: 46084 | H70: AMBULATORIO | I70: OSPEVIC | J70: 60 | K70: 102030 | L70: 0 | M70: 0 | N70: =IF($K70="","",$K70-N($L70)-N($M70)) -> 102030 | O70: AUDITADA | P70: AUDITADA | V70: 1 de 1 | W70: =IF(OR($F70="",$J70=""),"",$F70+$J70) -> 46144 | AF70: =IF(OR($R70="",$S70=""),"",$S70-$R70) | AG70: =IF(OR($S70="",$T70=""),"",$T70-$S70) | AH70: =IF(OR($T70="",$U70=""),"",$U70-$T70) | AI70: =IF(OR($R70="",$U70=""),"",$U70-$R70) | AJ70: =IF(OR($U70="",$AB70=""),"",$AB70-$U70) | AK70: =IF(OR($R70="",$AD70=""),"",$AD70-$R70) | AN70: Migrado (02-2026)
A71: =IF($B71="","",ROW()-3) -> 68 | B71: CLINICA PRIVADA INTEGRAL DE PSIQUIATRIA SAN NICOLAS SRL S. R. L. | C71: 30608875227 | D71: FAC | E71: 00003-00000252 | F71: 46084 | H71: AMBULATORIO | I71: OSPEVIC | J71: 60 | K71: 27234 | L71: 0 | M71: 0 | N71: =IF($K71="","",$K71-N($L71)-N($M71)) -> 27234 | O71: AUDITADA | P71: AUDITADA | V71: 1 de 1 | W71: =IF(OR($F71="",$J71=""),"",$F71+$J71) -> 46144 | AF71: =IF(OR($R71="",$S71=""),"",$S71-$R71) | AG71: =IF(OR($S71="",$T71=""),"",$T71-$S71) | AH71: =IF(OR($T71="",$U71=""),"",$U71-$T71) | AI71: =IF(OR($R71="",$U71=""),"",$U71-$R71) | AJ71: =IF(OR($U71="",$AB71=""),"",$AB71-$U71) | AK71: =IF(OR($R71="",$AD71=""),"",$AD71-$R71) | AN71: Migrado (02-2026)
A72: =IF($B72="","",ROW()-3) -> 69 | B72: CLINICA PRIVADA INTEGRAL DE PSIQUIATRIA SAN NICOLAS SRL S. R. L. | C72: 30608875227 | D72: FAC | E72: 00003-00000253 | F72: 46084 | I72: OSPEVIC | K72: 619431 | L72: 0 | M72: 0 | N72: =IF($K72="","",$K72-N($L72)-N($M72)) -> 619431 | O72: AUDITADA | P72: AUDITADA | V72: 1 de 1 | W72: =IF(OR($F72="",$J72=""),"",$F72+$J72) | AF72: =IF(OR($R72="",$S72=""),"",$S72-$R72) | AG72: =IF(OR($S72="",$T72=""),"",$T72-$S72) | AH72: =IF(OR($T72="",$U72=""),"",$U72-$T72) | AI72: =IF(OR($R72="",$U72=""),"",$U72-$R72) | AJ72: =IF(OR($U72="",$AB72=""),"",$AB72-$U72) | AK72: =IF(OR($R72="",$AD72=""),"",$AD72-$R72) | AN72: Migrado (02-2026)
A73: =IF($B73="","",ROW()-3) -> 70 | B73: CLINICA PRIVADA INTEGRAL DE PSIQUIATRIA SAN NICOLAS SRL S. R. L. | C73: 30608875227 | D73: FAC | E73: 00003-00000249 | F73: 46084 | I73: OSPLYFC | K73: 120970 | L73: 44300 | M73: 0 | N73: =IF($K73="","",$K73-N($L73)-N($M73)) -> 76670 | O73: AUDITADA | P73: AUDITADA | V73: 1 de 1 | W73: =IF(OR($F73="",$J73=""),"",$F73+$J73) | AF73: =IF(OR($R73="",$S73=""),"",$S73-$R73) | AG73: =IF(OR($S73="",$T73=""),"",$T73-$S73) | AH73: =IF(OR($T73="",$U73=""),"",$U73-$T73) | AI73: =IF(OR($R73="",$U73=""),"",$U73-$R73) | AJ73: =IF(OR($U73="",$AB73=""),"",$AB73-$U73) | AK73: =IF(OR($R73="",$AD73=""),"",$AD73-$R73) | AN73: Migrado (02-2026)
A74: =IF($B74="","",ROW()-3) -> 71 | B74: CLINICA PRIVADA INTEGRAL DE PSIQUIATRIA SAN NICOLAS SRL S. R. L. | C74: 30608875227 | D74: FAC | E74: 00003-00000250 | F74: 46084 | I74: OSSURRBAC | K74: 59800 | L74: 12200 | M74: 0 | N74: =IF($K74="","",$K74-N($L74)-N($M74)) -> 47600 | O74: AUDITADA | P74: AUDITADA | V74: 1 de 1 | W74: =IF(OR($F74="",$J74=""),"",$F74+$J74) | AF74: =IF(OR($R74="",$S74=""),"",$S74-$R74) | AG74: =IF(OR($S74="",$T74=""),"",$T74-$S74) | AH74: =IF(OR($T74="",$U74=""),"",$U74-$T74) | AI74: =IF(OR($R74="",$U74=""),"",$U74-$R74) | AJ74: =IF(OR($U74="",$AB74=""),"",$AB74-$U74) | AK74: =IF(OR($R74="",$AD74=""),"",$AD74-$R74) | AN74: Migrado (02-2026)
A75: =IF($B75="","",ROW()-3) -> 72 | B75: CLINICA PRIVADA INTEGRAL DE PSIQUIATRIA SAN NICOLAS SRL S. R. L. | C75: 30608875227 | D75: FAC | E75: 00003-00000259 | F75: 46085 | I75: OSPEVIC | K75: 762200 | L75: 155740 | M75: 0 | N75: =IF($K75="","",$K75-N($L75)-N($M75)) -> 606460 | O75: AUDITADA | P75: AUDITADA | V75: 1 de 1 | W75: =IF(OR($F75="",$J75=""),"",$F75+$J75) | AF75: =IF(OR($R75="",$S75=""),"",$S75-$R75) | AG75: =IF(OR($S75="",$T75=""),"",$T75-$S75) | AH75: =IF(OR($T75="",$U75=""),"",$U75-$T75) | AI75: =IF(OR($R75="",$U75=""),"",$U75-$R75) | AJ75: =IF(OR($U75="",$AB75=""),"",$AB75-$U75) | AK75: =IF(OR($R75="",$AD75=""),"",$AD75-$R75) | AN75: Migrado (02-2026)
A76: =IF($B76="","",ROW()-3) -> 73 | B76: CLINICA PRIVADA JESUS MARIA DR ANIBAL LUIS VIALE S.A. | C76: 30546133865 | D76: FAC | E76: 00008-00011873 | F76: 46087 | H76: AMBULATORIO | I76: OSPEVIC | J76: 45 | K76: 336114.73 | L76: 23100 | M76: 0 | N76: =IF($K76="","",$K76-N($L76)-N($M76)) -> 313014.73 | O76: AUDITADA | P76: AUDITADA | V76: 1 de 1 | W76: =IF(OR($F76="",$J76=""),"",$F76+$J76) -> 46132 | AF76: =IF(OR($R76="",$S76=""),"",$S76-$R76) | AG76: =IF(OR($S76="",$T76=""),"",$T76-$S76) | AH76: =IF(OR($T76="",$U76=""),"",$U76-$T76) | AI76: =IF(OR($R76="",$U76=""),"",$U76-$R76) | AJ76: =IF(OR($U76="",$AB76=""),"",$AB76-$U76) | AK76: =IF(OR($R76="",$AD76=""),"",$AD76-$R76) | AN76: Migrado (02-2026)
A77: =IF($B77="","",ROW()-3) -> 74 | B77: CLINICA PRIVADA JESUS MARIA DR ANIBAL LUIS VIALE S.A. | C77: 30546133865 | D77: FAC | E77: 00008-00011879 | F77: 46087 | H77: AMBULATORIO | I77: OSPIF | J77: 60 | K77: 64767.88 | L77: 9550 | M77: 0 | N77: =IF($K77="","",$K77-N($L77)-N($M77)) -> 55217.88 | O77: AUDITADA | P77: AUDITADA | V77: 1 de 1 | W77: =IF(OR($F77="",$J77=""),"",$F77+$J77) -> 46147 | AF77: =IF(OR($R77="",$S77=""),"",$S77-$R77) | AG77: =IF(OR($S77="",$T77=""),"",$T77-$S77) | AH77: =IF(OR($T77="",$U77=""),"",$U77-$T77) | AI77: =IF(OR($R77="",$U77=""),"",$U77-$R77) | AJ77: =IF(OR($U77="",$AB77=""),"",$AB77-$U77) | AK77: =IF(OR($R77="",$AD77=""),"",$AD77-$R77) | AN77: Migrado (02-2026)
A78: =IF($B78="","",ROW()-3) -> 75 | B78: CLINICA PRIVADA REGIONAL S R L | C78: 30680944691 | D78: FAC | E78: 00007-00002665 | F78: 46087 | H78: INTERNADO | I78: OSPIF | J78: 45 | K78: 116258.76 | L78: 0 | M78: 0 | N78: =IF($K78="","",$K78-N($L78)-N($M78)) -> 116258.76 | O78: AUDITADA | P78: AUDITADA | V78: 1 de 1 | W78: =IF(OR($F78="",$J78=""),"",$F78+$J78) -> 46132 | AF78: =IF(OR($R78="",$S78=""),"",$S78-$R78) | AG78: =IF(OR($S78="",$T78=""),"",$T78-$S78) | AH78: =IF(OR($T78="",$U78=""),"",$U78-$T78) | AI78: =IF(OR($R78="",$U78=""),"",$U78-$R78) | AJ78: =IF(OR($U78="",$AB78=""),"",$AB78-$U78) | AK78: =IF(OR($R78="",$AD78=""),"",$AD78-$R78) | AN78: Migrado (02-2026)
A79: =IF($B79="","",ROW()-3) -> 76 | B79: CLINICA PRIVADA SANTA MARIA S.A. | C79: 33711273129 | D79: FAC | E79: 00004-00012821 | F79: 46081 | H79: AMBULATORIO | I79: OSPEVIC | J79: 60 | K79: 139954.4 | L79: 0 | M79: 0 | N79: =IF($K79="","",$K79-N($L79)-N($M79)) -> 139954.4 | O79: AUDITADA | P79: AUDITADA | V79: 1 de 1 | W79: =IF(OR($F79="",$J79=""),"",$F79+$J79) -> 46141 | AF79: =IF(OR($R79="",$S79=""),"",$S79-$R79) | AG79: =IF(OR($S79="",$T79=""),"",$T79-$S79) | AH79: =IF(OR($T79="",$U79=""),"",$U79-$T79) | AI79: =IF(OR($R79="",$U79=""),"",$U79-$R79) | AJ79: =IF(OR($U79="",$AB79=""),"",$AB79-$U79) | AK79: =IF(OR($R79="",$AD79=""),"",$AD79-$R79) | AN79: Migrado (02-2026)
A80: =IF($B80="","",ROW()-3) -> 77 | B80: COLEGIO DE PSICOLOGOS DE LA PROVINCIA DE CORDOBA | C80: 30680948891 | D80: FAC | E80: 00012-00000819 | F80: 46087 | H80: AMBULATORIO | I80: OSPEVIC | J80: 45 | K80: 61000 | L80: 0 | M80: 0 | N80: =IF($K80="","",$K80-N($L80)-N($M80)) -> 61000 | O80: AUDITADA | P80: AUDITADA | V80: 1 de 1 | W80: =IF(OR($F80="",$J80=""),"",$F80+$J80) -> 46132 | AF80: =IF(OR($R80="",$S80=""),"",$S80-$R80) | AG80: =IF(OR($S80="",$T80=""),"",$T80-$S80) | AH80: =IF(OR($T80="",$U80=""),"",$U80-$T80) | AI80: =IF(OR($R80="",$U80=""),"",$U80-$R80) | AJ80: =IF(OR($U80="",$AB80=""),"",$AB80-$U80) | AK80: =IF(OR($R80="",$AD80=""),"",$AD80-$R80) | AN80: Migrado (02-2026)
A81: =IF($B81="","",ROW()-3) -> 78 | B81: COLEGIO MED REG DEL SUR DE CBA | C81: 30553588266 | D81: FAC | E81: 00002-00003486 | F81: 46087 | H81: AMBULATORIO | I81: OSPIF | J81: 45 | K81: 577376.09 | L81: 2442.5 | M81: 0 | N81: =IF($K81="","",$K81-N($L81)-N($M81)) -> 574933.59 | O81: AUDITADA | P81: AUDITADA | V81: 1 de 1 | W81: =IF(OR($F81="",$J81=""),"",$F81+$J81) -> 46132 | AF81: =IF(OR($R81="",$S81=""),"",$S81-$R81) | AG81: =IF(OR($S81="",$T81=""),"",$T81-$S81) | AH81: =IF(OR($T81="",$U81=""),"",$U81-$T81) | AI81: =IF(OR($R81="",$U81=""),"",$U81-$R81) | AJ81: =IF(OR($U81="",$AB81=""),"",$AB81-$U81) | AK81: =IF(OR($R81="",$AD81=""),"",$AD81-$R81) | AN81: Migrado (02-2026)
A82: =IF($B82="","",ROW()-3) -> 79 | B82: COLEGIO MEDICO DE OLIVA | C82: 30552575292 | D82: FAC | E82: 00005-00002793 | F82: 46078 | I82: OSPIF | K82: 510826.8 | L82: 312050 | M82: 0 | N82: =IF($K82="","",$K82-N($L82)-N($M82)) -> 198776.8 | O82: AUDITADA | P82: AUDITADA | V82: 1 de 1 | W82: =IF(OR($F82="",$J82=""),"",$F82+$J82) | AF82: =IF(OR($R82="",$S82=""),"",$S82-$R82) | AG82: =IF(OR($S82="",$T82=""),"",$T82-$S82) | AH82: =IF(OR($T82="",$U82=""),"",$U82-$T82) | AI82: =IF(OR($R82="",$U82=""),"",$U82-$R82) | AJ82: =IF(OR($U82="",$AB82=""),"",$AB82-$U82) | AK82: =IF(OR($R82="",$AD82=""),"",$AD82-$R82) | AN82: Migrado (02-2026)
A83: =IF($B83="","",ROW()-3) -> 80 | B83: COLEGIO MEDICO REGIONAL ARROYITO | C83: 30555217419 | D83: FAC | E83: 00004-00009497 | F83: 46086 | H83: AMBULATORIO | I83: OSPEVIC | J83: 45 | K83: 30587.17 | L83: 0 | M83: 0 | N83: =IF($K83="","",$K83-N($L83)-N($M83)) -> 30587.17 | O83: AUDITADA | P83: AUDITADA | V83: 1 de 1 | W83: =IF(OR($F83="",$J83=""),"",$F83+$J83) -> 46131 | AF83: =IF(OR($R83="",$S83=""),"",$S83-$R83) | AG83: =IF(OR($S83="",$T83=""),"",$T83-$S83) | AH83: =IF(OR($T83="",$U83=""),"",$U83-$T83) | AI83: =IF(OR($R83="",$U83=""),"",$U83-$R83) | AJ83: =IF(OR($U83="",$AB83=""),"",$AB83-$U83) | AK83: =IF(OR($R83="",$AD83=""),"",$AD83-$R83) | AN83: Migrado (02-2026)
A84: =IF($B84="","",ROW()-3) -> 81 | B84: COLEGIO MEDICO REGIONAL ARROYITO | C84: 30555217419 | D84: FAC | E84: 00004-00009521 | F84: 46090 | H84: INTERNADO | I84: OSPIF | J84: 45 | K84: 2834992.7 | L84: 69564.23 | M84: 0 | N84: =IF($K84="","",$K84-N($L84)-N($M84)) -> 2765428.5 | O84: AUDITADA | P84: AUDITADA | V84: 1 de 1 | W84: =IF(OR($F84="",$J84=""),"",$F84+$J84) -> 46135 | AF84: =IF(OR($R84="",$S84=""),"",$S84-$R84) | AG84: =IF(OR($S84="",$T84=""),"",$T84-$S84) | AH84: =IF(OR($T84="",$U84=""),"",$U84-$T84) | AI84: =IF(OR($R84="",$U84=""),"",$U84-$R84) | AJ84: =IF(OR($U84="",$AB84=""),"",$AB84-$U84) | AK84: =IF(OR($R84="",$AD84=""),"",$AD84-$R84) | AN84: Migrado (02-2026)
A85: =IF($B85="","",ROW()-3) -> 82 | B85: COLEGIO PROFESIONAL DE KINESIOLOGOS Y FISIOTERAPEUTAS DE LA PROVINCIA DE CORDOBA | C85: 30623578743 | D85: FAC | E85: 00002-00007059 | F85: 46087 | H85: AMBULATORIO | I85: OSPIF | J85: 45 | K85: 175500 | L85: 19500 | M85: 0 | N85: =IF($K85="","",$K85-N($L85)-N($M85)) -> 156000 | O85: AUDITADA | P85: AUDITADA | V85: 1 de 1 | W85: =IF(OR($F85="",$J85=""),"",$F85+$J85) -> 46132 | AF85: =IF(OR($R85="",$S85=""),"",$S85-$R85) | AG85: =IF(OR($S85="",$T85=""),"",$T85-$S85) | AH85: =IF(OR($T85="",$U85=""),"",$U85-$T85) | AI85: =IF(OR($R85="",$U85=""),"",$U85-$R85) | AJ85: =IF(OR($U85="",$AB85=""),"",$AB85-$U85) | AK85: =IF(OR($R85="",$AD85=""),"",$AD85-$R85) | AN85: Migrado (02-2026)
A86: =IF($B86="","",ROW()-3) -> 83 | B86: COSEME SA | C86: 30680565224 | D86: FAC | E86: 00046-00004402 | F86: 46083 | I86: OSPEVIC | K86: 227170.48 | L86: 11777.68 | M86: 0 | N86: =IF($K86="","",$K86-N($L86)-N($M86)) -> 215392.8 | O86: AUDITADA | P86: AUDITADA | V86: 1 de 1 | W86: =IF(OR($F86="",$J86=""),"",$F86+$J86) | AF86: =IF(OR($R86="",$S86=""),"",$S86-$R86) | AG86: =IF(OR($S86="",$T86=""),"",$T86-$S86) | AH86: =IF(OR($T86="",$U86=""),"",$U86-$T86) | AI86: =IF(OR($R86="",$U86=""),"",$U86-$R86) | AJ86: =IF(OR($U86="",$AB86=""),"",$AB86-$U86) | AK86: =IF(OR($R86="",$AD86=""),"",$AD86-$R86) | AN86: Migrado (02-2026)
A87: =IF($B87="","",ROW()-3) -> 84 | B87: COSEME SA | C87: 30680565224 | D87: FAC | E87: 00046-00004404 | F87: 46083 | I87: OSPEVIC | K87: 1221.83 | L87: 1221.83 | M87: 0 | N87: =IF($K87="","",$K87-N($L87)-N($M87)) -> 0 | O87: AUDITADA | P87: AUDITADA | V87: 1 de 1 | W87: =IF(OR($F87="",$J87=""),"",$F87+$J87) | AF87: =IF(OR($R87="",$S87=""),"",$S87-$R87) | AG87: =IF(OR($S87="",$T87=""),"",$T87-$S87) | AH87: =IF(OR($T87="",$U87=""),"",$U87-$T87) | AI87: =IF(OR($R87="",$U87=""),"",$U87-$R87) | AJ87: =IF(OR($U87="",$AB87=""),"",$AB87-$U87) | AK87: =IF(OR($R87="",$AD87=""),"",$AD87-$R87) | AN87: Migrado (02-2026)
A88: =IF($B88="","",ROW()-3) -> 85 | B88: COSEME SA | C88: 30680565224 | D88: FAC | E88: 00046-00004408 | F88: 46083 | I88: OSSURRBAC | K88: 20945.33 | L88: 997.4 | M88: 0 | N88: =IF($K88="","",$K88-N($L88)-N($M88)) -> 19947.93 | O88: AUDITADA | P88: AUDITADA | V88: 1 de 1 | W88: =IF(OR($F88="",$J88=""),"",$F88+$J88) | AF88: =IF(OR($R88="",$S88=""),"",$S88-$R88) | AG88: =IF(OR($S88="",$T88=""),"",$T88-$S88) | AH88: =IF(OR($T88="",$U88=""),"",$U88-$T88) | AI88: =IF(OR($R88="",$U88=""),"",$U88-$R88) | AJ88: =IF(OR($U88="",$AB88=""),"",$AB88-$U88) | AK88: =IF(OR($R88="",$AD88=""),"",$AD88-$R88) | AN88: Migrado (02-2026)
A89: =IF($B89="","",ROW()-3) -> 86 | B89: COSEME SA | C89: 30680565224 | D89: FAC | E89: 00047-00001816 | F89: 46083 | I89: OSPLYFC | K89: 21814.28 | L89: 21814.28 | M89: 0 | N89: =IF($K89="","",$K89-N($L89)-N($M89)) -> 0 | O89: AUDITADA | P89: AUDITADA | V89: 1 de 1 | W89: =IF(OR($F89="",$J89=""),"",$F89+$J89) | AF89: =IF(OR($R89="",$S89=""),"",$S89-$R89) | AG89: =IF(OR($S89="",$T89=""),"",$T89-$S89) | AH89: =IF(OR($T89="",$U89=""),"",$U89-$T89) | AI89: =IF(OR($R89="",$U89=""),"",$U89-$R89) | AJ89: =IF(OR($U89="",$AB89=""),"",$AB89-$U89) | AK89: =IF(OR($R89="",$AD89=""),"",$AD89-$R89) | AN89: Migrado (02-2026)
A90: =IF($B90="","",ROW()-3) -> 87 | B90: COSEME SA | C90: 30680565224 | D90: FAC | E90: 00046-00004454 | F90: 46086 | I90: OSPIF | K90: 60981.32 | L90: 19279.04 | M90: 0 | N90: =IF($K90="","",$K90-N($L90)-N($M90)) -> 41702.28 | O90: AUDITADA | P90: AUDITADA | V90: 1 de 1 | W90: =IF(OR($F90="",$J90=""),"",$F90+$J90) | AF90: =IF(OR($R90="",$S90=""),"",$S90-$R90) | AG90: =IF(OR($S90="",$T90=""),"",$T90-$S90) | AH90: =IF(OR($T90="",$U90=""),"",$U90-$T90) | AI90: =IF(OR($R90="",$U90=""),"",$U90-$R90) | AJ90: =IF(OR($U90="",$AB90=""),"",$AB90-$U90) | AK90: =IF(OR($R90="",$AD90=""),"",$AD90-$R90) | AN90: Migrado (02-2026)
A91: =IF($B91="","",ROW()-3) -> 88 | B91: COSEME SA | C91: 30680565224 | D91: FAC | E91: 00046-00004403 | F91: 46083 | I91: OSPEVIC | K91: 15766.62 | L91: 0 | M91: 0 | N91: =IF($K91="","",$K91-N($L91)-N($M91)) -> 15766.62 | O91: AUDITADA | P91: AUDITADA | V91: 1 de 1 | W91: =IF(OR($F91="",$J91=""),"",$F91+$J91) | AF91: =IF(OR($R91="",$S91=""),"",$S91-$R91) | AG91: =IF(OR($S91="",$T91=""),"",$T91-$S91) | AH91: =IF(OR($T91="",$U91=""),"",$U91-$T91) | AI91: =IF(OR($R91="",$U91=""),"",$U91-$R91) | AJ91: =IF(OR($U91="",$AB91=""),"",$AB91-$U91) | AK91: =IF(OR($R91="",$AD91=""),"",$AD91-$R91) | AN91: Migrado (02-2026)
A92: =IF($B92="","",ROW()-3) -> 89 | B92: DE LA VILLA SERVICIOS ASISTENCIALES S.A. | C92: 30623442566 | D92: FAC | E92: 00004-00015411 | F92: 46086 | H92: AMBULATORIO | I92: OSPLYFC | J92: 60 | K92: 79174.55 | L92: 0 | M92: 0 | N92: =IF($K92="","",$K92-N($L92)-N($M92)) -> 79174.55 | O92: AUDITADA | P92: AUDITADA | V92: 1 de 1 | W92: =IF(OR($F92="",$J92=""),"",$F92+$J92) -> 46146 | AF92: =IF(OR($R92="",$S92=""),"",$S92-$R92) | AG92: =IF(OR($S92="",$T92=""),"",$T92-$S92) | AH92: =IF(OR($T92="",$U92=""),"",$U92-$T92) | AI92: =IF(OR($R92="",$U92=""),"",$U92-$R92) | AJ92: =IF(OR($U92="",$AB92=""),"",$AB92-$U92) | AK92: =IF(OR($R92="",$AD92=""),"",$AD92-$R92) | AN92: Migrado (02-2026)
A93: =IF($B93="","",ROW()-3) -> 90 | B93: DE LA VILLA SERVICIOS ASISTENCIALES S.A. | C93: 30623442566 | D93: FAC | E93: 00004-00015412 | F93: 46086 | H93: AMBULATORIO | I93: OSPLYFC | J93: 60 | K93: 26189.49 | L93: 0 | M93: 0 | N93: =IF($K93="","",$K93-N($L93)-N($M93)) -> 26189.49 | O93: AUDITADA | P93: AUDITADA | V93: 1 de 1 | W93: =IF(OR($F93="",$J93=""),"",$F93+$J93) -> 46146 | AF93: =IF(OR($R93="",$S93=""),"",$S93-$R93) | AG93: =IF(OR($S93="",$T93=""),"",$T93-$S93) | AH93: =IF(OR($T93="",$U93=""),"",$U93-$T93) | AI93: =IF(OR($R93="",$U93=""),"",$U93-$R93) | AJ93: =IF(OR($U93="",$AB93=""),"",$AB93-$U93) | AK93: =IF(OR($R93="",$AD93=""),"",$AD93-$R93) | AN93: Migrado (02-2026)
A94: =IF($B94="","",ROW()-3) -> 91 | B94: DE LA VILLA SERVICIOS ASISTENCIALES S.A. | C94: 30623442566 | D94: FAC | E94: 00004-00015409 | F94: 46086 | H94: AMBULATORIO | I94: OSPIF | J94: 60 | K94: 1337850.5 | L94: 0 | M94: 0 | N94: =IF($K94="","",$K94-N($L94)-N($M94)) -> 1337850.5 | O94: AUDITADA | P94: AUDITADA | V94: 1 de 1 | W94: =IF(OR($F94="",$J94=""),"",$F94+$J94) -> 46146 | AF94: =IF(OR($R94="",$S94=""),"",$S94-$R94) | AG94: =IF(OR($S94="",$T94=""),"",$T94-$S94) | AH94: =IF(OR($T94="",$U94=""),"",$U94-$T94) | AI94: =IF(OR($R94="",$U94=""),"",$U94-$R94) | AJ94: =IF(OR($U94="",$AB94=""),"",$AB94-$U94) | AK94: =IF(OR($R94="",$AD94=""),"",$AD94-$R94) | AN94: Migrado (02-2026)
A95: =IF($B95="","",ROW()-3) -> 92 | B95: DE LA VILLA SERVICIOS ASISTENCIALES S.A. | C95: 30623442566 | D95: FAC | E95: 00004-00015410 | F95: 46086 | H95: AMBULATORIO | I95: OSPIF | J95: 60 | K95: 19452.79 | L95: 0 | M95: 0 | N95: =IF($K95="","",$K95-N($L95)-N($M95)) -> 19452.79 | O95: AUDITADA | P95: AUDITADA | V95: 1 de 1 | W95: =IF(OR($F95="",$J95=""),"",$F95+$J95) -> 46146 | AF95: =IF(OR($R95="",$S95=""),"",$S95-$R95) | AG95: =IF(OR($S95="",$T95=""),"",$T95-$S95) | AH95: =IF(OR($T95="",$U95=""),"",$U95-$T95) | AI95: =IF(OR($R95="",$U95=""),"",$U95-$R95) | AJ95: =IF(OR($U95="",$AB95=""),"",$AB95-$U95) | AK95: =IF(OR($R95="",$AD95=""),"",$AD95-$R95) | AN95: Migrado (02-2026)
A96: =IF($B96="","",ROW()-3) -> 93 | B96: DE LA VILLA SERVICIOS ASISTENCIALES S.A. | C96: 30623442566 | D96: FAC | E96: 00004-00015419 | F96: 46087 | H96: AMBULATORIO | I96: OSPEVIC | J96: 60 | K96: 43892.36 | L96: 0 | M96: 0 | N96: =IF($K96="","",$K96-N($L96)-N($M96)) -> 43892.36 | O96: AUDITADA | P96: AUDITADA | V96: 1 de 1 | W96: =IF(OR($F96="",$J96=""),"",$F96+$J96) -> 46147 | AF96: =IF(OR($R96="",$S96=""),"",$S96-$R96) | AG96: =IF(OR($S96="",$T96=""),"",$T96-$S96) | AH96: =IF(OR($T96="",$U96=""),"",$U96-$T96) | AI96: =IF(OR($R96="",$U96=""),"",$U96-$R96) | AJ96: =IF(OR($U96="",$AB96=""),"",$AB96-$U96) | AK96: =IF(OR($R96="",$AD96=""),"",$AD96-$R96) | AN96: Migrado (02-2026)
A97: =IF($B97="","",ROW()-3) -> 94 | B97: DE LA VILLA SERVICIOS ASISTENCIALES S.A. | C97: 30623442566 | D97: FAC | E97: 00004-00015420 | F97: 46087 | H97: AMBULATORIO | I97: OSSURRBAC | J97: 60 | K97: 39544.14 | L97: 0 | M97: 0 | N97: =IF($K97="","",$K97-N($L97)-N($M97)) -> 39544.14 | O97: AUDITADA | P97: AUDITADA | V97: 1 de 1 | W97: =IF(OR($F97="",$J97=""),"",$F97+$J97) -> 46147 | AF97: =IF(OR($R97="",$S97=""),"",$S97-$R97) | AG97: =IF(OR($S97="",$T97=""),"",$T97-$S97) | AH97: =IF(OR($T97="",$U97=""),"",$U97-$T97) | AI97: =IF(OR($R97="",$U97=""),"",$U97-$R97) | AJ97: =IF(OR($U97="",$AB97=""),"",$AB97-$U97) | AK97: =IF(OR($R97="",$AD97=""),"",$AD97-$R97) | AN97: Migrado (02-2026)
A98: =IF($B98="","",ROW()-3) -> 95 | B98: ECCO S. A. U. | C98: 30602764032 | D98: FAC | E98: 00203-00158006 | F98: 46087 | H98: TRASLADOS | I98: OSPEVIC | J98: 30 | K98: 1800000 | L98: 0 | M98: 0 | N98: =IF($K98="","",$K98-N($L98)-N($M98)) -> 1800000 | O98: AUDITADA | P98: AUDITADA | V98: 1 de 1 | W98: =IF(OR($F98="",$J98=""),"",$F98+$J98) -> 46117 | AF98: =IF(OR($R98="",$S98=""),"",$S98-$R98) | AG98: =IF(OR($S98="",$T98=""),"",$T98-$S98) | AH98: =IF(OR($T98="",$U98=""),"",$U98-$T98) | AI98: =IF(OR($R98="",$U98=""),"",$U98-$R98) | AJ98: =IF(OR($U98="",$AB98=""),"",$AB98-$U98) | AK98: =IF(OR($R98="",$AD98=""),"",$AD98-$R98) | AN98: Migrado (02-2026)
A99: =IF($B99="","",ROW()-3) -> 96 | B99: EL JUNCO SERVICIOS SOCIALES SA | C99: 30708910208 | D99: FAC | E99: 00118-00000721 | F99: 46087 | H99: REFACTURACION | I99: OSPLYFC | J99: 60 | K99: 12810 | L99: 0 | M99: 0 | N99: =IF($K99="","",$K99-N($L99)-N($M99)) -> 12810 | O99: AUDITADA | P99: AUDITADA | V99: 1 de 1 | W99: =IF(OR($F99="",$J99=""),"",$F99+$J99) -> 46147 | AF99: =IF(OR($R99="",$S99=""),"",$S99-$R99) | AG99: =IF(OR($S99="",$T99=""),"",$T99-$S99) | AH99: =IF(OR($T99="",$U99=""),"",$U99-$T99) | AI99: =IF(OR($R99="",$U99=""),"",$U99-$R99) | AJ99: =IF(OR($U99="",$AB99=""),"",$AB99-$U99) | AK99: =IF(OR($R99="",$AD99=""),"",$AD99-$R99) | AN99: Migrado (02-2026)
A100: =IF($B100="","",ROW()-3) -> 97 | B100: EL JUNCO SERVICIOS SOCIALES SA | C100: 30708910208 | D100: FAC | E100: 00118-00000716 | F100: 46086 | I100: OSPLYFC | K100: 119172 | L100: 0 | M100: 0 | N100: =IF($K100="","",$K100-N($L100)-N($M100)) -> 119172 | O100: AUDITADA | P100: AUDITADA | V100: 1 de 1 | W100: =IF(OR($F100="",$J100=""),"",$F100+$J100) | AF100: =IF(OR($R100="",$S100=""),"",$S100-$R100) | AG100: =IF(OR($S100="",$T100=""),"",$T100-$S100) | AH100: =IF(OR($T100="",$U100=""),"",$U100-$T100) | AI100: =IF(OR($R100="",$U100=""),"",$U100-$R100) | AJ100: =IF(OR($U100="",$AB100=""),"",$AB100-$U100) | AK100: =IF(OR($R100="",$AD100=""),"",$AD100-$R100) | AN100: Migrado (02-2026)
A101: =IF($B101="","",ROW()-3) -> 98 | B101: EL JUNCO SERVICIOS SOCIALES SA | C101: 30708910208 | D101: FAC | E101: 00118-00000717 | F101: 46086 | I101: OSPEVIC | K101: 132500 | L101: 0 | M101: 0 | N101: =IF($K101="","",$K101-N($L101)-N($M101)) -> 132500 | O101: AUDITADA | P101: AUDITADA | V101: 1 de 1 | W101: =IF(OR($F101="",$J101=""),"",$F101+$J101) | AF101: =IF(OR($R101="",$S101=""),"",$S101-$R101) | AG101: =IF(OR($S101="",$T101=""),"",$T101-$S101) | AH101: =IF(OR($T101="",$U101=""),"",$U101-$T101) | AI101: =IF(OR($R101="",$U101=""),"",$U101-$R101) | AJ101: =IF(OR($U101="",$AB101=""),"",$AB101-$U101) | AK101: =IF(OR($R101="",$AD101=""),"",$AD101-$R101) | AN101: Migrado (02-2026)
A102: =IF($B102="","",ROW()-3) -> 99 | B102: EL JUNCO SERVICIOS SOCIALES SA | C102: 30708910208 | D102: FAC | E102: 00118-00000718 | F102: 46086 | I102: OSSURRBAC | K102: 9100 | L102: 0 | M102: 0 | N102: =IF($K102="","",$K102-N($L102)-N($M102)) -> 9100 | O102: AUDITADA | P102: AUDITADA | V102: 1 de 1 | W102: =IF(OR($F102="",$J102=""),"",$F102+$J102) | AF102: =IF(OR($R102="",$S102=""),"",$S102-$R102) | AG102: =IF(OR($S102="",$T102=""),"",$T102-$S102) | AH102: =IF(OR($T102="",$U102=""),"",$U102-$T102) | AI102: =IF(OR($R102="",$U102=""),"",$U102-$R102) | AJ102: =IF(OR($U102="",$AB102=""),"",$AB102-$U102) | AK102: =IF(OR($R102="",$AD102=""),"",$AD102-$R102) | AN102: Migrado (02-2026)
A103: =IF($B103="","",ROW()-3) -> 100 | B103: EL JUNCO SERVICIOS SOCIALES SA | C103: 30708910208 | D103: FAC | E103: 00118-00000719 | F103: 46086 | I103: OSPIF | K103: 224460 | L103: 0 | M103: 0 | N103: =IF($K103="","",$K103-N($L103)-N($M103)) -> 224460 | O103: AUDITADA | P103: AUDITADA | V103: 1 de 1 | W103: =IF(OR($F103="",$J103=""),"",$F103+$J103) | AF103: =IF(OR($R103="",$S103=""),"",$S103-$R103) | AG103: =IF(OR($S103="",$T103=""),"",$T103-$S103) | AH103: =IF(OR($T103="",$U103=""),"",$U103-$T103) | AI103: =IF(OR($R103="",$U103=""),"",$U103-$R103) | AJ103: =IF(OR($U103="",$AB103=""),"",$AB103-$U103) | AK103: =IF(OR($R103="",$AD103=""),"",$AD103-$R103) | AN103: Migrado (02-2026)
A104: =IF($B104="","",ROW()-3) -> 101 | B104: EQUILIBRE SALUD S.A.S. | C104: 33716532629 | D104: FAC | E104: 00001-00000613 | F104: 46085 | H104: AMBULATORIO | I104: OSPIF | J104: 45 | K104: 54269 | L104: 0 | M104: 0 | N104: =IF($K104="","",$K104-N($L104)-N($M104)) -> 54269 | O104: AUDITADA | P104: AUDITADA | V104: 1 de 1 | W104: =IF(OR($F104="",$J104=""),"",$F104+$J104) -> 46130 | AF104: =IF(OR($R104="",$S104=""),"",$S104-$R104) | AG104: =IF(OR($S104="",$T104=""),"",$T104-$S104) | AH104: =IF(OR($T104="",$U104=""),"",$U104-$T104) | AI104: =IF(OR($R104="",$U104=""),"",$U104-$R104) | AJ104: =IF(OR($U104="",$AB104=""),"",$AB104-$U104) | AK104: =IF(OR($R104="",$AD104=""),"",$AD104-$R104) | AN104: Migrado (02-2026)
A105: =IF($B105="","",ROW()-3) -> 102 | B105: ESTIX S.A.S. | C105: 30717147835 | D105: FAC | E105: 00004-00000432 | F105: 46090 | H105: AMBULATORIO | I105: OSPEVIC | J105: 60 | K105: 96112.56 | L105: 0 | M105: 0 | N105: =IF($K105="","",$K105-N($L105)-N($M105)) -> 96112.56 | O105: AUDITADA | P105: AUDITADA | V105: 1 de 1 | W105: =IF(OR($F105="",$J105=""),"",$F105+$J105) -> 46150 | AF105: =IF(OR($R105="",$S105=""),"",$S105-$R105) | AG105: =IF(OR($S105="",$T105=""),"",$T105-$S105) | AH105: =IF(OR($T105="",$U105=""),"",$U105-$T105) | AI105: =IF(OR($R105="",$U105=""),"",$U105-$R105) | AJ105: =IF(OR($U105="",$AB105=""),"",$AB105-$U105) | AK105: =IF(OR($R105="",$AD105=""),"",$AD105-$R105) | AN105: Migrado (02-2026)
A106: =IF($B106="","",ROW()-3) -> 103 | B106: FEDERACION DE BIOQUIMICOS DE LA PROVINCIA DE CORDOBA | C106: 33577427009 | D106: FAC | E106: 0005-00005726 | F106: 46090 | H106: AMBULATORIO | I106: OSPIF | J106: 45 | K106: 705107 | L106: 255112 | M106: 0 | N106: =IF($K106="","",$K106-N($L106)-N($M106)) -> 449995 | O106: AUDITADA | P106: AUDITADA | V106: 1 de 1 | W106: =IF(OR($F106="",$J106=""),"",$F106+$J106) -> 46135 | AF106: =IF(OR($R106="",$S106=""),"",$S106-$R106) | AG106: =IF(OR($S106="",$T106=""),"",$T106-$S106) | AH106: =IF(OR($T106="",$U106=""),"",$U106-$T106) | AI106: =IF(OR($R106="",$U106=""),"",$U106-$R106) | AJ106: =IF(OR($U106="",$AB106=""),"",$AB106-$U106) | AK106: =IF(OR($R106="",$AD106=""),"",$AD106-$R106) | AN106: Migrado (02-2026)
A107: =IF($B107="","",ROW()-3) -> 104 | B107: FEDERACION DE BIOQUIMICOS DE LA PROVINCIA DE CORDOBA | C107: 33577427009 | D107: FAC | E107: 0005-00005727 | F107: 46090 | H107: AMBULATORIO | I107: OSPEVIC | J107: 45 | K107: 1339240 | L107: 261697 | M107: 0 | N107: =IF($K107="","",$K107-N($L107)-N($M107)) -> 1077543 | O107: AUDITADA | P107: AUDITADA | V107: 1 de 1 | W107: =IF(OR($F107="",$J107=""),"",$F107+$J107) -> 46135 | AF107: =IF(OR($R107="",$S107=""),"",$S107-$R107) | AG107: =IF(OR($S107="",$T107=""),"",$T107-$S107) | AH107: =IF(OR($T107="",$U107=""),"",$U107-$T107) | AI107: =IF(OR($R107="",$U107=""),"",$U107-$R107) | AJ107: =IF(OR($U107="",$AB107=""),"",$AB107-$U107) | AK107: =IF(OR($R107="",$AD107=""),"",$AD107-$R107) | AN107: Migrado (02-2026)
A108: =IF($B108="","",ROW()-3) -> 105 | B108: FUNDACION CENTRO PREV. BULIMIA | C108: 30714398454 | D108: FAC | E108: 00004-00002526 | F108: 46083 | H108: AMBULATORIO | I108: OSPEVIC | J108: 45 | K108: 600000 | L108: 600000 | M108: 0 | N108: =IF($K108="","",$K108-N($L108)-N($M108)) -> 0 | O108: AUDITADA | P108: AUDITADA | V108: 1 de 1 | W108: =IF(OR($F108="",$J108=""),"",$F108+$J108) -> 46128 | AF108: =IF(OR($R108="",$S108=""),"",$S108-$R108) | AG108: =IF(OR($S108="",$T108=""),"",$T108-$S108) | AH108: =IF(OR($T108="",$U108=""),"",$U108-$T108) | AI108: =IF(OR($R108="",$U108=""),"",$U108-$R108) | AJ108: =IF(OR($U108="",$AB108=""),"",$AB108-$U108) | AK108: =IF(OR($R108="",$AD108=""),"",$AD108-$R108) | AN108: Migrado (02-2026)
A109: =IF($B109="","",ROW()-3) -> 106 | B109: FUNDACION FECUNDART | C109: 30709242195 | D109: FAC | E109: 00006-00000033 | F109: 46091 | H109: AMBULATORIO | I109: OSPEVIC | J109: 45 | K109: 216159.6 | L109: 0 | M109: 0 | N109: =IF($K109="","",$K109-N($L109)-N($M109)) -> 216159.6 | O109: AUDITADA | P109: AUDITADA | V109: 1 de 1 | W109: =IF(OR($F109="",$J109=""),"",$F109+$J109) -> 46136 | AF109: =IF(OR($R109="",$S109=""),"",$S109-$R109) | AG109: =IF(OR($S109="",$T109=""),"",$T109-$S109) | AH109: =IF(OR($T109="",$U109=""),"",$U109-$T109) | AI109: =IF(OR($R109="",$U109=""),"",$U109-$R109) | AJ109: =IF(OR($U109="",$AB109=""),"",$AB109-$U109) | AK109: =IF(OR($R109="",$AD109=""),"",$AD109-$R109) | AN109: Migrado (02-2026)
A110: =IF($B110="","",ROW()-3) -> 107 | B110: G.M. AGRUPACION DE COLABORACION. | C110: 30717358909 | D110: FAC | E110: 1-14699 | F110: 46092 | H110: INTERNADO | I110: OSPIF | J110: 30 | K110: 783276.56 | L110: 499023.74 | M110: 0 | N110: =IF($K110="","",$K110-N($L110)-N($M110)) -> 284252.82 | O110: AUDITADA | P110: AUDITADA | V110: 1 de 1 | W110: =IF(OR($F110="",$J110=""),"",$F110+$J110) -> 46122 | AF110: =IF(OR($R110="",$S110=""),"",$S110-$R110) | AG110: =IF(OR($S110="",$T110=""),"",$T110-$S110) | AH110: =IF(OR($T110="",$U110=""),"",$U110-$T110) | AI110: =IF(OR($R110="",$U110=""),"",$U110-$R110) | AJ110: =IF(OR($U110="",$AB110=""),"",$AB110-$U110) | AK110: =IF(OR($R110="",$AD110=""),"",$AD110-$R110) | AN110: Migrado (02-2026)
A111: =IF($B111="","",ROW()-3) -> 108 | B111: GPAL BIOQUIMICA CLINICA S.A.S. | C111: 30716142015 | D111: FAC | E111: 00003-00000011 | F111: 46090 | H111: AMBULATORIO | I111: OSPEVIC | J111: 60 | K111: 192100 | L111: 0 | M111: 0 | N111: =IF($K111="","",$K111-N($L111)-N($M111)) -> 192100 | O111: AUDITADA | P111: AUDITADA | V111: 1 de 1 | W111: =IF(OR($F111="",$J111=""),"",$F111+$J111) -> 46150 | AF111: =IF(OR($R111="",$S111=""),"",$S111-$R111) | AG111: =IF(OR($S111="",$T111=""),"",$T111-$S111) | AH111: =IF(OR($T111="",$U111=""),"",$U111-$T111) | AI111: =IF(OR($R111="",$U111=""),"",$U111-$R111) | AJ111: =IF(OR($U111="",$AB111=""),"",$AB111-$U111) | AK111: =IF(OR($R111="",$AD111=""),"",$AD111-$R111) | AN111: Migrado (02-2026)
A112: =IF($B112="","",ROW()-3) -> 109 | B112: GPAL BIOQUIMICA CLINICA S.A.S. | C112: 30716142015 | D112: FAC | E112: 00003-00000010 | F112: 46088 | H112: AMBULATORIO | I112: OSSURRBAC | J112: 60 | K112: 223975 | L112: 31722 | M112: 0 | N112: =IF($K112="","",$K112-N($L112)-N($M112)) -> 192253 | O112: AUDITADA | P112: AUDITADA | V112: 1 de 1 | W112: =IF(OR($F112="",$J112=""),"",$F112+$J112) -> 46148 | AF112: =IF(OR($R112="",$S112=""),"",$S112-$R112) | AG112: =IF(OR($S112="",$T112=""),"",$T112-$S112) | AH112: =IF(OR($T112="",$U112=""),"",$U112-$T112) | AI112: =IF(OR($R112="",$U112=""),"",$U112-$R112) | AJ112: =IF(OR($U112="",$AB112=""),"",$AB112-$U112) | AK112: =IF(OR($R112="",$AD112=""),"",$AD112-$R112) | AN112: Migrado (02-2026)
A113: =IF($B113="","",ROW()-3) -> 110 | B113: GPAL BIOQUIMICA CLINICA S.A.S. | C113: 30716142015 | D113: FAC | E113: 00003-00000012 | F113: 46091 | H113: AMBULATORIO | I113: OSPLYFC | J113: 60 | K113: 575875 | L113: 86588 | M113: 0 | N113: =IF($K113="","",$K113-N($L113)-N($M113)) -> 489287 | O113: AUDITADA | P113: AUDITADA | V113: 1 de 1 | W113: =IF(OR($F113="",$J113=""),"",$F113+$J113) -> 46151 | AF113: =IF(OR($R113="",$S113=""),"",$S113-$R113) | AG113: =IF(OR($S113="",$T113=""),"",$T113-$S113) | AH113: =IF(OR($T113="",$U113=""),"",$U113-$T113) | AI113: =IF(OR($R113="",$U113=""),"",$U113-$R113) | AJ113: =IF(OR($U113="",$AB113=""),"",$AB113-$U113) | AK113: =IF(OR($R113="",$AD113=""),"",$AD113-$R113) | AN113: Migrado (02-2026)
A114: =IF($B114="","",ROW()-3) -> 111 | B114: GPAL BIOQUIMICA CLINICA S.A.S. | C114: 30716142015 | D114: FAC | E114: 00003-00000013 | F114: 46091 | H114: AMBULATORIO | I114: OSPIF | J114: 60 | K114: 1041683.5 | L114: 11383.5 | M114: 0 | N114: =IF($K114="","",$K114-N($L114)-N($M114)) -> 1030300 | O114: AUDITADA | P114: AUDITADA | V114: 1 de 1 | W114: =IF(OR($F114="",$J114=""),"",$F114+$J114) -> 46151 | AF114: =IF(OR($R114="",$S114=""),"",$S114-$R114) | AG114: =IF(OR($S114="",$T114=""),"",$T114-$S114) | AH114: =IF(OR($T114="",$U114=""),"",$U114-$T114) | AI114: =IF(OR($R114="",$U114=""),"",$U114-$R114) | AJ114: =IF(OR($U114="",$AB114=""),"",$AB114-$U114) | AK114: =IF(OR($R114="",$AD114=""),"",$AD114-$R114) | AN114: Migrado (02-2026)
A115: =IF($B115="","",ROW()-3) -> 112 | B115: GRUPO OPTICO SA | C115: 30709290866 | D115: FAC | E115: 00015-00005034 | F115: 46090 | H115: CAPITADO | I115: OSPIF | J115: 30 | K115: 16128 | L115: 0 | M115: 0 | N115: =IF($K115="","",$K115-N($L115)-N($M115)) -> 16128 | O115: AUDITADA | P115: AUDITADA | V115: 1 de 1 | W115: =IF(OR($F115="",$J115=""),"",$F115+$J115) -> 46120 | AF115: =IF(OR($R115="",$S115=""),"",$S115-$R115) | AG115: =IF(OR($S115="",$T115=""),"",$T115-$S115) | AH115: =IF(OR($T115="",$U115=""),"",$U115-$T115) | AI115: =IF(OR($R115="",$U115=""),"",$U115-$R115) | AJ115: =IF(OR($U115="",$AB115=""),"",$AB115-$U115) | AK115: =IF(OR($R115="",$AD115=""),"",$AD115-$R115) | AN115: Migrado (02-2026)
... A208: =IF($B208="","",ROW()-3) -> 205 | B208: VISOR PRO S.A.S. | C208: 30716413256 | D208: FAC | E208: 00006-00000002 | F208: 46090 | H208: AMBULATORIO | I208: OSPEVIC | J208: 60 | K208: 88500 | L208: 44600 | M208: 0 | N208: =IF($K208="","",$K208-N($L208)-N($M208)) -> 43900 | O208: AUDITADA | P208: AUDITADA | V208: 1 de 1 | W208: =IF(OR($F208="",$J208=""),"",$F208+$J208) -> 46150 | AF208: =IF(OR($R208="",$S208=""),"",$S208-$R208) | AG208: =IF(OR($S208="",$T208=""),"",$T208-$S208) | AH208: =IF(OR($T208="",$U208=""),"",$U208-$T208) | AI208: =IF(OR($R208="",$U208=""),"",$U208-$R208) | AJ208: =IF(OR($U208="",$AB208=""),"",$AB208-$U208) | AK208: =IF(OR($R208="",$AD208=""),"",$AD208-$R208) | AN208: Migrado (02-2026)
A209: =IF($B209="","",ROW()-3) -> 206 | B209: OMICRON | C209: 30712443681 | D209: FAC | E209: 0010-00010333 | F209: 46128 | H209: PROTESIS | I209: OSPEVIC | K209: 2530000 | L209: 0 | M209: 0 | N209: =IF($K209="","",$K209-N($L209)-N($M209)) -> 2530000 | O209: AUDITADA | P209: AUDITADA | V209: 1 de 1 | W209: =IF(OR($F209="",$J209=""),"",$F209+$J209) | AF209: =IF(OR($R209="",$S209=""),"",$S209-$R209) | AG209: =IF(OR($S209="",$T209=""),"",$T209-$S209) | AH209: =IF(OR($T209="",$U209=""),"",$U209-$T209) | AI209: =IF(OR($R209="",$U209=""),"",$U209-$R209) | AJ209: =IF(OR($U209="",$AB209=""),"",$AB209-$U209) | AK209: =IF(OR($R209="",$AD209=""),"",$AD209-$R209) | AN209: Migrado (02-2026)
A210: =IF($B210="","",ROW()-3) -> 207 | B210: ASOCIACION PRESTADORES DE HEMODIALISIS Y | C210: 30644610256 | D210: FAC | E210: 00003-00008345 | F210: 46086 | I210: OSPIF | K210: 7359816 | L210: 0 | M210: 0 | N210: =IF($K210="","",$K210-N($L210)-N($M210)) -> 7359816 | O210: AUDITADA | P210: AUDITADA | V210: 1 de 1 | W210: =IF(OR($F210="",$J210=""),"",$F210+$J210) | AF210: =IF(OR($R210="",$S210=""),"",$S210-$R210) | AG210: =IF(OR($S210="",$T210=""),"",$T210-$S210) | AH210: =IF(OR($T210="",$U210=""),"",$U210-$T210) | AI210: =IF(OR($R210="",$U210=""),"",$U210-$R210) | AJ210: =IF(OR($U210="",$AB210=""),"",$AB210-$U210) | AK210: =IF(OR($R210="",$AD210=""),"",$AD210-$R210) | AN210: Agregada de proyeccion CxP - completar TIPO_PRESTACION y PLAZO
A211: =IF($B211="","",ROW()-3) -> 208 | B211: PROMET S.R.L. | C211: 30708276878 | D211: FAC | E211: 00008-00002032 | F211: 46055 | I211: OSPEVIC | K211: 3994106.2 | L211: 0 | M211: 0 | N211: =IF($K211="","",$K211-N($L211)-N($M211)) -> 3994106.2 | O211: AUDITADA | P211: AUDITADA | V211: 1 de 1 | W211: =IF(OR($F211="",$J211=""),"",$F211+$J211) | AF211: =IF(OR($R211="",$S211=""),"",$S211-$R211) | AG211: =IF(OR($S211="",$T211=""),"",$T211-$S211) | AH211: =IF(OR($T211="",$U211=""),"",$U211-$T211) | AI211: =IF(OR($R211="",$U211=""),"",$U211-$R211) | AJ211: =IF(OR($U211="",$AB211=""),"",$AB211-$U211) | AK211: =IF(OR($R211="",$AD211=""),"",$AD211-$R211) | AN211: Agregada de proyeccion CxP - completar TIPO_PRESTACION y PLAZO
A212: =IF($B212="","",ROW()-3) -> 209 | B212: PROMET S.R.L. | C212: 30708276878 | D212: FAC | E212: 00008-00002040 | F212: 46063 | I212: OSPLYFC | K212: 1333218 | L212: 0 | M212: 0 | N212: =IF($K212="","",$K212-N($L212)-N($M212)) -> 1333218 | O212: AUDITADA | P212: AUDITADA | V212: 1 de 1 | W212: =IF(OR($F212="",$J212=""),"",$F212+$J212) | AF212: =IF(OR($R212="",$S212=""),"",$S212-$R212) | AG212: =IF(OR($S212="",$T212=""),"",$T212-$S212) | AH212: =IF(OR($T212="",$U212=""),"",$U212-$T212) | AI212: =IF(OR($R212="",$U212=""),"",$U212-$R212) | AJ212: =IF(OR($U212="",$AB212=""),"",$AB212-$U212) | AK212: =IF(OR($R212="",$AD212=""),"",$AD212-$R212) | AN212: Agregada de proyeccion CxP - completar TIPO_PRESTACION y PLAZO
A213: =IF($B213="","",ROW()-3) -> 210 | B213: PROMET S.R.L. | C213: 30708276878 | D213: FAC | E213: 00008-00002041 | F213: 46063 | I213: OSSURRBAC | K213: 175477 | L213: 0 | M213: 0 | N213: =IF($K213="","",$K213-N($L213)-N($M213)) -> 175477 | O213: AUDITADA | P213: AUDITADA | V213: 1 de 1 | W213: =IF(OR($F213="",$J213=""),"",$F213+$J213) | AF213: =IF(OR($R213="",$S213=""),"",$S213-$R213) | AG213: =IF(OR($S213="",$T213=""),"",$T213-$S213) | AH213: =IF(OR($T213="",$U213=""),"",$U213-$T213) | AI213: =IF(OR($R213="",$U213=""),"",$U213-$R213) | AJ213: =IF(OR($U213="",$AB213=""),"",$AB213-$U213) | AK213: =IF(OR($R213="",$AD213=""),"",$AD213-$R213) | AN213: Agregada de proyeccion CxP - completar TIPO_PRESTACION y PLAZO
A214: =IF($B214="","",ROW()-3) -> 211 | B214: SOCIEDAD DE BENEFICENCIA HOSPITAL ITALIANO | C214: 30545894528 | D214: FAC | E214: 00024-00000592 | F214: 46142 | I214: OSPEVIC | K214: 3837874 | L214: 0 | M214: 0 | N214: =IF($K214="","",$K214-N($L214)-N($M214)) -> 3837874 | O214: AUDITADA | P214: AUDITADA | V214: 1 de 1 | W214: =IF(OR($F214="",$J214=""),"",$F214+$J214) | AF214: =IF(OR($R214="",$S214=""),"",$S214-$R214) | AG214: =IF(OR($S214="",$T214=""),"",$T214-$S214) | AH214: =IF(OR($T214="",$U214=""),"",$U214-$T214) | AI214: =IF(OR($R214="",$U214=""),"",$U214-$R214) | AJ214: =IF(OR($U214="",$AB214=""),"",$AB214-$U214) | AK214: =IF(OR($R214="",$AD214=""),"",$AD214-$R214) | AN214: Agregada de proyeccion CxP - completar TIPO_PRESTACION y PLAZO
A215: =IF($B215="","",ROW()-3) | N215: =IF($K215="","",$K215-N($L215)-N($M215)) | W215: =IF(OR($F215="",$J215=""),"",$F215+$J215) | AF215: =IF(OR($R215="",$S215=""),"",$S215-$R215) | AG215: =IF(OR($S215="",$T215=""),"",$T215-$S215) | AH215: =IF(OR($T215="",$U215=""),"",$U215-$T215) | AI215: =IF(OR($R215="",$U215=""),"",$U215-$R215) | AJ215: =IF(OR($U215="",$AB215=""),"",$AB215-$U215) | AK215: =IF(OR($R215="",$AD215=""),"",$AD215-$R215)
A216: =IF($B216="","",ROW()-3) | N216: =IF($K216="","",$K216-N($L216)-N($M216)) | W216: =IF(OR($F216="",$J216=""),"",$F216+$J216) | AF216: =IF(OR($R216="",$S216=""),"",$S216-$R216) | AG216: =IF(OR($S216="",$T216=""),"",$T216-$S216) | AH216: =IF(OR($T216="",$U216=""),"",$U216-$T216) | AI216: =IF(OR($R216="",$U216=""),"",$U216-$R216) | AJ216: =IF(OR($U216="",$AB216=""),"",$AB216-$U216) | AK216: =IF(OR($R216="",$AD216=""),"",$AD216-$R216)
A217: =IF($B217="","",ROW()-3) | N217: =IF($K217="","",$K217-N($L217)-N($M217)) | W217: =IF(OR($F217="",$J217=""),"",$F217+$J217) | AF217: =IF(OR($R217="",$S217=""),"",$S217-$R217) | AG217: =IF(OR($S217="",$T217=""),"",$T217-$S217) | AH217: =IF(OR($T217="",$U217=""),"",$U217-$T217) | AI217: =IF(OR($R217="",$U217=""),"",$U217-$R217) | AJ217: =IF(OR($U217="",$AB217=""),"",$AB217-$U217) | AK217: =IF(OR($R217="",$AD217=""),"",$AD217-$R217)
A218: =IF($B218="","",ROW()-3) | N218: =IF($K218="","",$K218-N($L218)-N($M218)) | W218: =IF(OR($F218="",$J218=""),"",$F218+$J218) | AF218: =IF(OR($R218="",$S218=""),"",$S218-$R218) | AG218: =IF(OR($S218="",$T218=""),"",$T218-$S218) | AH218: =IF(OR($T218="",$U218=""),"",$U218-$T218) | AI218: =IF(OR($R218="",$U218=""),"",$U218-$R218) | AJ218: =IF(OR($U218="",$AB218=""),"",$AB218-$U218) | AK218: =IF(OR($R218="",$AD218=""),"",$AD218-$R218)
A219: =IF($B219="","",ROW()-3) | N219: =IF($K219="","",$K219-N($L219)-N($M219)) | W219: =IF(OR($F219="",$J219=""),"",$F219+$J219) | AF219: =IF(OR($R219="",$S219=""),"",$S219-$R219) | AG219: =IF(OR($S219="",$T219=""),"",$T219-$S219) | AH219: =IF(OR($T219="",$U219=""),"",$U219-$T219) | AI219: =IF(OR($R219="",$U219=""),"",$U219-$R219) | AJ219: =IF(OR($U219="",$AB219=""),"",$AB219-$U219) | AK219: =IF(OR($R219="",$AD219=""),"",$AD219-$R219)
A220: =IF($B220="","",ROW()-3) | N220: =IF($K220="","",$K220-N($L220)-N($M220)) | W220: =IF(OR($F220="",$J220=""),"",$F220+$J220) | AF220: =IF(OR($R220="",$S220=""),"",$S220-$R220) | AG220: =IF(OR($S220="",$T220=""),"",$T220-$S220) | AH220: =IF(OR($T220="",$U220=""),"",$U220-$T220) | AI220: =IF(OR($R220="",$U220=""),"",$U220-$R220) | AJ220: =IF(OR($U220="",$AB220=""),"",$AB220-$U220) | AK220: =IF(OR($R220="",$AD220=""),"",$AD220-$R220)
A221: =IF($B221="","",ROW()-3) | N221: =IF($K221="","",$K221-N($L221)-N($M221)) | W221: =IF(OR($F221="",$J221=""),"",$F221+$J221) | AF221: =IF(OR($R221="",$S221=""),"",$S221-$R221) | AG221: =IF(OR($S221="",$T221=""),"",$T221-$S221) | AH221: =IF(OR($T221="",$U221=""),"",$U221-$T221) | AI221: =IF(OR($R221="",$U221=""),"",$U221-$R221) | AJ221: =IF(OR($U221="",$AB221=""),"",$AB221-$U221) | AK221: =IF(OR($R221="",$AD221=""),"",$AD221-$R221)
A222: =IF($B222="","",ROW()-3) | N222: =IF($K222="","",$K222-N($L222)-N($M222)) | W222: =IF(OR($F222="",$J222=""),"",$F222+$J222) | AF222: =IF(OR($R222="",$S222=""),"",$S222-$R222) | AG222: =IF(OR($S222="",$T222=""),"",$T222-$S222) | AH222: =IF(OR($T222="",$U222=""),"",$U222-$T222) | AI222: =IF(OR($R222="",$U222=""),"",$U222-$R222) | AJ222: =IF(OR($U222="",$AB222=""),"",$AB222-$U222) | AK222: =IF(OR($R222="",$AD222=""),"",$AD222-$R222)
A223: =IF($B223="","",ROW()-3) | N223: =IF($K223="","",$K223-N($L223)-N($M223)) | W223: =IF(OR($F223="",$J223=""),"",$F223+$J223) | AF223: =IF(OR($R223="",$S223=""),"",$S223-$R223) | AG223: =IF(OR($S223="",$T223=""),"",$T223-$S223) | AH223: =IF(OR($T223="",$U223=""),"",$U223-$T223) | AI223: =IF(OR($R223="",$U223=""),"",$U223-$R223) | AJ223: =IF(OR($U223="",$AB223=""),"",$AB223-$U223) | AK223: =IF(OR($R223="",$AD223=""),"",$AD223-$R223)
A224: =IF($B224="","",ROW()-3) | N224: =IF($K224="","",$K224-N($L224)-N($M224)) | W224: =IF(OR($F224="",$J224=""),"",$F224+$J224) | AF224: =IF(OR($R224="",$S224=""),"",$S224-$R224) | AG224: =IF(OR($S224="",$T224=""),"",$T224-$S224) | AH224: =IF(OR($T224="",$U224=""),"",$U224-$T224) | AI224: =IF(OR($R224="",$U224=""),"",$U224-$R224) | AJ224: =IF(OR($U224="",$AB224=""),"",$AB224-$U224) | AK224: =IF(OR($R224="",$AD224=""),"",$AD224-$R224)
A225: =IF($B225="","",ROW()-3) | N225: =IF($K225="","",$K225-N($L225)-N($M225)) | W225: =IF(OR($F225="",$J225=""),"",$F225+$J225) | AF225: =IF(OR($R225="",$S225=""),"",$S225-$R225) | AG225: =IF(OR($S225="",$T225=""),"",$T225-$S225) | AH225: =IF(OR($T225="",$U225=""),"",$U225-$T225) | AI225: =IF(OR($R225="",$U225=""),"",$U225-$R225) | AJ225: =IF(OR($U225="",$AB225=""),"",$AB225-$U225) | AK225: =IF(OR($R225="",$AD225=""),"",$AD225-$R225)
A226: =IF($B226="","",ROW()-3) | N226: =IF($K226="","",$K226-N($L226)-N($M226)) | W226: =IF(OR($F226="",$J226=""),"",$F226+$J226) | AF226: =IF(OR($R226="",$S226=""),"",$S226-$R226) | AG226: =IF(OR($S226="",$T226=""),"",$T226-$S226) | AH226: =IF(OR($T226="",$U226=""),"",$U226-$T226) | AI226: =IF(OR($R226="",$U226=""),"",$U226-$R226) | AJ226: =IF(OR($U226="",$AB226=""),"",$AB226-$U226) | AK226: =IF(OR($R226="",$AD226=""),"",$AD226-$R226)
...

Sheet CONFIG
A1: TIPO_COMPROBANTE | B1: TIPO_PRESTACION | C1: OBRA_SOCIAL | D1: ESTADO | E1: ETAPA_AUDITORIA | F1: METODO_PAGO | G1: ESTADO_CHEQUE_BANCO | I1: Hoja de configuracion - listas para validaciones. No borrar.
A2: FAC | B2: AMBULATORIO | C2: OSPEVIC | D2: PENDIENTE | E2: RECIBIDA | F2: CHEQUE | G2: Aceptado
A3: NC | B3: INTERNADO | C3: OSPIF | D3: AUDITADA | E3: EN_AUD_MEDICA | F3: TRANSFERENCIA | G3: Deposito en proceso
A4: ND | B4: CAPITAS | C4: OSPLYFC | D4: PROYECTADA | E4: EN_FACTURISTA | F4: OP | G4: Pagado
B5: CAPITADO | C5: OSPM | D5: EMITIDA | E5: AUDITADA | F5: EFECTIVO | G5: Anulado
B6: TRASLADOS | C6: OSSURRBAC | D6: PAGADA | G6: Rechazado
B7: AJUSTE | C7: AMSURRBAC | G7: Repudiado
B8: AREA PROTEGIDA | C8: UOM
B9: INTERESES | C9: SIN ASIGNACION
B10: PROTESIS
B11: REFACTURACION
B12: OTROS
